Workbook
Name __brm2: #REF!
Name _brm2: #REF!
Name A: #REF!
Name aaaa: #REF!
Name aaaa: #REF!
Name aaaa: #REF!
Name aaaa: #REF!
Name aaaa: #REF!
Name aaaa: #REF!
Name aaaa: #REF!
Name aaaa: #REF!
Name aaaa: #REF!
Name aaaa: #REF!
Name aaaa: #REF!
Name aaaa: #REF!
Name aaaa: #REF!
Name aaaa: #REF!
Name aaaa: #REF!
Name aaaa: #REF!
Name aaaa: #REF!
Name aaaa: #REF!
Name aaaa: #REF!
Name aaaa: #REF!
Name aaaa: #REF!
Name aaaa: #REF!
Name aaaa: #REF!
Name aaaa: #REF!
Name aaaa: #REF!
Name aaaa: #REF!
Name aaaa: #REF!
Name aaaa: #REF!
Name aaaa: #REF!
Name aaaa: #REF!
Name aaaa: #REF!
Name aaaa: #REF!
Name aaaa: #REF!
Name aaaa: #REF!
Name aaaa: #REF!
Name aaaa: #REF!
Name aaaa: #REF!
Name aaaa: #REF!
Name aaaa: #REF!
Name aaaa: #REF!
Name aaaa: #REF!
Name aaaa: #REF!
Name aaaa: #REF!
Name aaaa: #REF!
Name aaaa: #REF!
Name aaaa: #REF!
Name aaaa: #REF!
Name aaaa: #REF!
Name aaaa: #REF!
Name aaaa: #REF!
Name aaaa: #REF!
Name aaaa: #REF!
Name aaaaa: #REF!
Name aaaaa: #REF!
Name aaaaa: #REF!
Name aaaaa: #REF!
Name aaaaa: #REF!

Sheet KO
C11: Koptāme/Summary
C13: Būves nosaukums/Building: Daudzīvokļu ēka / Residental building C2-10
C14: Objekta nosaukums/Object: Dzīvojamās ēkas C2-10 jaunbūve/ Residential building C2-10
C15: Objekta adrese/Object adress: Andrejostas iela 35, Rīga, LV-1045
A21: Nr.p.k./No | B21: Tāmes Nr./No | C21: Objekta nosaukums/Description | D21: Objekta izmaksas euro/Total euro
A23: 1 | B23: 2 | C23: 3 | D23: =C23+1 -> 4
A24: 1 | B24: 0 | C24: Sagatavošanās un būvlaukuma uzturēšanas darbi/Site preparation and maintenance, demolishing | D24: =KS!D21 -> 0
A25: 2 | B25: 1 | C25: Būvdarbi/General construction work (structure and finishings) | D25: =KS!D45 -> 0
A26: 3 | B26: 2 | C26: Santehniskie darbi/Internal engineering systems (HVAC, WSS) | D26: =KS!D60 -> 0
A27: 4 | B27: 3 | C27: Elektromontāžas un vājstrāvu montāžas darbi/Electricity and low current | D27: =KS!D73 -> 0
A28: 5 | C28: Ēkas būvniecības izmaksas/Building construction costs | D28: =D25+D26+D27 -> 0
A29: 6 | B29: 4 | C29: Ārējie inženiertīkli/Territory networks | D29: =KS!D87 -> 0
A30: 7 | B30: 5 | C30: Labiekārtošana un piebraucamie ceļi/Territory, landscaping and roads | D30: =KS!D100 -> 0
A31: 8 | C31: Objekta izmaksas/Total | D31: =D24+D28+D29+D30 -> 0
A32: 9 | C32: Virsizdevumi/Overhead ( %) | D32: =ROUND(D31*8%,2) -> 0
A33: 10 | C33: t. sk. darba aizsardzība ( %) | D33: =ROUND(D32*0.05,2) -> 0
A34: 11 | C34: Peļņa/Profit ( %) | D34: =ROUND(D31*5%,2) -> 0
A35: 12 | C35: Pavisam kopā/Total | D35: =D31+D32+D34 -> 0
C37: Pievienotās vērtības nodoklis/PVN/Value Added Tax/VAT (21,00 %) | D37: =D35*0.21 -> 0

Sheet KS
C2: Kopsavilkuma aprēķins/Summary
C4: Būves nosaukums/Building: Daudzīvokļu ēka / Residental building C2-10
C5: Objekta nosaukums/Object: Dzīvojamās ēkas C2-10 jaunbūve/ Residential building C2-10
C6: Objekta adrese/Object adress: Andrejostas iela 35, Rīga, LV-1045
C9: Par kopējo summu, (euro)/For the total amount, (euro) | D9: =D106 -> 0
C10: Kopējā darbietilpība (c/h)/Total labor volume (w/h) | D10: =H102 -> 0
A15: N.p.k. | B15: Tāmes Nr./Estimate No | C15: Būvdarbu veids vai konstruktīvā elementa nosaukums/Description | D15: Tāmes izmaksas /Total cost | E15: Tai skaitā/Including | H15: Darbietilpība (c/h)/Labor volume (w/h)
E16: darba alga/ salary | F16: būvizstrādājumi/ materials | G16: mehānismi/ mechanisms
A17: 1 | B17: 2 | C17: 3 | D17: =C17+1 -> 4 | E17: =D17+1 -> 5 | F17: =E17+1 -> 6 | G17: =F17+1 -> 7 | H17: =G17+1 -> 8
A19: 1 | B19: 0 | C19: Sagatavošanās un būvlaukuma uzturēšanas darbi/Site preparation and maintenance, demolishing
A20: =A19+1 -> 2 | B20: 0-1 | C20: Būvlaukuma sagatavošanas darbi, pagaidu būves, uzturēšanas darbi/Site preparation and maintenance | D20: =SUM(E20:G20) -> 0 | E20: ='0-1'!M96 -> 0 | F20: ='0-1'!N96 -> 0 | G20: ='0-1'!O96 -> 0 | H20: ='0-1'!L96 -> 0
A21: =A20+1 -> 3 | B21: 0 | C21: Sagatavošanās un būvlaukuma uzturēšanas darbi/Site preparation and maintenance, demolishing | D21: =SUM(D20:D20) -> 0 | E21: =SUM(E20:E20) -> 0 | F21: =SUM(F20:F20) -> 0 | G21: =SUM(G20:G20) -> 0 | H21: =SUM(H20:H20) -> 0
A23: =A21+1 -> 4 | B23: 1 | C23: Būvdarbi/General construction work (structure and finishings)
A24: =A23+1 -> 5 | B24: 1-0 | C24: Zemes darbi/Earthworks | D24: =SUM(E24:G24) -> 0 | E24: ='1-0Z'!M19 -> 0 | F24: ='1-0Z'!N19 -> 0 | G24: ='1-0Z'!O19 -> 0 | H24: ='1-0Z'!L19 -> 0
A25: =A24+1 -> 6 | B25: 1-2 | C25: Pamatu plātne, pamati, režģoģi / Baseplate, foundations | D25: =SUM(E25:G25) -> 0 | E25: ='1-2Pp'!M50 -> 0 | F25: ='1-2Pp'!N50 -> 0 | G25: ='1-2Pp'!O50 -> 0 | H25: ='1-2Pp'!L50 -> 0
A26: =A25+1 -> 7 | B26: 1-3 | C26: Nesošās sienas un kolonnas/ Load-bearing walls, columns | D26: =SUM(E26:G26) -> 0 | E26: ='1-3S'!M85 -> 0 | F26: ='1-3S'!N85 -> 0 | G26: ='1-3S'!O85 -> 0 | H26: ='1-3S'!L85 -> 0
A27: =A26+1 -> 8 | B27: 1-4 | C27: Tērauda konstrukcijas /Steel structures | D27: =SUM(E27:G27) -> 0 | E27: ='1-4T'!M67 -> 0 | F27: ='1-4T'!N67 -> 0 | G27: ='1-4T'!O67 -> 0 | H27: ='1-4T'!L67 -> 0
A28: =A27+1 -> 9 | B28: 1-5 | C28: Pārsegumu, siju montāža / Slabs, beams | D28: =SUM(E28:G28) -> 0 | E28: ='1-5P'!M379 -> 0 | F28: ='1-5P'!N379 -> 0 | G28: ='1-5P'!O379 -> 0 | H28: ='1-5P'!L379 -> 0
A29: =A28+1 -> 10 | B29: 1-6 | C29: Kāpnes, margas / Staircases, railings | D29: =SUM(E29:G29) -> 0 | E29: ='1-6K'!M45 -> 0 | F29: ='1-6K'!N45 -> 0 | G29: ='1-6K'!O45 -> 0 | H29: ='1-6K'!L45 -> 0
A30: =A29+1 -> 11 | B30: 1-7 | C30: Jumta un jumta elementu montāža / Roof and roof elements | D30: =SUM(E30:G30) -> 0 | E30: ='1-7J'!M183 -> 0 | F30: ='1-7J'!N183 -> 0 | G30: ='1-7J'!O183 -> 0 | H30: ='1-7J'!L183 -> 0
A31: =A30+1 -> 12 | B31: 1-8 | C31: Fasādes konstrukcijas un apdare / Facade finishing | D31: =SUM(E31:G31) -> 0 | E31: ='1-8F'!M121 -> 0 | F31: ='1-8F'!N121 -> 0 | G31: ='1-8F'!O121 -> 0 | H31: ='1-8F'!L121 -> 0
A32: =A31+1 -> 13 | B32: 1-9 | C32: Fasādes stiklojums, logi / Facade windows | D32: =SUM(E32:G32) -> 0 | E32: ='1-9L'!M85 -> 0 | F32: ='1-9L'!N85 -> 0 | G32: ='1-9L'!O85 -> 0 | H32: ='1-9L'!L85 -> 0
A33: =A32+1 -> 14 | B33: 1-10 | C33: Grīdu pamatnes / Floor constructions | D33: =SUM(E33:G33) -> 0 | E33: ='1-10Gp'!M181 -> 0 | F33: ='1-10Gp'!N181 -> 0 | G33: ='1-10Gp'!O181 -> 0 | H33: ='1-10Gp'!L181 -> 0
A34: =A33+1 -> 15 | B34: 1-11 | C34: Sienu konstrukcijas, stikla starpsienas / Internal walls, glass walls | D34: =SUM(E34:G34) -> 0 | E34: ='1-11S'!M74 -> 0 | F34: ='1-11S'!N74 -> 0 | G34: ='1-11S'!O74 -> 0 | H34: ='1-11S'!L74 -> 0
A35: =A34+1 -> 16 | B35: 1-12-1 | C35: Grīdu apdares darbi koptelpās / Floor finishing common areas | D35: =SUM(E35:G35) -> 0 | E35: ='1-12-1G'!M26 -> 0 | F35: ='1-12-1G'!N26 -> 0 | G35: ='1-12-1G'!O26 -> 0 | H35: ='1-12-1G'!L26 -> 0
A36: =A35+1 -> 17 | B36: 1-12-2 | C36: Grīdu apdares darbi dzīvokļos/ Floor finishing apartments | D36: =SUM(E36:G36) -> 0 | E36: ='1-12-2G'!M46 -> 0 | F36: ='1-12-2G'!N46 -> 0 | G36: ='1-12-2G'!O46 -> 0 | H36: ='1-12-2G'!L46 -> 0
A37: =A36+1 -> 18 | B37: 1-13-1 | C37: Griestu konstrukcijas / Ceiling constructions | D37: =SUM(E37:G37) -> 0 | E37: ='1-13-1G'!M79 -> 0 | F37: ='1-13-1G'!N79 -> 0 | G37: ='1-13-1G'!O79 -> 0 | H37: ='1-13-1G'!L79 -> 0
A38: =A37+1 -> 19 | B38: 1-13-2 | C38: Griestu apdares darbi koptelpās/ Ceiling finishing common areas | D38: =SUM(E38:G38) -> 0 | E38: ='1-13-2G'!M22 -> 0 | F38: ='1-13-2G'!N22 -> 0 | G38: ='1-13-2G'!O22 -> 0 | H38: ='1-13-2G'!L22 -> 0
A39: =A38+1 -> 20 | B39: 1-13-3 | C39: Griestu apdares darbi dzīvokļos/ Ceiling finishing apartments | D39: =SUM(E39:G39) -> 0 | E39: ='1-13-3G'!M38 -> 0 | F39: ='1-13-3G'!N38 -> 0 | G39: ='1-13-3G'!O38 -> 0 | H39: ='1-13-3G'!L38 -> 0
A40: =A39+1 -> 21 | B40: 1-14-1 | C40: Sienu apdares darbi koptelpās/ Wall finishing common areas | D40: =SUM(E40:G40) -> 0 | E40: ='1-14-1S'!M21 -> 0 | F40: ='1-14-1S'!N21 -> 0 | G40: ='1-14-1S'!O21 -> 0 | H40: ='1-14-1S'!L21 -> 0
A41: =A40+1 -> 22 | B41: 1-14-2 | C41: Sienu apdares darbi dzīvokļos / Wall finishing apartments | D41: =SUM(E41:G41) -> 0 | E41: ='1-14-2S'!M45 -> 0 | F41: ='1-14-2S'!N45 -> 0 | G41: ='1-14-2S'!O45 -> 0 | H41: ='1-14-2S'!L45 -> 0
A42: =A41+1 -> 23 | B42: 1-15 | C42: Durvis, vārti, lūkas / Doors, gates, hatches | D42: =SUM(E42:G42) -> 0 | E42: ='1-15D'!M73 -> 0 | F42: ='1-15D'!N73 -> 0 | G42: ='1-15D'!O73 -> 0 | H42: ='1-15D'!L73 -> 0
A43: =A42+1 -> 24 | B43: 1-16 | C43: Dažādi darbi, lūkas / Different jobs, details | D43: =SUM(E43:G43) -> 0 | E43: ='1-16'!M22 -> 0 | F43: ='1-16'!N22 -> 0 | G43: ='1-16'!O22 -> 0 | H43: ='1-16'!L22 -> 0
A44: =A43+1 -> 25 | B44: 1-17 | C44: Lifti, eskalatori / Elevators, escalators | D44: =SUM(E44:G44) -> 0 | E44: ='1-17'!M17 -> 0 | F44: ='1-17'!N17 -> 0 | G44: ='1-17'!O17 -> 0 | H44: ='1-17'!L17 -> 0
A45: =A44+1 -> 26 | B45: 1 | C45: Būvdarbi/General construction work (structure and finishings) | D45: =SUM(D24:D44) -> 0 | E45: =SUM(E24:E44) -> 0 | F45: =SUM(F24:F44) -> 0 | G45: =SUM(G24:G44) -> 0 | H45: =SUM(H24:H44) -> 0
A47: =A45+1 -> 27 | B47: 2 | C47: Santehniskie darbi/Internal engineering systems (HVAC, WSS)
A48: =A47+1 -> 28 | B48: 2-1 | C48: Siltummehānika / Heat engineering | D48: =SUM(E48:G48) -> 0 | E48: ='2-1'!M197 -> 0 | F48: ='2-1'!N197 -> 0 | G48: ='2-1'!O197 -> 0 | H48: ='2-1'!L197 -> 0
A49: =A48+1 -> 29 | B49: 2-2 | C49: Apkure/Heating | D49: =SUM(E49:G49) -> 0 | E49: ='2-2'!M228 -> 0 | F49: ='2-2'!N228 -> 0 | G49: ='2-2'!O228 -> 0 | H49: ='2-2'!L228 -> 0
A50: =A49+1 -> 30 | B50: 2-3 | C50: Ventilācija/Ventilation | D50: =SUM(E50:G50) -> 0 | E50: ='2-3'!M400 -> 0 | F50: ='2-3'!N400 -> 0 | G50: ='2-3'!O400 -> 0 | H50: ='2-3'!L400 -> 0
A51: =A50+1 -> 31 | B51: 2-4 | C51: Klimata kontroles sistēma / Climate control systems | D51: =SUM(E51:G51) -> 0 | E51: ='2-4'!M153 -> 0 | F51: ='2-4'!N153 -> 0 | G51: ='2-4'!O153 -> 0 | H51: ='2-4'!L153 -> 0
A52: =A51+1 -> 32 | B52: 2-5 | C52: Aukstais, laistīšanas, kapilārais, karstais, cirkulācijas ūdens / Cold, irrigation, capillary, hot, circulating water | D52: =SUM(E52:G52) -> 0 | E52: ='2-5'!M181 -> 0 | F52: ='2-5'!N181 -> 0 | G52: ='2-5'!O181 -> 0 | H52: ='2-5'!L181 -> 0
A53: =A52+1 -> 33 | B53: 2-6 | C53: Sadzīves kanalizācija K1 / Domestic sewerage K1 | D53: =SUM(E53:G53) -> 0 | E53: ='2-6'!M55 -> 0 | F53: ='2-6'!N55 -> 0 | G53: ='2-6'!O55 -> 0 | H53: ='2-6'!L55 -> 0
A54: =A53+1 -> 34 | B54: 2-7 | C54: Lietus kanalizācija ar eļļas piejaukumu K2 / Rain sewerage with oil mixture K2 | D54: =SUM(E54:G54) -> 0 | E54: ='2-7'!M45 -> 0 | F54: ='2-7'!N45 -> 0 | G54: ='2-7'!O45 -> 0 | H54: ='2-7'!L45 -> 0
A55: =A54+1 -> 35 | B55: 2-8 | C55: Lietus kanalizācija (daļēji tīrs ūdens) K3 / Rain sewerage (semi-pure water) K3 | D55: =SUM(E55:G55) -> 0 | E55: ='2-8'!M44 -> 0 | F55: ='2-8'!N44 -> 0 | G55: ='2-8'!O44 -> 0 | H55: ='2-8'!L44 -> 0
A56: =A55+1 -> 36 | B56: 2-9 | C56: Vakuuma lietus notekūdeņu novadīšanas sistēma / vacuum rainwater drainage system | D56: =SUM(E56:G56) -> 0 | E56: ='2-9'!M38 -> 0 | F56: ='2-9'!N38 -> 0 | G56: ='2-9'!O38 -> 0 | H56: ='2-9'!L38 -> 0
A57: =A56+1 -> 37 | B57: 2-10 | C57: Kondensāta kanalizācijas sistēma KK/ Condensate sewerage system KK | D57: =SUM(E57:G57) -> 0 | E57: ='2-10'!M38 -> 0 | F57: ='2-10'!N38 -> 0 | G57: ='2-10'!O38 -> 0 | H57: ='2-10'!L38 -> 0
A58: =A57+1 -> 38 | B58: 2-11 | C58: Santehnikas un aprīkojuma montāža / Sanitary appliances and equipment | D58: =SUM(E58:G58) -> 0 | E58: ='2-11'!M98 -> 0 | F58: ='2-11'!N98 -> 0 | G58: ='2-11'!O98 -> 0 | H58: ='2-11'!L98 -> 0
A59: =A58+1 -> 39 | B59: 2-12 | C59: Iekšējā ugunsdzēsības šļūteņu sistēma / Fixed firefighting Hose system; Internal hydrant system | D59: =SUM(E59:G59) -> 0 | E59: ='2-12'!M76 -> 0 | F59: ='2-12'!N76 -> 0 | G59: ='2-12'!O76 -> 0 | H59: ='2-12'!L76 -> 0
A60: =A59+1 -> 40 | B60: 2 | C60: Santehniskie darbi/Internal engineering systems (HVAC, WSS) | D60: =SUM(D48:D59) -> 0 | E60: =SUM(E48:E59) -> 0 | F60: =SUM(F48:F59) -> 0 | G60: =SUM(G48:G59) -> 0 | H60: =SUM(H48:H59) -> 0
A62: =A60+1 -> 41 | B62: 3 | C62: Elektromontāžas un vājstrāvu montāžas darbi/Electricity and low current
A63: =A62+1 -> 42 | B63: 3-1 | C63: Elektroapgāde (iekšējā)/Electricity (internal) | D63: =SUM(E63:G63) -> 0 | E63: ='3-1'!M379 -> 0 | F63: ='3-1'!N379 -> 0 | G63: ='3-1'!O379 -> 0 | H63: ='3-1'!L379 -> 0
A64: =A63+1 -> 43 | B64: 3-2 | C64: Gaismekļi/Lighting fixtures | D64: =SUM(E64:G64) -> 0 | E64: ='3-2'!M152 -> 0 | F64: ='3-2'!N152 -> 0 | G64: ='3-2'!O152 -> 0 | H64: ='3-2'!L152 -> 0
A65: =A64+1 -> 44 | B65: 3-3 | C65: Zibensaizsardzība un zemējums, potenciālu izlīdzināšana/Lightning protection and earthing system | D65: =SUM(E65:G65) -> 0 | E65: ='3-3'!M58 -> 0 | F65: ='3-3'!N58 -> 0 | G65: ='3-3'!O58 -> 0 | H65: ='3-3'!L58 -> 0
A66: =A65+1 -> 45 | B66: 3-4 | C66: Elektronisko sakaru inženiertīkli / Electronic communication engineering networks | D66: =SUM(E66:G66) -> 0 | E66: ='3-4'!M136 -> 0 | F66: ='3-4'!N136 -> 0 | G66: ='3-4'!O136 -> 0 | H66: ='3-4'!L136 -> 0
A67: =A66+1 -> 46 | B67: 3-5 | C67: Piekļuves kontroles sistēma / Access control system | D67: =SUM(E67:G67) -> 0 | E67: ='3-5'!M79 -> 0 | F67: ='3-5'!N79 -> 0 | G67: ='3-5'!O79 -> 0 | H67: ='3-5'!L79 -> 0
A68: =A67+1 -> 47 | B68: 3-6 | C68: Videonovērošanas sistēma / Video surveillance system | D68: =SUM(E68:G68) -> 0 | E68: ='3-6'!M91 -> 0 | F68: ='3-6'!N91 -> 0 | G68: ='3-6'!O91 -> 0 | H68: ='3-6'!L91 -> 0
A69: =A68+1 -> 48 | B69: 3-7 | C69: Dūmu aizsardzība. Automātikas daļa/Smoke exhaust system electrical part | D69: =SUM(E69:G69) -> 0 | E69: ='3-7'!M33 -> 0 | F69: ='3-7'!N33 -> 0 | G69: ='3-7'!O33 -> 0 | H69: ='3-7'!L33 -> 0
A70: =A69+1 -> 49 | B70: 3-8 | C70: Vadības un automatizācijas sistēmas / Management and automatization systems | D70: =SUM(E70:G70) -> 0 | E70: ='3-8'!M47 -> 0 | F70: ='3-8'!N47 -> 0 | G70: ='3-8'!O47 -> 0 | H70: ='3-8'!L47 -> 0
A71: =A70+1 -> 50 | B71: 3-9 | C71: Ugunsdzēsības automātikas sistēma / Fire automation system | D71: =SUM(E71:G71) -> 0 | E71: ='3-9'!M69 -> 0 | F71: ='3-9'!N69 -> 0 | G71: ='3-9'!O69 -> 0 | H71: ='3-9'!L69 -> 0
A72: =A71+1 -> 51 | B72: 3-10 | C72: Ugunsgrēka atklāšanas un trauksmes signalizācijas sistēma / Automatic fire detection and alarm system | D72: =SUM(E72:G72) -> 0 | E72: ='3-10'!M83 -> 0 | F72: ='3-10'!N83 -> 0 | G72: ='3-10'!O83 -> 0 | H72: ='3-10'!L83 -> 0
A73: =A72+1 -> 52 | B73: 3 | C73: Elektromontāžas un vājstrāvu montāžas darbi/Electricity and low current | D73: =SUM(D63:D72) -> 0 | E73: =SUM(E63:E72) -> 0 | F73: =SUM(F63:F72) -> 0 | G73: =SUM(G63:G72) -> 0 | H73: =SUM(H63:H72) -> 0
A74: =A73+1 -> 53
A75: =A74+1 -> 54 | C75: Ēkas būvniecības izmaksas/Building construction costs | D75: =D60+D45+D73 -> 0 | E75: =E60+E45+E73 -> 0 | F75: =F60+F45+F73 -> 0 | G75: =G60+G45+G73 -> 0 | H75: =H60+H45+H73 -> 0
A77: =A75+1 -> 55 | B77: 4 | C77: Ārējie inženiertīkli/Territory networks
A78: =A77+1 -> 56 | B78: 4-1 | C78: Siltumapgādes ārējie tīkli/ Heating (external) | D78: =SUM(E78:G78) -> 0 | E78: ='4-1'!M88 -> 0 | F78: ='4-1'!N88 -> 0 | G78: ='4-1'!O88 -> 0 | H78: ='4-1'!L88 -> 0
A79: =A78+1 -> 57 | B79: 4-2 | C79: Ūdensapgādes ārējie tīkli /Water supply system (territory) | D79: =SUM(E79:G79) -> 0 | E79: ='4-2'!M33 -> 0 | F79: ='4-2'!N33 -> 0 | G79: ='4-2'!O33 -> 0 | H79: ='4-2'!L33 -> 0
A80: =A79+1 -> 58 | B80: 4-3 | C80: Sadzīves un tauku kanalizācijas sistēma K1 ārējie tīkli / Domestic and fat sewerage system K1 (territory) | D80: =SUM(E80:G80) -> 0 | E80: ='4-3'!M36 -> 0 | F80: ='4-3'!N36 -> 0 | G80: ='4-3'!O36 -> 0 | H80: ='4-3'!L36 -> 0
A81: =A80+1 -> 59 | B81: 4-4 | C81: Lietus kanalizācijas sistēma K2 un K3 / Rainwater drainage system K2 and K3 | D81: =SUM(E81:G81) -> 0 | E81: ='4-4'!M64 -> 0 | F81: ='4-4'!N64 -> 0 | G81: ='4-4'!O64 -> 0 | H81: ='4-4'!L64 -> 0
A82: =A81+1 -> 60 | B82: 4-5 | C82: Ārējā elektroapgāde 10kV, transformatoru apakšstacija / Electricity 10kV (external), transformer substation | D82: =SUM(E82:G82) -> 0 | E82: ='4-5'!M25 -> 0 | F82: ='4-5'!N25 -> 0 | G82: ='4-5'!O25 -> 0 | H82: ='4-5'!L25 -> 0
A83: =A82+1 -> 61 | B83: 4-6 | C83: Elektroapgāde (ārējā) Teritorijas apgaisme / Electricity (external) Lighting of the territory | D83: =SUM(E83:G83) -> 0 | E83: ='4-6'!M70 -> 0 | F83: ='4-6'!N70 -> 0 | G83: ='4-6'!O70 -> 0 | H83: ='4-6'!L70 -> 0
A84: =A83+1 -> 62 | B84: 4-7 | C84: Elektroapgāde (ārējā) Vadības un automatizācijas sistēma / Electricity (external) Management and automatization system | D84: =SUM(E84:G84) -> 0 | E84: ='4-7'!M38 -> 0 | F84: ='4-7'!N38 -> 0 | G84: ='4-7'!O38 -> 0 | H84: ='4-7'!L38 -> 0
A85: =A84+1 -> 63 | B85: 4-8 | C85: Elektroapgāde (ārējā) / Electricity (external) | D85: =SUM(E85:G85) -> 0 | E85: ='4-8'!M62 -> 0 | F85: ='4-8'!N62 -> 0 | G85: ='4-8'!O62 -> 0 | H85: ='4-8'!L62 -> 0
A86: =A85+1 -> 64 | B86: 4-9 | C86: Elektronisko sakaru sistēmas tīkli (ārējie)/ Telecomunication network (external) | D86: =SUM(E86:G86) -> 0 | E86: ='4-9'!M40 -> 0 | F86: ='4-9'!N40 -> 0 | G86: ='4-9'!O40 -> 0 | H86: ='4-9'!L40 -> 0
A87: =A86+1 -> 65 | B87: 4 | C87: Ārējie inženiertīkli/Territory networks | D87: =SUM(D78:D86) -> 0 | E87: =SUM(E78:E86) -> 0 | F87: =SUM(F78:F86) -> 0 | G87: =SUM(G78:G86) -> 0 | H87: =SUM(H78:H86) -> 0
A89: =A87+1 -> 66 | B89: 5 | C89: Labiekārtošana un piebraucamie ceļi/Territory, landscaping and roads
A90: =A89+1 -> 67 | B90: 5-1 | C90: Ceļi un laukumi / Territory part – Road networks | D90: =SUM(E90:G90) -> 0 | E90: ='5-1'!M67 -> 0 | F90: ='5-1'!N67 -> 0 | G90: ='5-1'!O67 -> 0 | H90: ='5-1'!L67 -> 0
A91: =A90+1 -> 68 | B91: 5-2-1 | C91: Teritorijas labiekārtošana- segumi 1.stāvā /Territory -pavings 1st floor | D91: =SUM(E91:G91) -> 0 | E91: ='5-2-1'!M31 -> 0 | F91: ='5-2-1'!N31 -> 0 | G91: ='5-2-1'!O31 -> 0 | H91: ='5-2-1'!L31 -> 0
A92: =A91+1 -> 69 | B92: 5-2-2 | C92: Teritorijas labiekārtošana- segumi 1.stāvā /Territory -pavings 1st floor | D92: =SUM(E92:G92) -> 0 | E92: ='5-2-2'!M60 -> 0 | F92: ='5-2-2'!N60 -> 0 | G92: ='5-2-2'!O60 -> 0 | H92: ='5-2-2'!L60 -> 0
A93: =A92+1 -> 70 | B93: 5-2-3 | C93: Teritorijas labiekārtošana- segumi 1.stāvā /Territory -pavings 1st floor | D93: =SUM(E93:G93) -> 0 | E93: ='5-2-3'!M37 -> 0 | F93: ='5-2-3'!N37 -> 0 | G93: ='5-2-3'!O37 -> 0 | H93: ='5-2-3'!L37 -> 0
A94: =A93+1 -> 71 | B94: 5-3-1 | C94: Labiekārtošana 1.stāvā / Landscaping elements 1st floor | D94: =SUM(E94:G94) -> 0 | E94: ='5-3-1'!M83 -> 0 | F94: ='5-3-1'!N83 -> 0 | G94: ='5-3-1'!O83 -> 0 | H94: ='5-3-1'!L83 -> 0
A95: =A94+1 -> 72 | B95: 5-3-2 | C95: Labiekārtošana 2.stāvā / Landscaping elements 2ndfloor | D95: =SUM(E95:G95) -> 0 | E95: ='5-3-2'!M88 -> 0 | F95: ='5-3-2'!N88 -> 0 | G95: ='5-3-2'!O88 -> 0 | H95: ='5-3-2'!L88 -> 0
A96: =A95+1 -> 73 | B96: 5-3-3 | C96: Labiekārtošana 3.stāvā / Landscaping elements 3rd floor | D96: =SUM(E96:G96) -> 0 | E96: ='5-3-3'!M22 -> 0 | F96: ='5-3-3'!N22 -> 0 | G96: ='5-3-3'!O22 -> 0 | H96: ='5-3-3'!L22 -> 0
A97: =A96+1 -> 74 | B97: 5-4-1 | C97: Apzaļumošana 1.stāvā /Greenery 1st floor | D97: =SUM(E97:G97) -> 0 | E97: ='5-4-1'!M55 -> 0 | F97: ='5-4-1'!N55 -> 0 | G97: ='5-4-1'!O55 -> 0 | H97: ='5-4-1'!L55 -> 0
A98: =A97+1 -> 75 | B98: 5-4-2 | C98: Apzaļumošana 2.stāvā /Greenery 2nd floor | D98: =SUM(E98:G98) -> 0 | E98: ='5-4-2'!M61 -> 0 | F98: ='5-4-2'!N61 -> 0 | G98: ='5-4-2'!O61 -> 0 | H98: ='5-4-2'!L61 -> 0
A99: =A98+1 -> 76 | B99: 5-4-3 | C99: Apzaļumošana 3.stāvā /Greenery 3rd floor | D99: =SUM(E99:G99) -> 0 | E99: ='5-4-3'!M36 -> 0 | F99: ='5-4-3'!N36 -> 0 | G99: ='5-4-3'!O36 -> 0 | H99: ='5-4-3'!L36 -> 0
A100: =A99+1 -> 77 | B100: 5 | C100: Labiekārtošana un piebraucamie ceļi/Territory, landscaping and roads | D100: =SUM(D90:D99) -> 0 | E100: =SUM(E90:E99) -> 0 | F100: =SUM(F90:F99) -> 0 | G100: =SUM(G90:G99) -> 0 | H100: =SUM(H90:H99) -> 0
A102: =A100+1 -> 78 | C102: Kopā/Subtotal | D102: =D100+D87+D75+D21 -> 0 | E102: =E100+E87+E75+E21 -> 0 | F102: =F100+F87+F75+F21 -> 0 | G102: =G100+G87+G75+G21 -> 0 | H102: =H100+H87+H75+H21 -> 0
A103: =A102+1 -> 79 | C103: Virsizdevumi/Overhead ( %) | D103: =ROUND(D102*8%,2) -> 0
A104: =A103+1 -> 80 | C104: t. sk. darba aizsardzība ( %) | D104: =ROUND(D103*0.05,2) -> 0
A105: =A104+1 -> 81 | C105: Peļņa/Profit ( %) | D105: =ROUND(D102*5%,2) -> 0
A106: =A105+1 -> 82 | C106: Pavisam kopā/Total | D106: =D102+D103+D105 -> 0
C108: Floor | D108: Area | E108: eur/m2
C109: Basement | D109: 3020.5
C110: 1st floor | D110: 2074.3
C111: 2nd floor | D111: 2446.3
C112: 3rd floor | D112: 1679
C113: 4th floor | D113: 1644
C114: 5th floor | D114: 1645
C115: 6th floor | D115: 1433.6
D116: =SUM(D109:D115) -> 13942.7 | E116: =D106/D116 -> 0

Sheet A General requirements 
A1: Local estimate Nr. A
A2: General requirements
A4: =[1]KS!C4 -> Būves nosaukums/Building: C2-9
A5: =[1]KS!C5 -> Objekta nosaukums/Object: TEC ēkas pārbūve par atpūtas centru C2-9/TEC building reconstruction into a recreation center C2-9
A6: =[1]KS!C6 -> Objekta adrese/Object adress: Andrejostas iela 21, Rīga, LV-1045
A11: No. | B11: Name of construction work | C11: Unit | D11: Quantity | E11: Unit costs (EUR) | K11: Total costs (EUR)
E12: time rate (c/h) | F12: work rate (euro/h) | G12: Salary | H12: Materials | I12: Mechanisms | J12: Sum | K12: labor (c/h) | L12: Salary | M12: Materials | N12: Mechanisms | O12: Sum
B13: Page No. 1
B14: GENERAL REQUIREMENTS
B15: GENERAL | G15: =E15*F15 -> 0 | J15: =ROUND(SUM(G15:I15),2) -> 0 | K15: =ROUND(D15*E15,2) -> 0 | L15: =ROUND(D15*G15,2) -> 0 | M15: =ROUND(D15*H15,2) -> 0 | N15: =ROUND(D15*I15,2) -> 0 | O15: =ROUND(SUM(L15:N15),2) -> 0
A16: A | B16: Note 1: These General Requirements are applicable to the whole of the Works. Each Clause, Sub-Clause or Item is to be priced individually and the Tenderer shall not enter any lump sum(s) covering more than one, or all Clauses, Sub-Clauses or Items. | C16: item | D16: 1 | G16: =E16*F16 -> 0 | J16: =ROUND(SUM(G16:I16),2) -> 0 | K16: =ROUND(D16*E16,2) -> 0 | L16: =ROUND(D16*G16,2) -> 0 | M16: =ROUND(D16*H16,2) -> 0 | N16: =ROUND(D16*I16,2) -> 0 | O16: =ROUND(SUM(L16:N16),2) -> 0
A17: B | B17: Note 2: Where any Clause, Sub-Clause or Item has not been priced, has been ticked or has been dashed, it shall be deemed that the value of any such Clause, Sub-Clause or Item has been included elsewhere within the Contract Price. | C17: item | D17: 1 | G17: =E17*F17 -> 0 | J17: =ROUND(SUM(G17:I17),2) -> 0 | K17: =ROUND(D17*E17,2) -> 0 | L17: =ROUND(D17*G17,2) -> 0 | M17: =ROUND(D17*H17,2) -> 0 | N17: =ROUND(D17*I17,2) -> 0 | O17: =ROUND(SUM(L17:N17),2) -> 0
A18: C | B18: Note 3: The quantities inserted against items are estimated quantities for the Works for the purpose of Tender evaluation and not to be taken as actual or correct. Any errors in quantities is the Contractor’s risk. | C18: item | D18: 1 | G18: =E18*F18 -> 0 | J18: =ROUND(SUM(G18:I18),2) -> 0 | K18: =ROUND(D18*E18,2) -> 0 | L18: =ROUND(D18*G18,2) -> 0 | M18: =ROUND(D18*H18,2) -> 0 | N18: =ROUND(D18*I18,2) -> 0 | O18: =ROUND(SUM(L18:N18),2) -> 0
A19: D | B19: Note 4: The Lump sum Contract Price is deemed to cover the whole of the works as per Employer's Requirements, Drawings, Specifications, Basis of Design documents, including Schedule of Project Requirements, and whether or not included in the Pricing Schedule . | C19: item | D19: 1 | G19: =E19*F19 -> 0 | J19: =ROUND(SUM(G19:I19),2) -> 0 | K19: =ROUND(D19*E19,2) -> 0 | L19: =ROUND(D19*G19,2) -> 0 | M19: =ROUND(D19*H19,2) -> 0 | N19: =ROUND(D19*I19,2) -> 0 | O19: =ROUND(SUM(L19:N19),2) -> 0
A20: E | B20: Note 5: The unit rates inserted in the Pricing Schedule will be used to value any variations to the Works, whether omissions or additions. | C20: item | D20: 1 | G20: =E20*F20 -> 0 | J20: =ROUND(SUM(G20:I20),2) -> 0 | K20: =ROUND(D20*E20,2) -> 0 | L20: =ROUND(D20*G20,2) -> 0 | M20: =ROUND(D20*H20,2) -> 0 | N20: =ROUND(D20*I20,2) -> 0 | O20: =ROUND(SUM(L20:N20),2) -> 0
A21: F | B21: Note 6: The Tenderer should note that the General Requirements section of the Pricing Schedule shall be administered strictly in accordance with the Conditions of the Contract. Any obligations stated herein, which, in the opinion of the Engineer, are not performed, either in full or in part, shall be the subject of an instruction given by the Engineer in accordance with the Conditions of Contract. The valuation of such variation(s) shall be determined in accordance with the Conditions of Contract. | C21: item | D21: 1 | G21: =E21*F21 -> 0 | J21: =ROUND(SUM(G21:I21),2) -> 0 | K21: =ROUND(D21*E21,2) -> 0 | L21: =ROUND(D21*G21,2) -> 0 | M21: =ROUND(D21*H21,2) -> 0 | N21: =ROUND(D21*I21,2) -> 0 | O21: =ROUND(SUM(L21:N21),2) -> 0
A22: G | B22: Note 7: Fire protection of temporary site office, storage, etc. | C22: item | D22: 1 | G22: =E22*F22 -> 0 | J22: =ROUND(SUM(G22:I22),2) -> 0 | K22: =ROUND(D22*E22,2) -> 0 | L22: =ROUND(D22*G22,2) -> 0 | M22: =ROUND(D22*H22,2) -> 0 | N22: =ROUND(D22*I22,2) -> 0 | O22: =ROUND(SUM(L22:N22),2) -> 0
B24: Page 2 | G24: =E24*F24 -> 0 | J24: =ROUND(SUM(G24:I24),2) -> 0 | K24: =ROUND(D24*E24,2) -> 0 | L24: =ROUND(D24*G24,2) -> 0 | M24: =ROUND(D24*H24,2) -> 0 | N24: =ROUND(D24*I24,2) -> 0 | O24: =ROUND(SUM(L24:N24),2) -> 0
B25: Facilities for the Employer/Engineer Staff | G25: =E25*F25 -> 0 | J25: =ROUND(SUM(G25:I25),2) -> 0 | K25: =ROUND(D25*E25,2) -> 0 | L25: =ROUND(D25*G25,2) -> 0 | M25: =ROUND(D25*H25,2) -> 0 | N25: =ROUND(D25*I25,2) -> 0 | O25: =ROUND(SUM(L25:N25),2) -> 0
A26: A | B26: The Contractor shall provide vehicles for Employer/Engineer's use in accordance with Engineer's requirement including required insurance coverage and comply with all Authorities requirements. Any maintenance, parts and consumables including fuel shall be at the cost of the Contractor during construction and defects liability period. | C26: item | D26: N/A
A27: B | B27: The Contractor shall provide at all times for the duration of the Time for Completion and/or any agreed time extension all chainmen, staff and survey instruments as may be required by the Engineer for monitoring the proper construction and completion of the Works. | C27: item | D27: 1 | G27: =E27*F27 -> 0 | J27: =ROUND(SUM(G27:I27),2) -> 0 | K27: =ROUND(D27*E27,2) -> 0 | L27: =ROUND(D27*G27,2) -> 0 | M27: =ROUND(D27*H27,2) -> 0 | N27: =ROUND(D27*I27,2) -> 0 | O27: =ROUND(SUM(L27:N27),2) -> 0
A28: C | B28: The Contractor shall provide such labour, materials and transport as the Engineer's representative may require to assist him in carrying out tests and checks on materials and workmanship and setting out and measurement of works. | C28: item | D28: N/A
A29: D | B29: The Contractor shall include all the overtime charges for the Engineer's staff that are required to comply with Program of Works all in accordance with the Specification. | C29: item | D29: 1 | G29: =E29*F29 -> 0 | J29: =ROUND(SUM(G29:I29),2) -> 0 | K29: =ROUND(D29*E29,2) -> 0 | L29: =ROUND(D29*G29,2) -> 0 | M29: =ROUND(D29*H29,2) -> 0 | N29: =ROUND(D29*I29,2) -> 0 | O29: =ROUND(SUM(L29:N29),2) -> 0
B30: COMPLETION AND POST COMPLETION REQUIREMENTS | G30: =E30*F30 -> 0 | J30: =ROUND(SUM(G30:I30),2) -> 0 | K30: =ROUND(D30*E30,2) -> 0 | L30: =ROUND(D30*G30,2) -> 0 | M30: =ROUND(D30*H30,2) -> 0 | N30: =ROUND(D30*I30,2) -> 0 | O30: =ROUND(SUM(L30:N30),2) -> 0
B31: Operation and Maintenance Manuals | G31: =E31*F31 -> 0 | J31: =ROUND(SUM(G31:I31),2) -> 0 | K31: =ROUND(D31*E31,2) -> 0 | L31: =ROUND(D31*G31,2) -> 0 | M31: =ROUND(D31*H31,2) -> 0 | N31: =ROUND(D31*I31,2) -> 0 | O31: =ROUND(SUM(L31:N31),2) -> 0
A32: E | B32: The Contractor shall allow for the preparation and submission of Operation and Maintenance Manuals for each machine, equipment or any other item that requires future maintenance in the quantity and manner specified. | C32: item | D32: 1 | G32: =E32*F32 -> 0 | J32: =ROUND(SUM(G32:I32),2) -> 0 | K32: =ROUND(D32*E32,2) -> 0 | L32: =ROUND(D32*G32,2) -> 0 | M32: =ROUND(D32*H32,2) -> 0 | N32: =ROUND(D32*I32,2) -> 0 | O32: =ROUND(SUM(L32:N32),2) -> 0
B33: Hand Over Manuals | G33: =E33*F33 -> 0 | J33: =ROUND(SUM(G33:I33),2) -> 0 | K33: =ROUND(D33*E33,2) -> 0 | L33: =ROUND(D33*G33,2) -> 0 | M33: =ROUND(D33*H33,2) -> 0 | N33: =ROUND(D33*I33,2) -> 0 | O33: =ROUND(SUM(L33:N33),2) -> 0
A34: F | B34: The Contractor shall allow for the preparation and submission of Hand Over Manuals, in accordance with the Specification. | C34: item | D34: 1 | G34: =E34*F34 -> 0 | J34: =ROUND(SUM(G34:I34),2) -> 0 | K34: =ROUND(D34*E34,2) -> 0 | L34: =ROUND(D34*G34,2) -> 0 | M34: =ROUND(D34*H34,2) -> 0 | N34: =ROUND(D34*I34,2) -> 0 | O34: =ROUND(SUM(L34:N34),2) -> 0
B36: Page 3 | G36: =E36*F36 -> 0 | J36: =ROUND(SUM(G36:I36),2) -> 0 | K36: =ROUND(D36*E36,2) -> 0 | L36: =ROUND(D36*G36,2) -> 0 | M36: =ROUND(D36*H36,2) -> 0 | N36: =ROUND(D36*I36,2) -> 0 | O36: =ROUND(SUM(L36:N36),2) -> 0
B37: Warranties | G37: =E37*F37 -> 0 | J37: =ROUND(SUM(G37:I37),2) -> 0 | K37: =ROUND(D37*E37,2) -> 0 | L37: =ROUND(D37*G37,2) -> 0 | M37: =ROUND(D37*H37,2) -> 0 | N37: =ROUND(D37*I37,2) -> 0 | O37: =ROUND(SUM(L37:N37),2) -> 0
A38: A | B38: The Contractor shall allow for the preparation and submission of Warranties for each machine, equipment or any other item as specified within Contract Documents. | C38: item | D38: 1 | G38: =E38*F38 -> 0 | J38: =ROUND(SUM(G38:I38),2) -> 0 | K38: =ROUND(D38*E38,2) -> 0 | L38: =ROUND(D38*G38,2) -> 0 | M38: =ROUND(D38*H38,2) -> 0 | N38: =ROUND(D38*I38,2) -> 0 | O38: =ROUND(SUM(L38:N38),2) -> 0
B39: Assets register | G39: =E39*F39 -> 0 | J39: =ROUND(SUM(G39:I39),2) -> 0 | K39: =ROUND(D39*E39,2) -> 0 | L39: =ROUND(D39*G39,2) -> 0 | M39: =ROUND(D39*H39,2) -> 0 | N39: =ROUND(D39*I39,2) -> 0 | O39: =ROUND(SUM(L39:N39),2) -> 0
A40: B | B40: The Contractor shall allow for the preparation and submission of Assets register for the Completed Works as required under the Contract Documents. | C40: item | D40: 1 | G40: =E40*F40 -> 0 | J40: =ROUND(SUM(G40:I40),2) -> 0 | K40: =ROUND(D40*E40,2) -> 0 | L40: =ROUND(D40*G40,2) -> 0 | M40: =ROUND(D40*H40,2) -> 0 | N40: =ROUND(D40*I40,2) -> 0 | O40: =ROUND(SUM(L40:N40),2) -> 0
B41: As Built Drawings | G41: =E41*F41 -> 0 | J41: =ROUND(SUM(G41:I41),2) -> 0 | K41: =ROUND(D41*E41,2) -> 0 | L41: =ROUND(D41*G41,2) -> 0 | M41: =ROUND(D41*H41,2) -> 0 | N41: =ROUND(D41*I41,2) -> 0 | O41: =ROUND(SUM(L41:N41),2) -> 0
A42: C | B42: The Contractor shall allow for the preparation and submission of As Built Drawings at the times and in the quantity and manner specified or required by the Engineer. | C42: item | D42: 1 | G42: =E42*F42 -> 0 | J42: =ROUND(SUM(G42:I42),2) -> 0 | K42: =ROUND(D42*E42,2) -> 0 | L42: =ROUND(D42*G42,2) -> 0 | M42: =ROUND(D42*H42,2) -> 0 | N42: =ROUND(D42*I42,2) -> 0 | O42: =ROUND(SUM(L42:N42),2) -> 0
B43: Handover | G43: =E43*F43 -> 0 | J43: =ROUND(SUM(G43:I43),2) -> 0 | K43: =ROUND(D43*E43,2) -> 0 | L43: =ROUND(D43*G43,2) -> 0 | M43: =ROUND(D43*H43,2) -> 0 | N43: =ROUND(D43*I43,2) -> 0 | O43: =ROUND(SUM(L43:N43),2) -> 0
A44: D | B44: The Contractor shall allow for the perpetration and submission of any documents required for handover to the Authorities. | C44: item | D44: 1 | G44: =E44*F44 -> 0 | J44: =ROUND(SUM(G44:I44),2) -> 0 | K44: =ROUND(D44*E44,2) -> 0 | L44: =ROUND(D44*G44,2) -> 0 | M44: =ROUND(D44*H44,2) -> 0 | N44: =ROUND(D44*I44,2) -> 0 | O44: =ROUND(SUM(L44:N44),2) -> 0
B46: Page 4 | G46: =E46*F46 -> 0 | J46: =ROUND(SUM(G46:I46),2) -> 0 | K46: =ROUND(D46*E46,2) -> 0 | L46: =ROUND(D46*G46,2) -> 0 | M46: =ROUND(D46*H46,2) -> 0 | N46: =ROUND(D46*I46,2) -> 0 | O46: =ROUND(SUM(L46:N46),2) -> 0
B47: MANAGEMENT AND STAFF | G47: =E47*F47 -> 0 | J47: =ROUND(SUM(G47:I47),2) -> 0 | K47: =ROUND(D47*E47,2) -> 0 | L47: =ROUND(D47*G47,2) -> 0 | M47: =ROUND(D47*H47,2) -> 0 | N47: =ROUND(D47*I47,2) -> 0 | O47: =ROUND(SUM(L47:N47),2) -> 0
B48: The Contractor is to allow in his tender for all site administration and supervision costs including all necessary security arrangements (photographic security pass system, etc.), and the safety of the public and adjoining property and shall be liable for any claims arising from loss or damage suffered. | G48: =E48*F48 -> 0 | J48: =ROUND(SUM(G48:I48),2) -> 0 | K48: =ROUND(D48*E48,2) -> 0 | L48: =ROUND(D48*G48,2) -> 0 | M48: =ROUND(D48*H48,2) -> 0 | N48: =ROUND(D48*I48,2) -> 0 | O48: =ROUND(SUM(L48:N48),2) -> 0
B49: Mobilisation of Management and Staff | C49: item | D49: 1 | G49: =E49*F49 -> 0 | J49: =ROUND(SUM(G49:I49),2) -> 0 | K49: =ROUND(D49*E49,2) -> 0 | L49: =ROUND(D49*G49,2) -> 0 | M49: =ROUND(D49*H49,2) -> 0 | N49: =ROUND(D49*I49,2) -> 0 | O49: =ROUND(SUM(L49:N49),2) -> 0
A50: A | B50: During construction period | C50: item | D50: 1 | G50: =E50*F50 -> 0 | J50: =ROUND(SUM(G50:I50),2) -> 0 | K50: =ROUND(D50*E50,2) -> 0 | L50: =ROUND(D50*G50,2) -> 0 | M50: =ROUND(D50*H50,2) -> 0 | N50: =ROUND(D50*I50,2) -> 0 | O50: =ROUND(SUM(L50:N50),2) -> 0
A51: B | B51: During defects liability period | C51: item | D51: 1 | G51: =E51*F51 -> 0 | J51: =ROUND(SUM(G51:I51),2) -> 0 | K51: =ROUND(D51*E51,2) -> 0 | L51: =ROUND(D51*G51,2) -> 0 | M51: =ROUND(D51*H51,2) -> 0 | N51: =ROUND(D51*I51,2) -> 0 | O51: =ROUND(SUM(L51:N51),2) -> 0
A52: C | B52: Inclusion is to be made for all necessary security and watchmen, all lighting required for safeguarding the works and plant and for making good and reinstating after any damage or theft. | C52: item | D52: 1 | G52: =E52*F52 -> 0 | J52: =ROUND(SUM(G52:I52),2) -> 0 | K52: =ROUND(D52*E52,2) -> 0 | L52: =ROUND(D52*G52,2) -> 0 | M52: =ROUND(D52*H52,2) -> 0 | N52: =ROUND(D52*I52,2) -> 0 | O52: =ROUND(SUM(L52:N52),2) -> 0
A53: D | B53: Contractor to allow for containment of the existing animals and the necessary coordination with the local authorities to execute the scope of works without compromising the existing number of animals on site, as required. | C53: item | D53: 1 | G53: =E53*F53 -> 0 | J53: =ROUND(SUM(G53:I53),2) -> 0 | K53: =ROUND(D53*E53,2) -> 0 | L53: =ROUND(D53*G53,2) -> 0 | M53: =ROUND(D53*H53,2) -> 0 | N53: =ROUND(D53*I53,2) -> 0 | O53: =ROUND(SUM(L53:N53),2) -> 0
B54: Transport of Work Force | G54: =E54*F54 -> 0 | J54: =ROUND(SUM(G54:I54),2) -> 0 | K54: =ROUND(D54*E54,2) -> 0 | L54: =ROUND(D54*G54,2) -> 0 | M54: =ROUND(D54*H54,2) -> 0 | N54: =ROUND(D54*I54,2) -> 0 | O54: =ROUND(SUM(L54:N54),2) -> 0
A55: E | B55: The Contractor shall make all necessary arrangements for the transport of his own, and his subcontractor's employees for the duration of the Works | C55: item | D55: 1 | G55: =E55*F55 -> 0 | J55: =ROUND(SUM(G55:I55),2) -> 0 | K55: =ROUND(D55*E55,2) -> 0 | L55: =ROUND(D55*G55,2) -> 0 | M55: =ROUND(D55*H55,2) -> 0 | N55: =ROUND(D55*I55,2) -> 0 | O55: =ROUND(SUM(L55:N55),2) -> 0
G56: =E56*F56 -> 0 | J56: =ROUND(SUM(G56:I56),2) -> 0 | K56: =ROUND(D56*E56,2) -> 0 | L56: =ROUND(D56*G56,2) -> 0 | M56: =ROUND(D56*H56,2) -> 0 | N56: =ROUND(D56*I56,2) -> 0 | O56: =ROUND(SUM(L56:N56),2) -> 0
B57: Page 5 | G57: =E57*F57 -> 0 | J57: =ROUND(SUM(G57:I57),2) -> 0 | K57: =ROUND(D57*E57,2) -> 0 | L57: =ROUND(D57*G57,2) -> 0 | M57: =ROUND(D57*H57,2) -> 0 | N57: =ROUND(D57*I57,2) -> 0 | O57: =ROUND(SUM(L57:N57),2) -> 0
B58: SITE ESTABLISHMENT | G58: =E58*F58 -> 0 | J58: =ROUND(SUM(G58:I58),2) -> 0 | K58: =ROUND(D58*E58,2) -> 0 | L58: =ROUND(D58*G58,2) -> 0 | M58: =ROUND(D58*H58,2) -> 0 | N58: =ROUND(D58*I58,2) -> 0 | O58: =ROUND(SUM(L58:N58),2) -> 0
B59: Offices and Facilities for the Contractor | G59: =E59*F59 -> 0 | J59: =ROUND(SUM(G59:I59),2) -> 0 | K59: =ROUND(D59*E59,2) -> 0 | L59: =ROUND(D59*G59,2) -> 0 | M59: =ROUND(D59*H59,2) -> 0 | N59: =ROUND(D59*I59,2) -> 0 | O59: =ROUND(SUM(L59:N59),2) -> 0
B60: Site offices for the use of the staff of the Contractor, and all his Sub-Contractors are to be provided by the Contractor, along with adequate office furniture, computers, photocopier, etc. all in accordance with the Authorities requirements and approved by Employer and Engineer. | G60: =E60*F60 -> 0 | J60: =ROUND(SUM(G60:I60),2) -> 0 | K60: =ROUND(D60*E60,2) -> 0 | L60: =ROUND(D60*G60,2) -> 0 | M60: =ROUND(D60*H60,2) -> 0 | N60: =ROUND(D60*I60,2) -> 0 | O60: =ROUND(SUM(L60:N60),2) -> 0
B61: The Contractor shall be responsible to pay all electricity, water, drinking water and Etisalat charges for Fixed telephone and internet charges for the duration of the construction period and the defects notification period. | G61: =E61*F61 -> 0 | J61: =ROUND(SUM(G61:I61),2) -> 0 | K61: =ROUND(D61*E61,2) -> 0 | L61: =ROUND(D61*G61,2) -> 0 | M61: =ROUND(D61*H61,2) -> 0 | N61: =ROUND(D61*I61,2) -> 0 | O61: =ROUND(SUM(L61:N61),2) -> 0
A62: A | B62: Provision of site offices all in accordance with the Specification and Engineers Instructions. | C62: item | D62: see 0-1
B63: Maintenance of the offices / office equipment for the Staff of the Contractor, and all his Sub-Contractors and pay electricity, water, drinking water, removal of the sewage/waste, and Etisalat charges (Fixed telephone and internet charges) including necessary manpower: | G63: =E63*F63 -> 0 | J63: =ROUND(SUM(G63:I63),2) -> 0 | K63: =ROUND(D63*E63,2) -> 0 | L63: =ROUND(D63*G63,2) -> 0 | M63: =ROUND(D63*H63,2) -> 0 | N63: =ROUND(D63*I63,2) -> 0 | O63: =ROUND(SUM(L63:N63),2) -> 0
A64: B | B64: During construction period | C64: item | D64: 1 | G64: =E64*F64 -> 0 | J64: =ROUND(SUM(G64:I64),2) -> 0 | K64: =ROUND(D64*E64,2) -> 0 | L64: =ROUND(D64*G64,2) -> 0 | M64: =ROUND(D64*H64,2) -> 0 | N64: =ROUND(D64*I64,2) -> 0 | O64: =ROUND(SUM(L64:N64),2) -> 0
A65: C | B65: During defects liability period | C65: item | D65: 1 | G65: =E65*F65 -> 0 | J65: =ROUND(SUM(G65:I65),2) -> 0 | K65: =ROUND(D65*E65,2) -> 0 | L65: =ROUND(D65*G65,2) -> 0 | M65: =ROUND(D65*H65,2) -> 0 | N65: =ROUND(D65*I65,2) -> 0 | O65: =ROUND(SUM(L65:N65),2) -> 0
B66: Provide all office consumables for use within the site offices, as required: | G66: =E66*F66 -> 0 | J66: =ROUND(SUM(G66:I66),2) -> 0 | K66: =ROUND(D66*E66,2) -> 0 | L66: =ROUND(D66*G66,2) -> 0 | M66: =ROUND(D66*H66,2) -> 0 | N66: =ROUND(D66*I66,2) -> 0 | O66: =ROUND(SUM(L66:N66),2) -> 0
A67: D | B67: During construction period | C67: item | D67: 1 | G67: =E67*F67 -> 0 | J67: =ROUND(SUM(G67:I67),2) -> 0 | K67: =ROUND(D67*E67,2) -> 0 | L67: =ROUND(D67*G67,2) -> 0 | M67: =ROUND(D67*H67,2) -> 0 | N67: =ROUND(D67*I67,2) -> 0 | O67: =ROUND(SUM(L67:N67),2) -> 0
A68: E | B68: During defects liability period | C68: item | D68: 1 | G68: =E68*F68 -> 0 | J68: =ROUND(SUM(G68:I68),2) -> 0 | K68: =ROUND(D68*E68,2) -> 0 | L68: =ROUND(D68*G68,2) -> 0 | M68: =ROUND(D68*H68,2) -> 0 | N68: =ROUND(D68*I68,2) -> 0 | O68: =ROUND(SUM(L68:N68),2) -> 0
A69: F | B69: Weatherproof lock-up sheds, workshops and stores for the storage and protection of materials, tools and plant, all in accordance with the Specification and Authorities requirements. | C69: item | D69: 1 | G69: =E69*F69 -> 0 | J69: =ROUND(SUM(G69:I69),2) -> 0 | K69: =ROUND(D69*E69,2) -> 0 | L69: =ROUND(D69*G69,2) -> 0 | M69: =ROUND(D69*H69,2) -> 0 | N69: =ROUND(D69*I69,2) -> 0 | O69: =ROUND(SUM(L69:N69),2) -> 0
A70: G | B70: The Contractor is to remove the site office and the related facilities from the site upon completion of the Works (Demobilization). | C70: item | D70: 1 | G70: =E70*F70 -> 0 | J70: =ROUND(SUM(G70:I70),2) -> 0 | K70: =ROUND(D70*E70,2) -> 0 | L70: =ROUND(D70*G70,2) -> 0 | M70: =ROUND(D70*H70,2) -> 0 | N70: =ROUND(D70*I70,2) -> 0 | O70: =ROUND(SUM(L70:N70),2) -> 0
A71: H | B71: Allow for, within the Contractor offices, a working desks for the Engineer and Supervision teams (4 people) | C71: item | D71: 1 | G71: =E71*F71 -> 0 | J71: =ROUND(SUM(G71:I71),2) -> 0 | K71: =ROUND(D71*E71,2) -> 0 | L71: =ROUND(D71*G71,2) -> 0 | M71: =ROUND(D71*H71,2) -> 0 | N71: =ROUND(D71*I71,2) -> 0 | O71: =ROUND(SUM(L71:N71),2) -> 0
B72: Waste Management | G72: =E72*F72 -> 0 | J72: =ROUND(SUM(G72:I72),2) -> 0 | K72: =ROUND(D72*E72,2) -> 0 | L72: =ROUND(D72*G72,2) -> 0 | M72: =ROUND(D72*H72,2) -> 0 | N72: =ROUND(D72*I72,2) -> 0 | O72: =ROUND(SUM(L72:N72),2) -> 0
B73: The Contractor shall allow for the waste management and removal from site, in accordance with the Specification/requirements. | G73: =E73*F73 -> 0 | J73: =ROUND(SUM(G73:I73),2) -> 0 | K73: =ROUND(D73*E73,2) -> 0 | L73: =ROUND(D73*G73,2) -> 0 | M73: =ROUND(D73*H73,2) -> 0 | N73: =ROUND(D73*I73,2) -> 0 | O73: =ROUND(SUM(L73:N73),2) -> 0
A74: J | B74: During construction period | C74: item | D74: 1 | G74: =E74*F74 -> 0 | J74: =ROUND(SUM(G74:I74),2) -> 0 | K74: =ROUND(D74*E74,2) -> 0 | L74: =ROUND(D74*G74,2) -> 0 | M74: =ROUND(D74*H74,2) -> 0 | N74: =ROUND(D74*I74,2) -> 0 | O74: =ROUND(SUM(L74:N74),2) -> 0
A75: K | B75: During defects liability period | C75: item | D75: 1 | G75: =E75*F75 -> 0 | J75: =ROUND(SUM(G75:I75),2) -> 0 | K75: =ROUND(D75*E75,2) -> 0 | L75: =ROUND(D75*G75,2) -> 0 | M75: =ROUND(D75*H75,2) -> 0 | N75: =ROUND(D75*I75,2) -> 0 | O75: =ROUND(SUM(L75:N75),2) -> 0
G76: =E76*F76 -> 0 | J76: =ROUND(SUM(G76:I76),2) -> 0 | K76: =ROUND(D76*E76,2) -> 0 | L76: =ROUND(D76*G76,2) -> 0 | M76: =ROUND(D76*H76,2) -> 0 | N76: =ROUND(D76*I76,2) -> 0 | O76: =ROUND(SUM(L76:N76),2) -> 0
B77: Page 6 | G77: =E77*F77 -> 0 | J77: =ROUND(SUM(G77:I77),2) -> 0 | K77: =ROUND(D77*E77,2) -> 0 | L77: =ROUND(D77*G77,2) -> 0 | M77: =ROUND(D77*H77,2) -> 0 | N77: =ROUND(D77*I77,2) -> 0 | O77: =ROUND(SUM(L77:N77),2) -> 0
A78: A | B78: All accommodation required for welfare facilities including adequate shelter from inclement weather, accommodation for the storage and drying of clothes, taking of meals and sanitary and washing facilities for all people employed on the site, first aid facilities, fire fighting equipment and drinking water facilities, including all necessary service connections, all in accordance with the Specification and Schedule of Project Requirements, and the laws and regulations of relevant UAE authorities and compliance with ESTIDAMA requirements for liveable conditions. | C78: item | D78: 1 | G78: =E78*F78 -> 0 | J78: =ROUND(SUM(G78:I78),2) -> 0 | K78: =ROUND(D78*E78,2) -> 0 | L78: =ROUND(D78*G78,2) -> 0 | M78: =ROUND(D78*H78,2) -> 0 | N78: =ROUND(D78*I78,2) -> 0 | O78: =ROUND(SUM(L78:N78),2) -> 0
B79: Testing of Materials | G79: =E79*F79 -> 0 | J79: =ROUND(SUM(G79:I79),2) -> 0 | K79: =ROUND(D79*E79,2) -> 0 | L79: =ROUND(D79*G79,2) -> 0 | M79: =ROUND(D79*H79,2) -> 0 | N79: =ROUND(D79*I79,2) -> 0 | O79: =ROUND(SUM(L79:N79),2) -> 0
A80: B | B80: The Contractor is to provide, on site laboratories for all testing requirements fully equipped in accordance with the Authorities requirements and Specification and Engineers Instructions (Establishment Charges), as required. | C80: item | D80: 1 | G80: =E80*F80 -> 0 | J80: =ROUND(SUM(G80:I80),2) -> 0 | K80: =ROUND(D80*E80,2) -> 0 | L80: =ROUND(D80*G80,2) -> 0 | M80: =ROUND(D80*H80,2) -> 0 | N80: =ROUND(D80*I80,2) -> 0 | O80: =ROUND(SUM(L80:N80),2) -> 0
A81: C | B81: Maintenance of the Site Laboratories, including all consumables as required. | C81: item | D81: 1 | G81: =E81*F81 -> 0 | J81: =ROUND(SUM(G81:I81),2) -> 0 | K81: =ROUND(D81*E81,2) -> 0 | L81: =ROUND(D81*G81,2) -> 0 | M81: =ROUND(D81*H81,2) -> 0 | N81: =ROUND(D81*I81,2) -> 0 | O81: =ROUND(SUM(L81:N81),2) -> 0
A82: D | B82: The Contractor is to remove the site laboratories and the related facilities from the site upon completion of the Works (Demobilization). | C82: item | D82: 1 | G82: =E82*F82 -> 0 | J82: =ROUND(SUM(G82:I82),2) -> 0 | K82: =ROUND(D82*E82,2) -> 0 | L82: =ROUND(D82*G82,2) -> 0 | M82: =ROUND(D82*H82,2) -> 0 | N82: =ROUND(D82*I82,2) -> 0 | O82: =ROUND(SUM(L82:N82),2) -> 0
A83: E | B83: The Contractor shall also allow for all requirements, obligations, etc., with regard to all tests that are to be carried out by an approved independent Latvian Municipality accredited laboratory. | C83: item | D83: 1 | G83: =E83*F83 -> 0 | J83: =ROUND(SUM(G83:I83),2) -> 0 | K83: =ROUND(D83*E83,2) -> 0 | L83: =ROUND(D83*G83,2) -> 0 | M83: =ROUND(D83*H83,2) -> 0 | N83: =ROUND(D83*I83,2) -> 0 | O83: =ROUND(SUM(L83:N83),2) -> 0
B84: Testing of the Works | G84: =E84*F84 -> 0 | J84: =ROUND(SUM(G84:I84),2) -> 0 | K84: =ROUND(D84*E84,2) -> 0 | L84: =ROUND(D84*G84,2) -> 0 | M84: =ROUND(D84*H84,2) -> 0 | N84: =ROUND(D84*I84,2) -> 0 | O84: =ROUND(SUM(L84:N84),2) -> 0
A85: F | B85: Allow for testing and commissioning of the Works in accordance with the requirements of relevant Authorities, Specifications and Schedule of Project Requirements. | C85: item | D85: 1 | G85: =E85*F85 -> 0 | J85: =ROUND(SUM(G85:I85),2) -> 0 | K85: =ROUND(D85*E85,2) -> 0 | L85: =ROUND(D85*G85,2) -> 0 | M85: =ROUND(D85*H85,2) -> 0 | N85: =ROUND(D85*I85,2) -> 0 | O85: =ROUND(SUM(L85:N85),2) -> 0
B86: DESIGN & ENGINEERING of the Works | G86: =E86*F86 -> 0 | J86: =ROUND(SUM(G86:I86),2) -> 0 | K86: =ROUND(D86*E86,2) -> 0 | L86: =ROUND(D86*G86,2) -> 0 | M86: =ROUND(D86*H86,2) -> 0 | N86: =ROUND(D86*I86,2) -> 0 | O86: =ROUND(SUM(L86:N86),2) -> 0
A87: G | B87: Allow for DESIGN & ENGINEERING of the Works in accordance with the Employer's requirements, requirements of relevant Authorities, Specifications and Schedule of Project Requirements. | C87: item | D87: 1 | G87: =E87*F87 -> 0 | J87: =ROUND(SUM(G87:I87),2) -> 0 | K87: =ROUND(D87*E87,2) -> 0 | L87: =ROUND(D87*G87,2) -> 0 | M87: =ROUND(D87*H87,2) -> 0 | N87: =ROUND(D87*I87,2) -> 0 | O87: =ROUND(SUM(L87:N87),2) -> 0
G88: =E88*F88 -> 0 | J88: =ROUND(SUM(G88:I88),2) -> 0 | K88: =ROUND(D88*E88,2) -> 0 | L88: =ROUND(D88*G88,2) -> 0 | M88: =ROUND(D88*H88,2) -> 0 | N88: =ROUND(D88*I88,2) -> 0 | O88: =ROUND(SUM(L88:N88),2) -> 0
B89: Page 7 | G89: =E89*F89 -> 0 | J89: =ROUND(SUM(G89:I89),2) -> 0 | K89: =ROUND(D89*E89,2) -> 0 | L89: =ROUND(D89*G89,2) -> 0 | M89: =ROUND(D89*H89,2) -> 0 | N89: =ROUND(D89*I89,2) -> 0 | O89: =ROUND(SUM(L89:N89),2) -> 0
B90: TEMPORARY SERVICES | G90: =E90*F90 -> 0 | J90: =ROUND(SUM(G90:I90),2) -> 0 | K90: =ROUND(D90*E90,2) -> 0 | L90: =ROUND(D90*G90,2) -> 0 | M90: =ROUND(D90*H90,2) -> 0 | N90: =ROUND(D90*I90,2) -> 0 | O90: =ROUND(SUM(L90:N90),2) -> 0
B91: Water and Electricity | G91: =E91*F91 -> 0 | J91: =ROUND(SUM(G91:I91),2) -> 0 | K91: =ROUND(D91*E91,2) -> 0 | L91: =ROUND(D91*G91,2) -> 0 | M91: =ROUND(D91*H91,2) -> 0 | N91: =ROUND(D91*I91,2) -> 0 | O91: =ROUND(SUM(L91:N91),2) -> 0
A92: A | B92: The Contractor shall provide and maintain water, electricity and power required for the works including that required by the sub contractors. Pay all charges and bear all costs for the necessary temporary installation including pipe work, pumps, water tankers, storage tanks, generating equipment, etc., and remove on completion and make good all work disturbed (during the construction period). | C92: item | D92: 1 | G92: =E92*F92 -> 0 | J92: =ROUND(SUM(G92:I92),2) -> 0 | K92: =ROUND(D92*E92,2) -> 0 | L92: =ROUND(D92*G92,2) -> 0 | M92: =ROUND(D92*H92,2) -> 0 | N92: =ROUND(D92*I92,2) -> 0 | O92: =ROUND(SUM(L92:N92),2) -> 0
B93: All utility usage or consumption charges will be for the Contractor's account and allowance for all utility connection and usage charges shall therefore be deemed to be included in the Contract Price. | G93: =E93*F93 -> 0 | J93: =ROUND(SUM(G93:I93),2) -> 0 | K93: =ROUND(D93*E93,2) -> 0 | L93: =ROUND(D93*G93,2) -> 0 | M93: =ROUND(D93*H93,2) -> 0 | N93: =ROUND(D93*I93,2) -> 0 | O93: =ROUND(SUM(L93:N93),2) -> 0
A94: B | B94: During construction period. | C94: item | D94: 1 | G94: =E94*F94 -> 0 | J94: =ROUND(SUM(G94:I94),2) -> 0 | K94: =ROUND(D94*E94,2) -> 0 | L94: =ROUND(D94*G94,2) -> 0 | M94: =ROUND(D94*H94,2) -> 0 | N94: =ROUND(D94*I94,2) -> 0 | O94: =ROUND(SUM(L94:N94),2) -> 0
A95: C | B95: During defects liability period | C95: item | D95: 1 | G95: =E95*F95 -> 0 | J95: =ROUND(SUM(G95:I95),2) -> 0 | K95: =ROUND(D95*E95,2) -> 0 | L95: =ROUND(D95*G95,2) -> 0 | M95: =ROUND(D95*H95,2) -> 0 | N95: =ROUND(D95*I95,2) -> 0 | O95: =ROUND(SUM(L95:N95),2) -> 0
A96: D | B96: All temporary utilities, including water, electricity, etc., required for executing, testing and commissioning the Works shall be for the Contractor's account. | C96: item | D96: 1 | G96: =E96*F96 -> 0 | J96: =ROUND(SUM(G96:I96),2) -> 0 | K96: =ROUND(D96*E96,2) -> 0 | L96: =ROUND(D96*G96,2) -> 0 | M96: =ROUND(D96*H96,2) -> 0 | N96: =ROUND(D96*I96,2) -> 0 | O96: =ROUND(SUM(L96:N96),2) -> 0
A97: E | B97: The Contractor shall allow for all irrigation services and equipment which are to be demolished or which encroach upon the site of the new Works to be properly terminated, diverted or relocated as necessary. The Contractor shall include for liaison with the appropriate statutory authorities and compliance with their requirements and payments of any duties, charges etc., arising therefrom. | C97: item | D97: 1 | G97: =E97*F97 -> 0 | J97: =ROUND(SUM(G97:I97),2) -> 0 | K97: =ROUND(D97*E97,2) -> 0 | L97: =ROUND(D97*G97,2) -> 0 | M97: =ROUND(D97*H97,2) -> 0 | N97: =ROUND(D97*I97,2) -> 0 | O97: =ROUND(SUM(L97:N97),2) -> 0
B98: SITE SERVICES | G98: =E98*F98 -> 0 | J98: =ROUND(SUM(G98:I98),2) -> 0 | K98: =ROUND(D98*E98,2) -> 0 | L98: =ROUND(D98*G98,2) -> 0 | M98: =ROUND(D98*H98,2) -> 0 | N98: =ROUND(D98*I98,2) -> 0 | O98: =ROUND(SUM(L98:N98),2) -> 0
B99: Existing Site Services | G99: =E99*F99 -> 0 | J99: =ROUND(SUM(G99:I99),2) -> 0 | K99: =ROUND(D99*E99,2) -> 0 | L99: =ROUND(D99*G99,2) -> 0 | M99: =ROUND(D99*H99,2) -> 0 | N99: =ROUND(D99*I99,2) -> 0 | O99: =ROUND(SUM(L99:N99),2) -> 0
A100: F | B100: The Contractor shall allow for all electricity, water, drainage and telephone services, buildings, structures and equipment which are to be protected for the entire duration of the works. The Contractor shall include for liaison with the appropriate statutory authorities and compliance with their requirements and payments of any duties, charges etc., arising therefrom. | C100: item | D100: 1 | G100: =E100*F100 -> 0 | J100: =ROUND(SUM(G100:I100),2) -> 0 | K100: =ROUND(D100*E100,2) -> 0 | L100: =ROUND(D100*G100,2) -> 0 | M100: =ROUND(D100*H100,2) -> 0 | N100: =ROUND(D100*I100,2) -> 0 | O100: =ROUND(SUM(L100:N100),2) -> 0
A101: G | B101: The Contractor shall allow for all electricity, water, drainage and telephone services, buildings, structures and equipment which are to be demolished or which encroach upon the site of the new Works to be properly terminated, diverted or relocated as necessary, as required. The Contractor shall include for liaison with the appropriate statutory authorities and compliance with their requirements and payments of any duties, charges etc., arising therefrom. | C101: item | D101: 1 | G101: =E101*F101 -> 0 | J101: =ROUND(SUM(G101:I101),2) -> 0 | K101: =ROUND(D101*E101,2) -> 0 | L101: =ROUND(D101*G101,2) -> 0 | M101: =ROUND(D101*H101,2) -> 0 | N101: =ROUND(D101*I101,2) -> 0 | O101: =ROUND(SUM(L101:N101),2) -> 0
G102: =E102*F102 -> 0 | J102: =ROUND(SUM(G102:I102),2) -> 0 | K102: =ROUND(D102*E102,2) -> 0 | L102: =ROUND(D102*G102,2) -> 0 | M102: =ROUND(D102*H102,2) -> 0 | N102: =ROUND(D102*I102,2) -> 0 | O102: =ROUND(SUM(L102:N102),2) -> 0
B103: Page 8 | G103: =E103*F103 -> 0 | J103: =ROUND(SUM(G103:I103),2) -> 0 | K103: =ROUND(D103*E103,2) -> 0 | L103: =ROUND(D103*G103,2) -> 0 | M103: =ROUND(D103*H103,2) -> 0 | N103: =ROUND(D103*I103,2) -> 0 | O103: =ROUND(SUM(L103:N103),2) -> 0
B104: SAFETY AND ENVIRONMENTAL PROTECTION | G104: =E104*F104 -> 0 | J104: =ROUND(SUM(G104:I104),2) -> 0 | K104: =ROUND(D104*E104,2) -> 0 | L104: =ROUND(D104*G104,2) -> 0 | M104: =ROUND(D104*H104,2) -> 0 | N104: =ROUND(D104*I104,2) -> 0 | O104: =ROUND(SUM(L104:N104),2) -> 0
B105: Construction Environment Management Plan | G105: =E105*F105 -> 0 | J105: =ROUND(SUM(G105:I105),2) -> 0 | K105: =ROUND(D105*E105,2) -> 0 | L105: =ROUND(D105*G105,2) -> 0 | M105: =ROUND(D105*H105,2) -> 0 | N105: =ROUND(D105*I105,2) -> 0 | O105: =ROUND(SUM(L105:N105),2) -> 0
A106: A | B106: The Contractor shall allow for full compliance with the Construction Environment Management Plan as described in Sustainability Certification Project Requirements and Procedures. | C106: item | D106: 1 | G106: =E106*F106 -> 0 | J106: =ROUND(SUM(G106:I106),2) -> 0 | K106: =ROUND(D106*E106,2) -> 0 | L106: =ROUND(D106*G106,2) -> 0 | M106: =ROUND(D106*H106,2) -> 0 | N106: =ROUND(D106*I106,2) -> 0 | O106: =ROUND(SUM(L106:N106),2) -> 0
B107: CONTROL AND PROTECTION | G107: =E107*F107 -> 0 | J107: =ROUND(SUM(G107:I107),2) -> 0 | K107: =ROUND(D107*E107,2) -> 0 | L107: =ROUND(D107*G107,2) -> 0 | M107: =ROUND(D107*H107,2) -> 0 | N107: =ROUND(D107*I107,2) -> 0 | O107: =ROUND(SUM(L107:N107),2) -> 0
B108: Fire Protection | G108: =E108*F108 -> 0 | J108: =ROUND(SUM(G108:I108),2) -> 0 | K108: =ROUND(D108*E108,2) -> 0 | L108: =ROUND(D108*G108,2) -> 0 | M108: =ROUND(D108*H108,2) -> 0 | N108: =ROUND(D108*I108,2) -> 0 | O108: =ROUND(SUM(L108:N108),2) -> 0
...

Sheet B Day works 
A1: Local estimate Nr. B
A2: General requirements
A4: =[1]KS!C4 -> Būves nosaukums/Building: C2-9
A5: =[1]KS!C5 -> Objekta nosaukums/Object: TEC ēkas pārbūve par atpūtas centru C2-9/TEC building reconstruction into a recreation center C2-9
A6: =[1]KS!C6 -> Objekta adrese/Object adress: Andrejostas iela 21, Rīga, LV-1045
A11: No. | B11: Name of construction work | C11: Unit | D11: Quantity | E11: Rate (euro/h) | F11: TOTAL
B13: Page 1
B14: GENERALLY
A15: A | B15: The daywork schedule will be administered strictly in accordance with the General Conditions of Contract and the Particular Conditions of Contract.
A16: B | B16: The daywork schedule shall only be for labour, materials and plant outside of or in addition to the Scope of Works as required or reasonably implied by all Contract Documents and will be as approved by the Engineer.
A17: C | B17: The Contractor will be paid for daywork schedule items carried out during the course of the Contract at the rates tendered in this schedule of rates. Profit and overheads are not to be included in the actual rates but stated as a percentage to be added at the end of Labour, Materials & Plant Sections of this schedule of rates.
A18: D | B18: The time engaged in the authorized works will be certified and paid. In the event of labour or plant having to be brought to the site specially for an item of the dayworks schedule, then a reasonable allowance will be made for travelling time. The allowance for travelling time is to be agreed before the dayworks schedule item is executed.
A19: E | B19: Daywork schedule rates tendered by the Contractor will be carefully taken into account at the time Tenders are being considered.
A20: F | B20: This dayworks schedule may be used in relation to all or part of the works. Where an Authority standard BOQ format has been used for a specific part of the work (which may include a specific dayworks schedule), either dayworks schedule may be used, at the discretion of the Engineer.
B22: Page 2
B23: RATES OF LABOUR
A24: A | B24: The Daywork rates quoted for Labour are to be the NET amounts payable including for use and waste of hand tools, use of all ordinary non-mechanical plant, stagings, scaffolding, tarpaulins, use of electric, light and water for the Works etc., and all special inducements for working. Unless specifically authorised in writing by the Consultant, non-productive overtime or special rates for overtime will not be admissible. The cost of all insurance, supervisory staff, including engineers, foremen, instruments, etc. clerks, storemen etc. to be included in the percentage addition for profit and overheads.
A25: B | B25: The NET rates for labour shall be the rates for persons directly engaged in the Works on Site or in the Contractor's workshops located in Abu Dhabi.
B26: RATES FOR MATERIAL
A27: C | B27: Materials used as items of the daywork schedule shall be as specified for the Works. The rates shall include delivery to the Site. In the event any materials are required for use as items of the daywork schedule which are not included in the schedule, the current NET market price shall apply, plus a percentage for profit and overhead, as identified within this schedule, which shall include all costs for collecting from the site store yard, loading, transporting, unloading at the Site.
A28: D | B28: The NET unit cost of materials shall be the actual cost of materials purchased specifically for the Works, or materials used from the Contractor's stock charged at current market prices plus a reasonable allowance for delivery to the Site.
B29: RATES FOR PLANT
A30: E | B30: The definition of hire terms are as follows:
A31: F | B31: Hourly hire - any hour of any day less than eight hours.
A32: G | B32: Daily hire - an eight-hour day. In the event that more than eight hours in less than twenty-four hours are worked consecutively (excluding normal breaks, etc.), the excess hours will be paid for as a direct proportion of daily hire rates.
E33: 0
B34: Page 3
B35: RATES FOR PLANT (CONT'D)
A36: A | B36: Plant (other than small tools and workshop equipment and operatives) used in the daywork schedule shall be paid for at the rates included in the daywork schedule or at the rates approved in writing by the Engineer prior to the execution of the Works. The Contractor shall present to the Engineer his proposed rates for plant or equipment not included in the daywork schedule as soon as possible after he becomes aware of the requirement to utilize such plant.
A37: B | B37: Plant hire rates shall include for drivers, attendants and operators, cost of maintaining in proper working order, attendance in starting up and shutting down, refuelling and all fuel and power, oils, greases and cleaning materials, replacement and/or sharpening of tools and all other ancillary items including consumable spares.
A38: C | B38: Time engaged actually working only will be allowed. idle time in maintenance, standing time or travelling to the site will not be allowed.
E39: 0
B40: Page 4
B41: LABOUR ON SITE
A42: A | B42: Semi-skilled labourers | C42: hr | E42: Rate Only
A43: B | B43: Unskilled labourers | C43: hr | E43: Rate Only
A44: C | B44: Steel fixer / Bender | C44: hr | E44: Rate Only
A45: D | B45: Welder | C45: hr | E45: Rate Only
A46: E | B46: Banksman | C46: hr | E46: Rate Only
A47: F | B47: Carpenter | C47: hr | E47: Rate Only
A48: G | B48: Bricklayer / Stone Mason / Concrete finisher | C48: hr | E48: Rate Only
A49: H | B49: Scaffolder | C49: hr | E49: Rate Only
A50: J | B50: Plant operator: Heavy Duty | C50: hr | E50: Rate Only
A51: K | B51: Plant operator: Light Duty | C51: hr | E51: Rate Only
A52: L | B52: Driver: Heavy Duty | C52: hr | E52: Rate Only
A53: M | B53: Driver: Light Duty | C53: hr | E53: Rate Only
... A55: P | B55: Allow for Profit and Overhead on labour | C55: % | E55: Rate Only
E56: 0
B57: Page 5
B58: MATERIAL DELIVERED TO SITE
B59: The Contractor shall be paid the additional percentage required to be added to the invoice cost of materials
A60: A | B60: Cement (Sulphate resistant) | C60: bag | E60: Rate Only
A61: B | B61: Cement (Ordinary Portland) | C61: bag | E61: Rate Only
A62: C | B62: Sand for concrete | C62: m3 | E62: Rate Only
A63: D | B63: 20 mm Course aggregate | C63: m3 | E63: Rate Only
A64: E | B64: Reinforcement Steel | C64: kg | E64: Rate Only
A65: F | B65: A142 fabric reinforcement to BS4483 | C65: m2 | E65: Rate Only
A66: G | B66: A393 fabric reinforcement to BS4484 | C66: m2 | E66: Rate Only
A67: H | B67: Formwork | C67: m2 | E67: Rate Only
A68: J | B68: 6mm Protection Plywood | C68: m2 | E68: Rate Only
A69: K | B69: 1000 gauge polyethylene sheet | C69: m2 | E69: Rate Only
A70: L | B70: Allow for Profit and Overhead on material | C70: % | E70: Rate Only
E71: 0
B72: Page 5
B73: PLANT HIRE
B74: The Contractor shall inserted the rates required for the following plant and machinery
A75: A | B75: Piling rig | C75: hr | E75: Rate Only
A76: B | B76: Truck (chassis), 11-15 T | C76: hr | E76: Rate Only
A77: C | B77: Trailers (flat-bed), up to 10T | C77: hr | E77: Rate Only
A78: D | B78: Pick-ups light duty, 1501-2000cc | C78: hr | E78: Rate Only
A79: E | B79: Mobile crane 30 Ton | C79: hr | E79: Rate Only
A80: F | B80: Mobile crane 50 Ton | C80: hr | E80: Rate Only
A81: G | B81: Concrete mixers, 200/150 (07/05) | C81: hr | E81: Rate Only
A82: H | B82: Bar bending (power) machine (up to 50mm) | C82: hr | E82: Rate Only
A83: I | B83: Welding and cutting set | C83: hr | E83: Rate Only
A84: J | B84: Water pumps self priming, 50mm | C84: hr | E84: Rate Only
A85: K | B85: Generators (small), 25 KVA complete with all accessories | C85: hr | E85: Rate Only
A86: L | B86: Hammer drill, heavy | C86: hr | E86: Rate Only
... A91: R | B91: Allow for Profit and Overhead on plant | C91: % | E91: Rate Only
E92: 0
B93: Page 6
B94: Page 1 | E94: Rate Only
B95: Page 2 | E95: Rate Only
B96: Page 3 | E96: Rate Only
B97: Page 4 | E97: Rate Only
B98: Page 5 | E98: Rate Only
B99: Total page 6 | E99: Rate Only
E100: 0

Sheet 0-1
F1: Lokālā tāme Nr./Local estimate No | G1: 0-1
F2: Būvlaukuma sagatavošanas darbi, pagaidu būves, uzturēšanas darbi/Site preparation and maintenance
A4: =KS!C4 -> Būves nosaukums/Building: Daudzīvokļu ēka / Residental building C2-10
A5: =KS!C5 -> Objekta nosaukums/Object: Dzīvojamās ēkas C2-10 jaunbūve/ Residential building C2-10
A6: =KS!C6 -> Objekta adrese/Object adress: Andrejostas iela 35, Rīga, LV-1045 | M6: Tāmes izmaksas | P6: euro
P8: =P96 -> 0
F10: Vienības izmaksas/Unit rate | N10: Kopā uz visu apjomu/Total amount
A11: N.p.k./No | B11: Kods*/Code | C11: Būvdarbu nosaukums/Description of the construction work | D11: Mērvienība/ Unit | E11: Daudzums/ Quantity | F11: laika norma (c/h)/time rate (w/h) | G11: darba samaksas likme* (euro/h)/labour wage rate (euro/h)* | H11: darba alga/ salary | I11: būvizstrādājumi/ materials | J11: mehānismi/ mechanisms | K11: kopā/ total | L11: darbietilpība (c/h)/labor (w/h) | M11: darba alga/ salary | N11: būvizstrādājumi/ materials | O11: mehānismi/ mechanisms | P11: summa/ Total
A12: 1 | B12: 2 | C12: 3 | D12: 4 | E12: 5 | F12: =E12+1 -> 6 | G12: =F12+1 -> 7 | H12: =G12+1 -> 8 | I12: =H12+1 -> 9 | J12: =I12+1 -> 10 | K12: =J12+1 -> 11 | L12: =K12+1 -> 12 | M12: =L12+1 -> 13 | ... P12: =O12+1 -> 16
C14: Būvlaukuma sagatavošanas darbi un uzturēšana kopā ēkām C2-09 un C2-10/ Site preparation and maintenance for buildings C2-09 un C2-10
C15: Būvlaukuma aprīkojums, pagaidu būves saskaņā ar DOP daļas risinājumiem/ Construction site equipment, temporary structures in accordance with the solutions of the DOP part
A16: 1 | C16: Apsardzes telpas uzstādīšana. 6.0 x 2.5 m (izmēru nosaka uzņemējs)/ Security premises, cabin container type 2.5x6x2.35(m) | D16: gb | E16: 1
A17: =A16+1 -> 2 | C17: Caurlaides barjera/ Pass barrier | D17: gb | E17: 1
A18: =A17+1 -> 3 | C18: Elektro mehaniskas (hidrauliskas) teritorijas barjera / Electro-mechanical (hydraulic) area barrier | D18: gb | E18: 1
A19: =A18+1 -> 4 | C19: Mehaniskas teritorijas vārti / Mechanical area barrier | D19: gb | E19: 4
A20: =A19+1 -> 5 | C20: Elektro mehaniskas (hidrauliskas) teritorijas barjera (1.2m) / Electro-mechanical (hydraulic) area barrier | D20: gb | E20: 2
A21: =A20+1 -> 6 | C21: Ugunsdzēsības stenda uzstādīšana (stenda komplektācija saskaņā ar MK noteikumu "Ugunsdrošības noteikumi" prasībām) / Firefighting stand installation (stand assembly in accordance with the requirements of the Cabinet Regulation "Fire Safety Regulations") | D21: gb | E21: 3
A22: =A21+1 -> 7 | C22: Sauso biotualešu uzstādīšana. 1.5 x 1.5 m/ Installation of dry biotoilets. 1.5 x 1.5 m | D22: gb | E22: 15
A23: =A22+1 -> 8 | C23: Konteinera tipa sanitartehnisko telpu uzstādīšana 2.5 x 6.0 m Ieskaitot nomas, mobilizacijas, uzstādīšanas un demobilizācijas izmaksas / Installation of container-type sanitary facilities 2.5 x 6.0 m Including rental, mobilization, installation and demobilization costs | D23: gb | E23: 4
A24: =A23+1 -> 9 | C24: Sadzīves atkritumu konteinera uzstādīšana un apkalpošāna visā būvdarbu laikā / Installation and maintenance of a municipal waste container throughout the construction work | D24: kpl | E24: 2
A25: =A24+1 -> 10 | C25: Inženieru telpu uzstādīšana 2.5 x 6.0 m . Ieskaitot nomas, mobilizacijas, uzstādīšanas un demobilizācijas izmaksas ar ugunsdzēšamu aparātu/ Installation of engineering premises 2.5 x 6.0 m. Including rental, mobilization, installation and demobilization costs | D25: gb | E25: 8
A26: =A25+1 -> 11 | C26: Strādnieku telpu uzstādīšana 2.5 x 6.0 m Ieskaitot nomas, mobilizacijas, uzstādīšanas un demobilizācijas izmaksas ar ugunsdzēšamu aparātu/ Installation of workers' premises 2.5 x 6.0 m Including rental, mobilization, installation and demobilization costs | D26: gb | E26: 30
A27: =A26+1 -> 12 | C27: Konteinera tipa noliktavas telpu uzstādīšana 2.5 x 6.0 m Ieskaitot nomas, mobilizacijas, uzstādīšanas un demobilizācijas izmaksas. ar ugunsdzēšamu aparātu/ Installation of container-type warehouse premises 2.5 x 6.0 m Including rental, mobilization, installation and demobilization costs | D27: gb | E27: 11
A28: 13 | C28: Būvlaukuma pagaidu žogs. Pagaidu nožogojums "BEKAERT". Ieskaitot nomas, mobilizacijas, un demobilizācijas izmaksas. Temporary fence on the construction site. Temporary fencing "BEKAERT". Including rental, mobilization, installation and demobilization costs. | D28: m | E28: 946
A29: 14 | C29: Pagaidu ūdensvada pieslēguma izbūve, t.sk.:/ Construction of a temporary water supply connection, including: | D29: kpl | E29: 1
A30: 14.1 | C30: Noteikumu pagaidu pieslēguma izbūvei pieprasīšana / Requesting regulations for the construction of a temporary connection | D30: kpl | E30: 1
A31: 14.2 | C31: ūdensskaitītājs DN15/ water meter DN15 | D31: gb | E31: 1
A32: 14.3 | C32: cauruļvads DN25 ar uzsildīšanu/ DN25 pipeline with heating | D32: kpl | E32: 1
A33: 15 | C33: Pagaidu spices izbūvēšana un tamponēšana/ setting and dismantling of temporal spoke | D33: kpl | E33: 4
A34: =A33+1 -> 16 | C34: Pagaidu elektroapgādes pieslēguma izbūve, t.sk., skatīt ELT-sadaļu:/ Construction of temporary power supply connection, including: | D34: kpl | E34: 1
A35: 16.1 | C35: pagaidu sadales kaste 150 kW / 380 V / 50 Hz / 3 fāzes/ temporary distribution box 150 kW / 380 V / 50 Hz / 3 phases; | D35: gb | E35: 8
A36: 16.2 | C36: 2 kabeļi ar atbilstošu šķērsgriezumu, L vienam kabelim/ 2 cables with corresponding cross-section, L for one cable. | D36: kpl | E36: 1
A37: 17 | C37: Būvlaukuma Apgaismojums Lighting
A38: 17.1 | C38: Būvlaukums. Apgaismojuma masts ar LED prožektoru 50 W (100W) uz 9 m augsta staba un elektropieslēgumu (stabs) / Lighting mast with LED floodlight 50 W (100W) on 9 m high pole and electrical connection. Stabs/ mast | D38: gb | E38: 18
A39: 17.2 | C39: Būvlaukums. Apgaismojuma masts ar LED prožektoru 50 W (100W) uz 9 m augsta staba un elektropieslēgumu (stabs) / Lighting mast with LED floodlight 50 W (100W) on 9 m high pole and electrical connection. Prožektors/ floodlight | D39: gb | E39: 36
A40: 18 | C40: Būvnieku pilsētiņa. Apgaismojums
A41: 18.1 | C41: Būvnieku pilsetiņa. Apgaismojuma masts ar LED prožektoru 50 W (100W) uz 9 m augsta staba un elektropieslēgumu (stabs) / Lighting mast with LED floodlight 50 W (100W) on 9 m high pole and electrical connection. Stabs/ mast | D41: gb | E41: 9
A42: 18.2 | C42: Būvnieku pilsetiņa. Apgaismojuma masts ar LED prožektoru 50 W (100W) uz 9 m augsta staba un elektropieslēgumu (stabs) / Lighting mast with LED floodlight 50 W (100W) on 9 m high pole and electrical connection. Prožektors/ floodlight | D42: gb | E42: 18
A43: 19 | C43: Pagaidu EST pieslēguma izbūve / Construction of a temporary EST connection | D43: kpl | E43: 1
A44: =A43+1 -> 20 | C44: Būvlaukuma video monitorings/ Construction site video monitoring | D44: kpl | E44: 1
A45: =A44+1 -> 21 | C45: Būvgružu konteineru būvdarbu laikā/ Container for construction waste | D45: gb | E45: 4
A46: =A45+1 -> 22 | C46: Smēķēšanas vieta/ smoking place | D46: gb | E46: 2
A47: =A46+1 -> 23 | C47: Stenda ar stropēšanas shēmām un kravu masu tabulu uzstādīšana/ Installation of a stand with slinging schemes and cargo weight tables | D47: gb | E47: 3
A48: =A47+1 -> 24 | C48: Stropēšanas aprīkojuma glabāšanas vietas ierīkošana/ Installation of sling equipment storage space | D48: gb | E48: 3
A49: =A48+1 -> 25 | C49: ABC klases pulvera ugunsdzēšamais aparāts. 6 kg ABC pulvera pārnēsājamie ugunsdzēsības aparāti PA-6A. apjoms norādīts orientējoši. /ABC class powder fire extinguisher. 6 kg ABC powder portable fire extinguishers PA-6A. the amount is indicative. | D49: gb
A50: =A49+1 -> 26 | C50: Riteņu mazgāšanas/ tīrišanas laukuma izbūve un uzturēšana/ Wheel washing area construction and maintenance | D50: kpl | E50: 3
A51: =A50+1 -> 27 | C51: Būvtāfele un informācijas zīmes/ Construction board and information signs | D51: kpl | E51: 1
A52: =A51+1 -> 28 | C52: Teritorijas kustības shēma/ Territorial movement scheme | D52: gb | E52: 1
A53: =A52+1 -> 29 | C53: Pagaidu ceļa izbūve ar platumu min 4,5 m (blietēta esošā grunts, 300-350 mm blietētas dolomīta šķembas)/ Temporary road construction with a width of at least 4.5 m (compacted existing soil, 300-350 mm compacted dolomite rubble) | D53: m2 | E53: 8000
A54: =A53+1 -> 30 | C54: Ceļu plātnes dz./betona (6000x2000x140) pārvietošana- pagaidu ceļu izbūvei/ Road reinforcement / concrete slabs (6000x2000x140) ayer or installation for the installation of underground utilities | D54: gb | E54: 0
A55: =A54+1 -> 31 | C55: Grunts ūdens līmeņa pazemināšanas sistēmas noma, ierīkošana, uzturēšana un demontāža (Iekārtas darbības laiku nosaka būvuzņemējs saskaņojot )/ Rental, installation, maintenance and dismantling of groundwater level lowering system (The operation time of the equipment is determined by the construction contractor in coordination with the building designer) | D55: kpl | E55: 2
A56: =A55+0.1 -> 31.1 | C56: caurules/ garums līdz Daugavai/ Pipes/Length to the Daugava | D56: m | E56: 150
A57: =A55+1 -> 32 | C57: Brīdinājuma zīmju īre (montāža/demontāža)/ Rental of warning signs (assembly / disassembly) | D57: kpl | E57: 1
A58: =A57+1 -> 33 | C58: Ceļu zīmes būvlaukumā/ In a sign of travels site area | D58: kpl | E58: 1
A59: =A58+1 -> 34 | C59: Ceļu zīmes saskaņā ar MK noteikumiem Nr. 421 „Noteikumi par darba vietu aprīkošanu uz ceļiem”. Spiedvada kanalizācijas izbūvešanas etapā/ Signs of travels in accordance with the MK conditions Nr. 421 . In the Spiedvada sewage system izbūvešanas stage | D59: kpl | E59: 1
A60: =A59+1 -> 35 | C60: Montāžas darbi celtņiem/ Assembly work cranes
A61: =A60+0.1 -> 35.1 | C61: TORŅA CELTNIS Nr.C2-9-1, Liebherr 256 HC vai analogs , R=48.3 m, UZ ENKURIEM / TOWER CRANE No. C2-9-1, Liebherr 256 HC or similar, R=48.3 m, ON ANCHORS | D61: gb | E61: 0
A62: =A61+0.1 -> 35.2 | C62: TORŅA CELTNIS Nr.C2-9-2, ZBK-80 vai analogs, R=50.0 m / TOWER CRANE No. C2-9-2, ZBK-80 or similar, R=50.0 m | D62: gb | E62: 0
A63: =A62+0.1 -> 35.3 | C63: TORŅA CELTNIS Nr.C2-9-3, Liebherr 256 HC, R=36.7 m vai analogs / TOWER CRANE No. C2-9-3, Liebherr 256 HC, R=36.7 m or similar | D63: gb | E63: 0
A64: =A63+0.1 -> 35.4 | C64: TORŅA CELTNIS Nr.C2-10-2 "Liebherr 500 HC- 20", R=40.0 m VAI ANALOGU, UZ ENKURIEM / TOWER CRANE No. C2-10-2 "Liebherr 500 HC- 20", R=40.0 m OR SIMILAR, ON ANCHORS | D64: gb | E64: 1
A65: =A64+0.1 -> 35.5 | C65: TORŅA CELTNIS Nr.C2-10-1 "Liebherr 256 HC", R=43.3 m VAI ANALOGU / TOWER CRANE No. C2-10-1 "Liebherr 256 HC", R=43.3 m OR SIMILAR | D65: gb | E65: 1
A66: =A65+0.1 -> 35.6 | C66: Pamati zem torņa celtņu (pāļi, skat BK 1.kārta+ režģogs) / Foundations under tower cranes (piles + lattice girder) | D66: kpl | E66: 2
A67: =A66+0.1 -> 35.7 | C67: DVP torņa celtņu montāža/ demontāža / Assembly/dismantling of DVP tower cranes | D67: kpl | E67: 2
A68: =A60+1 -> 36 | C68: Koki (apomi un iekļauti labiekārtošanas darbā, skatīt kopā ar TS-L sadaļu)/ Trees (including tree pits, part of landscaping work, refer to the TS-L section)
A69: =A68+0.1 -> 36.1 | C69: Koku nociršana / Tree felling | D69: gb | E69: 14
C70: Būvlaukuma uzturēšana (izmaksas iekļautas virsizdevumos)/ Site maintenance (costs included in overheads)*
A71: =A68+1 -> 37 | C71: Apsardzes izmaksas (1 punkta)/ Security costs (1 point)** | D71: mēn. | E71: 34
A72: =A71+1 -> 38 | C72: Atkritumu konteineru noma (8m3 4 gab), būvgružu sķirošana un utilizācija/ Waste container rental (8m3 4 pcs.), Construction waste sorting and utilization | D72: mēn. | E72: 34
A73: =A72+1 -> 39 | C73: Būvasu nospraušana un ģeodēziskā uzraudzība būvdarbu laikā/ Construction shaft marking and geodetic supervision during construction works/ Construction shaft marking and geodetic supervision during construction works | D73: obj. | E73: 1
A74: =A73+1 -> 40 | C74: Satiksmes organizācijas projektu izstrādāšana, skaņošana un satiksmes organizācijas risinājumu nodrošinājums būvdarbu laika dažādos etapos(tai skaitā nepieciešamā aprīkojuma noma)/ Development, tuning of traffic organization projects and provision of traffic organization solutions in various stages of construction works (including rental of necessary equipment) | D74: obj. | E74: 1
A75: =A74+1 -> 41 | C75: Elektrokabeļu, būvlaukuma sadaļu un cita sīkā aprīkojuma noma/ Rental of electric cables, construction site sections and other small equipment | D75: mēn. | E75: 34
A76: =A75+1 -> 42 | C76: Pagaidu atļaujas un citu teritoriju izmantošanas izmaksas/ Costs of temporary permits and use of other areas | D76: kpl | E76: 1
A77: =A76+1 -> 43 | C77: Sakaru pakalpojumi objektā/ Communication services on site | D77: mēn. | E77: 34
A78: =A77+1 -> 44 | C78: Elektroenerģijas izmaksas objektā/ Electricity costs at the facility | D78: mēn. | E78: 34
A79: =A78+1 -> 45 | C79: Ūdens izmaksas objektā/ Water costs at the facility | D79: mēn. | E79: 34
A80: =A79+1 -> 46 | C80: Apkalpošana sanitāro-tehniskie iekārtas. Asenizatora pakalpojumi./ Service of sanitary-technical equipment. Sewerage services. | D80: mēn. | E80: 34
A81: =A80+1 -> 47 | C81: Brīdinājuma zīmju īre (montāža/demontāža)/Rental of warning signs (assembly / disassembly) | D81: mēn. | E81: 34
A82: =A81+1 -> 48 | C82: Dzeramā ūdens stendu noma un ūdens (___gab.)/ Drinking water stand rental and water (___pcs.) | D82: mēn. | E82: 34
A83: =A82+1 -> 49 | C83: Izbūvēto telpu ģenerālo tīrīšana/ General cleaning of constructed premises | D83: m2
A84: =A83+1 -> 50 | C84: Būvlaukuma un darba vietu attīrīšana no sniega, smiltīm uc., novākšana/ Cleaning of construction sites and workplaces from snow, sand, etc., removal | D84: kpl | E84: 1
A85: =A84+1 -> 51 | C85: Braucamo ceļu tīrīšana/ Driveway cleaning | D85: kpl | E85: 1
C86: Citi darbi/ Other works
A87: =A85+1 -> 52 | C87: CTA (izmaksas iekļautas virsizdevumos)/ CTA (costs included in overheads) | D87: mēn. | E87: 34
A88: =A87+1 -> 53 | C88: Būvniecības risku apdrošināšana 100% līguma summas apmērā (izmaksas iekļautas virsizdevumos)/ Construction risk insurance in the amount of 100% of the contract amount (costs are included in overheads) | D88: mēn. | E88: 34
A89: =A88+1 -> 54 | C89: Darbu veikšanas projektu (DVP) izstrādāšana visiem būvdarbu veidiem/ Development of works performance projects (DVP) for all types of construction works | D89: kpl | E89: 1
A90: =A89+1 -> 55 | C90: Informācijas savākšanu par blakus zemes gabalos esošajām pazemes un virszemes konstrukcijam. Monitoring / Collection of information on underground and surface communications on adjacent plots. | D90: kpl/obj. | E90: 1
A91: =A90+1 -> 56 | C91: Hidroģeoloģiskās pārbaudes veikšana/ Hydrogeological inspection | D91: obj. | E91: 1
A92: =A91+1 -> 57 | C92: Būvniecības izpilddokumentācijas kārtošana būvdarbu laikā, būves ekspluatācijas instrukcijas sagatavošana./ Arrangement of construction executive documentation during construction works, preparation of construction operation instructions. | D92: kpl | E92: 1
A93: =A92+1 -> 58 | C93: Būvdarbu laikā nepieciešamo pārbaužu veikšana, atzinumu saņemšana un būves nodošana ekspluatācija/ Carrying out the necessary inspections during construction works, receiving opinions and putting the building into operation | D93: kpl | E93: 1
A94: =A93+1 -> 59 | C94: ENERGOEFIKTĪVITĀTES NOVERTĒJUMS: BlowerDoorTests/ BlowerDoor test | D94: kpl | E94: 1
C96: Izmaksas kopā, t. sk. darba devēja sociālais nodoklis (%) /Total costs, including employer's social tax (%) | L96: =SUM($L$13:L95) -> 0 | M96: =SUM($M$13:M95) -> 0 | N96: =SUM($N$13:N95) -> 0 | O96: =SUM($O$13:O95) -> 0 | P96: =SUM($P$13:P95) -> 0

Sheet 1-0Z
F1: Lokālā tāme Nr./Local estimate No | G1: 1-0
F2: Zemes darbi/Earthworks
A4: =KS!C4 -> Būves nosaukums/Building: Daudzīvokļu ēka / Residental building C2-10
A5: =KS!C5 -> Objekta nosaukums/Object: Dzīvojamās ēkas C2-10 jaunbūve/ Residential building C2-10
A6: =KS!C6 -> Objekta adrese/Object adress: Andrejostas iela 35, Rīga, LV-1045 | M6: Tāmes izmaksas | O6: 0
P8: Tāme sastādīta/Date _____. gada ____. ____________
F10: Vienības izmaksas/Unit rate | N10: Kopā uz visu apjomu/Total amount
A11: N.p.k./No | B11: Kods*/Code | C11: Būvdarbu nosaukums/Description of the construction work | D11: Mērvienība/ Unit | E11: Daudzums/ Quantity | F11: laika norma (c/h)/time rate (w/h) | G11: darba samaksas likme* (euro/h)/labour wage rate (euro/h)* | H11: darba alga/ salary | I11: būvizstrādājumi/ materials | J11: mehānismi/ mechanisms | K11: kopā/ total | L11: darbietilpība (c/h)/labor (w/h) | M11: darba alga/ salary | N11: būvizstrādājumi/ materials | O11: mehānismi/ mechanisms | P11: summa/ Total
A12: 1 | B12: 2 | C12: 3 | D12: 4 | E12: 5 | F12: =E12+1 -> 6 | G12: =F12+1 -> 7 | H12: =G12+1 -> 8 | I12: =H12+1 -> 9 | J12: =I12+1 -> 10 | K12: =J12+1 -> 11 | L12: =K12+1 -> 12 | M12: =L12+1 -> 13 | ... P12: =O12+1 -> 16
C14: C2-10
A15: 1 | C15: Būvbedres grunts izstrāde zem ēkas C2-9/ Excavated soil under the building | D15: m3 | E15: 9647
A16: =A15+1 -> 2 | C16: Grunts iekraušana un izvešana būvlaukuma atbērtnē (apjoms norādīts sablīvētā veidā) /Loading and unloading of soil at the construction site (volume is indicated in compacted form) | D16: m3 | E16: 9647
A17: =A16+1 -> 3 | C17: Būvbedres aizbēršana ar pievesto smilti (apjoms norādīts sablīvētā veidā), zem ēkas/Backfilling of a construction pit with applied sand (volume is indicated in compacted form) under the building | D17: m3 | E17: 2992.5
C19: Izmaksas kopā, t. sk. darba devēja sociālais nodoklis (%) /Total costs, including employer's social tax (%) | L19: =SUM($L$13:L18) -> 0 | M19: =SUM($M$13:M18) -> 0 | N19: =SUM($N$13:N18) -> 0 | O19: =SUM($O$13:O18) -> 0 | P19: =SUM($P$13:P18) -> 0

Sheet 1-2Pp
F1: Lokālā tāme Nr./Local estimate No | G1: 1-2
F2: Pamatu plātne, pamati, režģoģi / Baseplate, foundations
A4: =KS!C4 -> Būves nosaukums/Building: Daudzīvokļu ēka / Residental building C2-10
A5: =KS!C5 -> Objekta nosaukums/Object: Dzīvojamās ēkas C2-10 jaunbūve/ Residential building C2-10
A6: =KS!C6 -> Objekta adrese/Object adress: Andrejostas iela 35, Rīga, LV-1045 | M6: Tāmes izmaksas | O6: 0
P8: Tāme sastādīta/Date _____. gada ____. ____________
F10: Vienības izmaksas/Unit rate | N10: Kopā uz visu apjomu/Total amount
A11: N.p.k./No | B11: Kods*/Code | C11: Būvdarbu nosaukums/Description of the construction work | D11: Mērvienība/ Unit | E11: Daudzums/ Quantity | F11: laika norma (c/h)/time rate (w/h) | G11: darba samaksas likme* (euro/h)/labour wage rate (euro/h)* | H11: darba alga/ salary | I11: būvizstrādājumi/ materials | J11: mehānismi/ mechanisms | K11: kopā/ total | L11: darbietilpība (c/h)/labor (w/h) | M11: darba alga/ salary | N11: būvizstrādājumi/ materials | O11: mehānismi/ mechanisms | P11: summa/ Total
A12: 1 | B12: 2 | C12: 3 | D12: 4 | E12: 5 | F12: =E12+1 -> 6 | G12: =F12+1 -> 7 | H12: =G12+1 -> 8 | I12: =H12+1 -> 9 | J12: =I12+1 -> 10 | K12: =J12+1 -> 11 | L12: =K12+1 -> 12 | M12: =L12+1 -> 13 | ... P12: =O12+1 -> 16
C14: Monolītā dzelzsbetona pamatu plātnes un režģoģi / Reinforced concrete foundation slabs and pile caps
A15: 1 | C15: Pamatnes betonēšana b=100 mm Betons C40/50 ar kristalizējošu piedevu SHOMBURG BETOCRETE-CP-360-WP, betons ar betona piegādi, sūknēšanu, vibrēšanu, līdzināšanu, mitrināšanu, plēves piesegšanu, tehnoloģisko un deformācijas šuvju izveidi, ieliekamo detaļu iebetonēšanu, ja nepieciešams/Reinforced concrete floor b=100 mm, Concrete C40/50 whith crystallizing additive SHOMBURG BETOCRETE-CP-360-WP, concrete with concrete delivery, pumping, vibrating, leveling, wetting, covering with film, creating technological and deformation joints, concreting of insert parts, if necessary | D15: m3 | E15: 128.54
A16: =A15+1 -> 2 | C16: Pamatnes betonēšana b=110 mm Betons C40/50 ar kristalizējošu piedevu SHOMBURG BETOCRETE-CP-360-WP, betons ar betona piegādi, sūknēšanu, vibrēšanu, līdzināšanu, mitrināšanu, plēves piesegšanu, tehnoloģisko un deformācijas šuvju izveidi, ieliekamo detaļu iebetonēšanu, ja nepieciešams/Reinforced concrete floor b=110 mm, Concrete C40/50 whith crystallizing additive SHOMBURG BETOCRETE-CP-360-WP, concrete with concrete delivery, pumping, vibrating, leveling, wetting, covering with film, creating technological and deformation joints, concreting of insert parts, if necessary | D16: m3 | E16: 13.67
A17: =A16+1 -> 3 | C17: Pamatnes betonēšana b=220 mm Betons C40/50 ar kristalizējošu piedevu SHOMBURG BETOCRETE-CP-360-WP, betons ar betona piegādi, sūknēšanu, vibrēšanu, līdzināšanu, mitrināšanu, plēves piesegšanu, tehnoloģisko un deformācijas šuvju izveidi, ieliekamo detaļu iebetonēšanu, ja nepieciešams/Reinforced concrete floor b=220 mm, Concrete C40/50 whith crystallizing additive SHOMBURG BETOCRETE-CP-360-WP, concrete with concrete delivery, pumping, vibrating, leveling, wetting, covering with film, creating technological and deformation joints, concreting of insert parts, if necessary | D17: m3 | E17: 4.09
A18: =A17+1 -> 4 | C18: Pamatnes betonēšana b=300 mm Betons C40/50 ar kristalizējošu piedevu SHOMBURG BETOCRETE-CP-360-WP, betons ar betona piegādi, sūknēšanu, vibrēšanu, līdzināšanu, mitrināšanu, plēves piesegšanu, tehnoloģisko un deformācijas šuvju izveidi, ieliekamo detaļu iebetonēšanu, ja nepieciešams/Reinforced concrete floor b=300 mm, Concrete C40/50 whith crystallizing additive SHOMBURG BETOCRETE-CP-360-WP, concrete with concrete delivery, pumping, vibrating, leveling, wetting, covering with film, creating technological and deformation joints, concreting of insert parts, if necessary | D18: m3 | E18: 952.31
A19: =A18+1 -> 5 | C19: Pamatnes betonēšana b=400 mm Betons C40/50 ar kristalizējošu piedevu SHOMBURG BETOCRETE-CP-360-WP, betons ar betona piegādi, sūknēšanu, vibrēšanu, līdzināšanu, mitrināšanu, plēves piesegšanu, tehnoloģisko un deformācijas šuvju izveidi, ieliekamo detaļu iebetonēšanu, ja nepieciešams/Reinforced concrete floor b=400 mm, Concrete C40/50 whith crystallizing additive SHOMBURG BETOCRETE-CP-360-WP, concrete with concrete delivery, pumping, vibrating, leveling, wetting, covering with film, creating technological and deformation joints, concreting of insert parts, if necessary | D19: m3 | E19: 2.51
A20: =A19+1 -> 6 | C20: Pamatnes betonēšana b=530 mm Betons C40/50 ar kristalizējošu piedevu SHOMBURG BETOCRETE-CP-360-WP, betons ar betona piegādi, sūknēšanu, vibrēšanu, līdzināšanu, mitrināšanu, plēves piesegšanu, tehnoloģisko un deformācijas šuvju izveidi, ieliekamo detaļu iebetonēšanu, ja nepieciešams/Reinforced concrete floor b=530 mm, Concrete C40/50 whith crystallizing additive SHOMBURG BETOCRETE-CP-360-WP, concrete with concrete delivery, pumping, vibrating, leveling, wetting, covering with film, creating technological and deformation joints, concreting of insert parts, if necessary | D20: m3 | E20: 17.79
A21: =A20+1 -> 7 | C21: Pamatnes malas 230x230mm betonēšana Betons C40/50 ar kristalizējošu piedevu SHOMBURG BETOCRETE-CP-360-WP, betons ar betona piegādi, sūknēšanu, vibrēšanu, līdzināšanu, mitrināšanu, plēves piesegšanu, tehnoloģisko un deformācijas šuvju izveidi, ieliekamo detaļu iebetonēšanu, ja nepieciešams/Reinforced concrete floor Slab_Edge_230x230mm, Concrete C40/50 whith crystallizing additive SHOMBURG BETOCRETE-CP-360-WP, concrete with concrete delivery, pumping, vibrating, leveling, wetting, covering with film, creating technological and deformation joints, concreting of insert parts, if necessary | D21: m3 | E21: 0.86
A22: =A21+1 -> 8 | C22: Pamatnes stiegrošana, t. sk palīgmateriāli (distanceri, sienamās stieples, konusi, uzgriežņi u.c.), stiegrojums B500B / Slab reinforcement and consumables (spacers, wall wires, cones, bolts etc.), reinforcement B500B | D22: t | E22: 134.37
A23: =A22+1 -> 9 | C23: Veidņu (apjoms precizējams veidņu izklājumā) , tsk. (palīgmateriāli (kokmateriāli, saplāksnis, stiprinājumi, caurlītes, konusi, aizbāžņi, eļļa, plēve) montāža, noma, demontāža režģogiem/ Formwork (volume to be specified in the formwork layout), incl. (auxiliary materials (timber, plywood, fasteners, tubes, cones, plugs, oil, film) assembly, rental, dismantling | D23: kpl | E23: 1
A24: =A23+1 -> 10 | B24: Cap_500mm | C24: Režģogu betonēšana Betons C40/50 ar kristalizējošu piedevu SHOMBURG BETOCRETE-CP-360-WP, betons ar betona piegādi, sūknēšanu, vibrēšanu, līdzināšanu, mitrināšanu, plēves piesegšanu, tehnoloģisko un deformācijas šuvju izveidi, ieliekamo detaļu iebetonēšanu, ja nepieciešams/ Pile cap , Concrete C40/50 whith crystallizing additive SHOMBURG BETOCRETE-CP-360-WP, concrete with concrete delivery, pumping, vibrating, leveling, wetting, covering with film, creating technological and deformation joints, concreting of insert parts, if necessary | D24: m3 | E24: 22.28
A25: =A24+1 -> 11 | B25: Cap_600mm | C25: Režģogu betonēšana Betons C40/50 ar kristalizējošu piedevu SHOMBURG BETOCRETE-CP-360-WP, betons ar betona piegādi, sūknēšanu, vibrēšanu, līdzināšanu, mitrināšanu, plēves piesegšanu, tehnoloģisko un deformācijas šuvju izveidi, ieliekamo detaļu iebetonēšanu, ja nepieciešams/ Pile cap , Concrete C40/50 whith crystallizing additive SHOMBURG BETOCRETE-CP-360-WP, concrete with concrete delivery, pumping, vibrating, leveling, wetting, covering with film, creating technological and deformation joints, concreting of insert parts, if necessary | D25: m3 | E25: 12.96
A26: 11.1 | B26: Cap_650mm | C26: Režģogu betonēšana Betons C40/50 ar kristalizējošu piedevu SHOMBURG BETOCRETE-CP-360-WP, betons ar betona piegādi, sūknēšanu, vibrēšanu, līdzināšanu, mitrināšanu, plēves piesegšanu, tehnoloģisko un deformācijas šuvju izveidi, ieliekamo detaļu iebetonēšanu, ja nepieciešams/ Pile cap , Concrete C40/50 whith crystallizing additive SHOMBURG BETOCRETE-CP-360-WP, concrete with concrete delivery, pumping, vibrating, leveling, wetting, covering with film, creating technological and deformation joints, concreting of insert parts, if necessary | D26: m3 | E26: 4.88
A27: =A25+1 -> 12 | B27: Cap_800mm | C27: Režģogu betonēšana Betons C40/50 ar kristalizējošu piedevu SHOMBURG BETOCRETE-CP-360-WP, betons ar betona piegādi, sūknēšanu, vibrēšanu, līdzināšanu, mitrināšanu, plēves piesegšanu, tehnoloģisko un deformācijas šuvju izveidi, ieliekamo detaļu iebetonēšanu, ja nepieciešams/ Pile cap , Concrete C40/50 whith crystallizing additive SHOMBURG BETOCRETE-CP-360-WP, concrete with concrete delivery, pumping, vibrating, leveling, wetting, covering with film, creating technological and deformation joints, concreting of insert parts, if necessary | D27: m3 | E27: 6.84
A28: =A27+1 -> 13 | B28: Cap_900mm | C28: Režģogu betonēšana Betons C40/50 ar kristalizējošu piedevu SHOMBURG BETOCRETE-CP-360-WP, betons ar betona piegādi, sūknēšanu, vibrēšanu, līdzināšanu, mitrināšanu, plēves piesegšanu, tehnoloģisko un deformācijas šuvju izveidi, ieliekamo detaļu iebetonēšanu, ja nepieciešams/ Pile cap , Concrete C40/50 whith crystallizing additive SHOMBURG BETOCRETE-CP-360-WP, concrete with concrete delivery, pumping, vibrating, leveling, wetting, covering with film, creating technological and deformation joints, concreting of insert parts, if necessary | D28: m3 | E28: 474.78
A29: =A28+1 -> 14 | B29: Cap_1100mm | C29: Režģogu betonēšana Betons C40/50 ar kristalizējošu piedevu SHOMBURG BETOCRETE-CP-360-WP, betons ar betona piegādi, sūknēšanu, vibrēšanu, līdzināšanu, mitrināšanu, plēves piesegšanu, tehnoloģisko un deformācijas šuvju izveidi, ieliekamo detaļu iebetonēšanu, ja nepieciešams/ Pile cap , Concrete C40/50 whith crystallizing additive SHOMBURG BETOCRETE-CP-360-WP, concrete with concrete delivery, pumping, vibrating, leveling, wetting, covering with film, creating technological and deformation joints, concreting of insert parts, if necessary | D29: m3 | E29: 417.42
A30: =A29+1 -> 15 | B30: Cap_1300mm | C30: Režģogu betonēšana Betons C40/50 ar kristalizējošu piedevu SHOMBURG BETOCRETE-CP-360-WP, betons ar betona piegādi, sūknēšanu, vibrēšanu, līdzināšanu, mitrināšanu, plēves piesegšanu, tehnoloģisko un deformācijas šuvju izveidi, ieliekamo detaļu iebetonēšanu, ja nepieciešams/ Pile cap , Concrete C40/50 whith crystallizing additive SHOMBURG BETOCRETE-CP-360-WP, concrete with concrete delivery, pumping, vibrating, leveling, wetting, covering with film, creating technological and deformation joints, concreting of insert parts, if necessary | D30: m3 | E30: 339.73
A31: =A30+1 -> 16 | B31: Cap_1400mm | C31: Režģogu betonēšana Betons C40/50 ar kristalizējošu piedevu SHOMBURG BETOCRETE-CP-360-WP, betons ar betona piegādi, sūknēšanu, vibrēšanu, līdzināšanu, mitrināšanu, plēves piesegšanu, tehnoloģisko un deformācijas šuvju izveidi, ieliekamo detaļu iebetonēšanu, ja nepieciešams/ Pile cap , Concrete C40/50 whith crystallizing additive SHOMBURG BETOCRETE-CP-360-WP, concrete with concrete delivery, pumping, vibrating, leveling, wetting, covering with film, creating technological and deformation joints, concreting of insert parts, if necessary | D31: m3 | E31: 74.52
A32: 16.1 | B32: R-6.1 | C32: Režģogu betonēšana Betons C40/50 ar kristalizējošu piedevu SHOMBURG BETOCRETE-CP-360-WP, betons ar betona piegādi, sūknēšanu, vibrēšanu, līdzināšanu, mitrināšanu, plēves piesegšanu, tehnoloģisko un deformācijas šuvju izveidi, ieliekamo detaļu iebetonēšanu, ja nepieciešams/ Pile cap , Concrete C40/50 whith crystallizing additive SHOMBURG BETOCRETE-CP-360-WP, concrete with concrete delivery, pumping, vibrating, leveling, wetting, covering with film, creating technological and deformation joints, concreting of insert parts, if necessary | D32: m3 | E32: 0.42
A33: 16.2 | B33: R-7.1 | C33: Režģogu betonēšana Betons C40/50 ar kristalizējošu piedevu SHOMBURG BETOCRETE-CP-360-WP, betons ar betona piegādi, sūknēšanu, vibrēšanu, līdzināšanu, mitrināšanu, plēves piesegšanu, tehnoloģisko un deformācijas šuvju izveidi, ieliekamo detaļu iebetonēšanu, ja nepieciešams/ Pile cap , Concrete C40/50 whith crystallizing additive SHOMBURG BETOCRETE-CP-360-WP, concrete with concrete delivery, pumping, vibrating, leveling, wetting, covering with film, creating technological and deformation joints, concreting of insert parts, if necessary | D33: m3 | E33: 1.06
A34: 16.3 | B34: R-8.1 | C34: Režģogu betonēšana Betons C40/50 ar kristalizējošu piedevu SHOMBURG BETOCRETE-CP-360-WP, betons ar betona piegādi, sūknēšanu, vibrēšanu, līdzināšanu, mitrināšanu, plēves piesegšanu, tehnoloģisko un deformācijas šuvju izveidi, ieliekamo detaļu iebetonēšanu, ja nepieciešams/ Pile cap , Concrete C40/50 whith crystallizing additive SHOMBURG BETOCRETE-CP-360-WP, concrete with concrete delivery, pumping, vibrating, leveling, wetting, covering with film, creating technological and deformation joints, concreting of insert parts, if necessary | D34: m3 | E34: 1.06
A35: 16.4 | B35: R-9.1 | C35: Režģogu betonēšana Betons C40/50 ar kristalizējošu piedevu SHOMBURG BETOCRETE-CP-360-WP, betons ar betona piegādi, sūknēšanu, vibrēšanu, līdzināšanu, mitrināšanu, plēves piesegšanu, tehnoloģisko un deformācijas šuvju izveidi, ieliekamo detaļu iebetonēšanu, ja nepieciešams/ Pile cap , Concrete C40/50 whith crystallizing additive SHOMBURG BETOCRETE-CP-360-WP, concrete with concrete delivery, pumping, vibrating, leveling, wetting, covering with film, creating technological and deformation joints, concreting of insert parts, if necessary | D35: m3 | E35: 4.72
A36: =A31+1 -> 17 | B36: R-3.1 | C36: Režģogu betonēšana Betons C40/50 ar kristalizējošu piedevu SHOMBURG BETOCRETE-CP-360-WP, betons ar betona piegādi, sūknēšanu, vibrēšanu, līdzināšanu, mitrināšanu, plēves piesegšanu, tehnoloģisko un deformācijas šuvju izveidi, ieliekamo detaļu iebetonēšanu, ja nepieciešams/ Pile cap , Concrete C40/50 whith crystallizing additive SHOMBURG BETOCRETE-CP-360-WP, concrete with concrete delivery, pumping, vibrating, leveling, wetting, covering with film, creating technological and deformation joints, concreting of insert parts, if necessary | D36: m3 | E36: 6.77
A37: =A36+1 -> 18 | B37: R-4.1 | C37: Režģogu betonēšana Betons C40/50 ar kristalizējošu piedevu SHOMBURG BETOCRETE-CP-360-WP, betons ar betona piegādi, sūknēšanu, vibrēšanu, līdzināšanu, mitrināšanu, plēves piesegšanu, tehnoloģisko un deformācijas šuvju izveidi, ieliekamo detaļu iebetonēšanu, ja nepieciešams/ Pile cap , Concrete C40/50 whith crystallizing additive SHOMBURG BETOCRETE-CP-360-WP, concrete with concrete delivery, pumping, vibrating, leveling, wetting, covering with film, creating technological and deformation joints, concreting of insert parts, if necessary | D37: m3 | E37: 21.81
A38: =A37+1 -> 19 | B38: R-6.1 | C38: Režģogu betonēšana Betons C40/50 ar kristalizējošu piedevu SHOMBURG BETOCRETE-CP-360-WP, betons ar betona piegādi, sūknēšanu, vibrēšanu, līdzināšanu, mitrināšanu, plēves piesegšanu, tehnoloģisko un deformācijas šuvju izveidi, ieliekamo detaļu iebetonēšanu, ja nepieciešams/ Pile cap , Concrete C40/50 whith crystallizing additive SHOMBURG BETOCRETE-CP-360-WP, concrete with concrete delivery, pumping, vibrating, leveling, wetting, covering with film, creating technological and deformation joints, concreting of insert parts, if necessary | D38: m3 | E38: 14.99
A39: =A38+1 -> 20 | B39: R-7.1 | C39: Režģogu betonēšana Betons C40/50 ar kristalizējošu piedevu SHOMBURG BETOCRETE-CP-360-WP, betons ar betona piegādi, sūknēšanu, vibrēšanu, līdzināšanu, mitrināšanu, plēves piesegšanu, tehnoloģisko un deformācijas šuvju izveidi, ieliekamo detaļu iebetonēšanu, ja nepieciešams/ Pile cap , Concrete C40/50 whith crystallizing additive SHOMBURG BETOCRETE-CP-360-WP, concrete with concrete delivery, pumping, vibrating, leveling, wetting, covering with film, creating technological and deformation joints, concreting of insert parts, if necessary | D39: m3 | E39: 84.19
A40: =A39+1 -> 21 | B40: R-8.1 | C40: Režģogu betonēšana Betons C40/50 ar kristalizējošu piedevu SHOMBURG BETOCRETE-CP-360-WP, betons ar betona piegādi, sūknēšanu, vibrēšanu, līdzināšanu, mitrināšanu, plēves piesegšanu, tehnoloģisko un deformācijas šuvju izveidi, ieliekamo detaļu iebetonēšanu, ja nepieciešams/ Pile cap , Concrete C40/50 whith crystallizing additive SHOMBURG BETOCRETE-CP-360-WP, concrete with concrete delivery, pumping, vibrating, leveling, wetting, covering with film, creating technological and deformation joints, concreting of insert parts, if necessary | D40: m3 | E40: 91.19
A41: =A40+1 -> 22 | B41: R-9.1 | C41: Režģogu betonēšana Betons C40/50 ar kristalizējošu piedevu SHOMBURG BETOCRETE-CP-360-WP, betons ar betona piegādi, sūknēšanu, vibrēšanu, līdzināšanu, mitrināšanu, plēves piesegšanu, tehnoloģisko un deformācijas šuvju izveidi, ieliekamo detaļu iebetonēšanu, ja nepieciešams/ Pile cap , Concrete C40/50 whith crystallizing additive SHOMBURG BETOCRETE-CP-360-WP, concrete with concrete delivery, pumping, vibrating, leveling, wetting, covering with film, creating technological and deformation joints, concreting of insert parts, if necessary | D41: m3 | E41: 25.08
A42: =A41+1 -> 23 | C42: Režģogu stiegrošana un palīgmateriāli (distanceri, sienamās stieples, konusi, uzgriežņi u.c.), stiegrojums B500B / Sheet pile cap beam reinforcement and consumables (spacers, wall wires, cones, bolts etc.), reinforcement B500B | D42: t | E42: 256.75
C44: Pandusa monolītā dzelzsbetona plātne/ Ramp reinforced concrete foundation structures | D44: m2 | E44: 424.27
A45: =A42+1 -> 24 | C45: Veidņu (apjoms precizējams veidņu izklājumā) , tsk. (palīgmateriāli (kokmateriāli, saplāksnis, stiprinājumi, caurlītes, konusi, aizbāžņi, eļļa, plēve) montāža, noma, demontāža režģogiem/ Formwork (volume to be specified in the formwork layout), incl. (auxiliary materials (timber, plywood, fasteners, tubes, cones, plugs, oil, film) assembly, rental, dismantling | D45: kpl | E45: 1
A46: =A45+1 -> 25 | C46: Pamatnes betonēšana b=300 mm Betons C40/50 ar kristalizējošu piedevu SHOMBURG BETOCRETE-CP-360-WP, betons ar betona piegādi, sūknēšanu, vibrēšanu, līdzināšanu, mitrināšanu, plēves piesegšanu, tehnoloģisko un deformācijas šuvju izveidi, ieliekamo detaļu iebetonēšanu, ja nepieciešams /Reinforced concrete ramp 300 mm, Concrete C40/50 whith crystallizing additive SHOMBURG BETOCRETE-CP-360-WP, concrete with concrete delivery, pumping, vibrating, leveling, wetting, covering with film, creating technological and deformation joints, concreting of insert parts, if necessary | D46: m3 | E46: 127.28
A47: =A46+1 -> 26 | C47: Sijas pandusa zonā betonēšana Betons C40/50 ar kristalizējošu piedevu SHOMBURG BETOCRETE-CP-360-WP , betons ar betona piegādi, sūknēšanu, vibrēšanu, līdzināšanu, mitrināšanu, plēves piesegšanu, tehnoloģisko un deformācijas šuvju izveidi, ieliekamo detaļu iebetonēšanu, ja nepieciešams/Reinforced concrete ramp area beams, Concrete C40/50 whith crystallizing additive SHOMBURG BETOCRETE-CP-360-WP, concrete with concrete delivery, pumping, vibrating, leveling, wetting, covering with film, creating technological and deformation joints, concreting of insert parts, if necessary | D47: m3 | E47: 6.93
A48: =A47+1 -> 27 | C48: Pamatnes stiegrošana, t. sk palīgmateriāli (distanceri, sienamās stieples, konusi, uzgriežņi u.c.), stiegrojums B500B / Slab reinforcement and consumables (spacers, wall wires, cones, bolts etc.), reinforcement B500B | D48: t | E48: 21.47
C50: Izmaksas kopā, t. sk. darba devēja sociālais nodoklis (%) /Total costs, including employer's social tax (%) | L50: =SUM($L$13:L49) -> 0 | M50: =SUM($M$13:M49) -> 0 | N50: =SUM($N$13:N49) -> 0 | O50: =SUM($O$13:O49) -> 0 | P50: =SUM($P$13:P49) -> 0

Sheet 1-3S
F1: Lokālā tāme Nr./Local estimate No | G1: 1-3
F2: Nesošās sienas un kolonnas/ Load-bearing walls, columns
A4: =KS!C4 -> Būves nosaukums/Building: Daudzīvokļu ēka / Residental building C2-10
A5: =KS!C5 -> Objekta nosaukums/Object: Dzīvojamās ēkas C2-10 jaunbūve/ Residential building C2-10
A6: =KS!C6 -> Objekta adrese/Object adress: Andrejostas iela 35, Rīga, LV-1045 | M6: Tāmes izmaksas | O6: 0
P8: Tāme sastādīta/Date _____. gada ____. ____________
F10: Vienības izmaksas/Unit rate | N10: Kopā uz visu apjomu/Total amount
A11: N.p.k./No | B11: Kods*/Code | C11: Būvdarbu nosaukums/Description of the construction work | D11: Mērvienība/ Unit | E11: Daudzums/ Quantity | F11: laika norma (c/h)/time rate (w/h) | G11: darba samaksas likme* (euro/h)/labour wage rate (euro/h)* | H11: darba alga/ salary | I11: būvizstrādājumi/ materials | J11: mehānismi/ mechanisms | K11: kopā/ total | L11: darbietilpība (c/h)/labor (w/h) | M11: darba alga/ salary | N11: būvizstrādājumi/ materials | O11: mehānismi/ mechanisms | P11: summa/ Total
A12: 1 | B12: 2 | C12: 3 | D12: 4 | E12: 5 | F12: =E12+1 -> 6 | G12: =F12+1 -> 7 | H12: =G12+1 -> 8 | I12: =H12+1 -> 9 | J12: =I12+1 -> 10 | K12: =J12+1 -> 11 | L12: =K12+1 -> 12 | M12: =L12+1 -> 13 | ... P12: =O12+1 -> 16
A14: 1 | C14: Detalizācijas rasējumu izstrāde saliekamajām DzKD / Development of detailed drawings for prefabricated DzKD | D14: kpl | E14: 1
C15: Sienas/Walls
C16: Dūmu šahtu konstrukcijas / Smoke shaft structures
C17: Monolīta dzelzsbetona siena / Reinforced concrete wall, b=160mm
A18: =A14+1 -> 2 | C18: Veidņu (apjoms precizējams veidņu izklājumā) , tsk. (palīgmateriāli (kokmateriāli, saplāksnis, stiprinājumi, caurlītes, konusi, aizbāžņi, eļļa, plēve) montāža, noma, demontāža/ Formwork (volume to be specified in the formwork layout), incl. (auxiliary materials (timber, plywood, fasteners, tubes, cones, plugs, oil, film) assembly, rental, dismantling | D18: m2 | E18: 46.88
A19: =A18+1 -> 3 | C19: Sienu betonēšana Betons C40/50, betons ar betona piegādi, sūknēšanu, vibrēšanu, līdzināšanu, mitrināšanu, plēves piesegšanu, tehnoloģisko un deformācijas šuvju izveidi, ieliekamo detaļu iebetonēšanu, ja nepieciešams/ Reinforced concrete wall, Concrete C40/50, concrete with concrete delivery, pumping, vibrating, leveling, wetting, covering with film, creating technological and deformation joints, concreting of insert parts, if necessary | D19: m3 | E19: 3.75
A20: =A19+1 -> 4 | C20: Sienu stiegrošana un palīgmateriāli (distanceri, sienamās stieples, konusi, uzgriežņi u.c.), stiegrojums B500B / Wall reinforcement and consumables (spacers, wall wires, cones, bolts etc.), reinforcement B500B | D20: t | E20: 0.53
C21: Monolītā dzelzsbetona sienas / Reinforced concrete walls
C22: Monolīta dzelzsbetona siena / Reinforced concrete wall, b=180mm
A23: =A20+1 -> 5 | C23: Veidņu (apjoms precizējams veidņu izklājumā) , tsk. (palīgmateriāli (kokmateriāli, saplāksnis, stiprinājumi, caurlītes, konusi, aizbāžņi, eļļa, plēve) montāža, noma, demontāža/ Formwork (volume to be specified in the formwork layout), incl. (auxiliary materials (timber, plywood, fasteners, tubes, cones, plugs, oil, film) assembly, rental, dismantling | D23: m2 | E23: 9.11
A24: =A23+1 -> 6 | C24: Sienu betonēšana Betons C40/50 , betons ar betona piegādi, sūknēšanu, vibrēšanu, līdzināšanu, mitrināšanu, plēves piesegšanu, tehnoloģisko un deformācijas šuvju izveidi, ieliekamo detaļu iebetonēšanu, ja nepieciešams/ Reinforced concrete wall, Concrete C40/50, concrete with concrete delivery, pumping, vibrating, leveling, wetting, covering with film, creating technological and deformation joints, concreting of insert parts, if necessary | D24: m3 | E24: 0.82
A25: =A24+1 -> 7 | C25: Sienu stiegrošana un palīgmateriāli (distanceri, sienamās stieples, konusi, uzgriežņi u.c.), stiegrojums B500B / Wall reinforcement and consumables (spacers, wall wires, cones, bolts etc.), reinforcement B500B | D25: t | E25: 0.12
C26: Monolīta dzelzsbetona siena / Reinforced concrete wall, b=200mm
A27: =A25+1 -> 8 | C27: Veidņu (apjoms precizējams veidņu izklājumā) , tsk. (palīgmateriāli (kokmateriāli, saplāksnis, stiprinājumi, caurlītes, konusi, aizbāžņi, eļļa, plēve) montāža, noma, demontāža/ Formwork (volume to be specified in the formwork layout), incl. (auxiliary materials (timber, plywood, fasteners, tubes, cones, plugs, oil, film) assembly, rental, dismantling | D27: m2 | E27: 731.9
A28: =A27+1 -> 9 | C28: Sienu betonēšana Betons C40/50 , betons ar betona piegādi, sūknēšanu, vibrēšanu, līdzināšanu, mitrināšanu, plēves piesegšanu, tehnoloģisko un deformācijas šuvju izveidi, ieliekamo detaļu iebetonēšanu, ja nepieciešams/ Reinforced concrete wall, Concrete C40/50, concrete with concrete delivery, pumping, vibrating, leveling, wetting, covering with film, creating technological and deformation joints, concreting of insert parts, if necessary | D28: m3 | E28: 73.19
A29: =A28+1 -> 10 | C29: Sienu stiegrošana un palīgmateriāli (distanceri, sienamās stieples, konusi, uzgriežņi u.c.), stiegrojums B500B / Wall reinforcement and consumables (spacers, wall wires, cones, bolts etc.), reinforcement B500B | D29: t | E29: 10.32
C30: Monolīta dzelzsbetona siena / Reinforced concrete wall, b=220mm
A31: =A29+1 -> 11 | C31: Veidņu (apjoms precizējams veidņu izklājumā) , tsk. (palīgmateriāli (kokmateriāli, saplāksnis, stiprinājumi, caurlītes, konusi, aizbāžņi, eļļa, plēve) montāža, noma, demontāža/ Formwork (volume to be specified in the formwork layout), incl. (auxiliary materials (timber, plywood, fasteners, tubes, cones, plugs, oil, film) assembly, rental, dismantling | D31: m2 | E31: 369.09
A32: =A31+1 -> 12 | C32: Sienu betonēšana Betons C40/50 , betons ar betona piegādi, sūknēšanu, vibrēšanu, līdzināšanu, mitrināšanu, plēves piesegšanu, tehnoloģisko un deformācijas šuvju izveidi, ieliekamo detaļu iebetonēšanu, ja nepieciešams/ Reinforced concrete wall, Concrete C40/50, concrete with concrete delivery, pumping, vibrating, leveling, wetting, covering with film, creating technological and deformation joints, concreting of insert parts, if necessary | D32: m3 | E32: 40.6
A33: =A32+1 -> 13 | C33: Sienu stiegrošana un palīgmateriāli (distanceri, sienamās stieples, konusi, uzgriežņi u.c.), stiegrojums B500B / Wall reinforcement and consumables (spacers, wall wires, cones, bolts etc.), reinforcement B500B | D33: t | E33: 5.72
C34: Monolīta dzelzsbetona siena / Reinforced concrete wall, b=250mm
A35: =A33+1 -> 14 | C35: Veidņu (apjoms precizējams veidņu izklājumā) , tsk. (palīgmateriāli (kokmateriāli, saplāksnis, stiprinājumi, caurlītes, konusi, aizbāžņi, eļļa, plēve) montāža, noma, demontāža/ Formwork (volume to be specified in the formwork layout), incl. (auxiliary materials (timber, plywood, fasteners, tubes, cones, plugs, oil, film) assembly, rental, dismantling | D35: m2 | E35: 1630.16
A36: =A35+1 -> 15 | C36: Sienu betonēšana Betons C40/50 , betons ar betona piegādi, sūknēšanu, vibrēšanu, līdzināšanu, mitrināšanu, plēves piesegšanu, tehnoloģisko un deformācijas šuvju izveidi, ieliekamo detaļu iebetonēšanu, ja nepieciešams/ Reinforced concrete wall, Concrete C40/50, concrete with concrete delivery, pumping, vibrating, leveling, wetting, covering with film, creating technological and deformation joints, concreting of insert parts, if necessary | D36: m3 | E36: 203.77
A37: =A36+1 -> 16 | C37: Sienu stiegrošana un palīgmateriāli (distanceri, sienamās stieples, konusi, uzgriežņi u.c.), stiegrojums B500B / Wall reinforcement and consumables (spacers, wall wires, cones, bolts etc.), reinforcement B500B | D37: t | E37: 28.73
C38: Monolītā dzelzsbetona siena / Reinforced concrete wall, b=300mm
A39: =A37+1 -> 17 | C39: Veidņu (apjoms precizējams veidņu izklājumā) , tsk. (palīgmateriāli (kokmateriāli, saplāksnis, stiprinājumi, caurlītes, konusi, aizbāžņi, eļļa, plēve) montāža, noma, demontāža/ Formwork (volume to be specified in the formwork layout), incl. (auxiliary materials (timber, plywood, fasteners, tubes, cones, plugs, oil, film) assembly, rental, dismantling | D39: m2 | E39: 1330
A40: =A39+1 -> 18 | C40: Sienu betonēšana Betons C40/50 ar kristalizējošu piedevu SHOMBURG BETOCRETE-CP-360-WP, betons ar betona piegādi, sūknēšanu, vibrēšanu, līdzināšanu, mitrināšanu, plēves piesegšanu, tehnoloģisko un deformācijas šuvju izveidi, ieliekamo detaļu iebetonēšanu, ja nepieciešams/ Reinforced concrete wall, Concrete C40/50 whith crystallizing additive SHOMBURG BETOCRETE-CP-360-WP, concrete with concrete delivery, pumping, vibrating, leveling, wetting, covering with film, creating technological and deformation joints, concreting of insert parts, if necessary | D40: m3 | E40: 199.5
A41: =A40+1 -> 19 | C41: Sienu stiegrošana un palīgmateriāli (distanceri, sienamās stieples, konusi, uzgriežņi u.c.), stiegrojums B500B / Wall reinforcement and consumables (spacers, wall wires, cones, bolts etc.), reinforcement B500B | D41: t | E41: 28.13
C43: Saliekamās dz/b sienas/ Precast concrete walls
A44: =A41+1 -> 20 | C44: Saliekama dzelzsbetona vienslāņa sienas paneļa b=150mm montāža un šuvju hermetizācija ; montāžas un hermetizācijas materiāli (hermētiķis, šuvju aukla, smalkgraudains šuvju betons , stiegrojums), t.sk. stiprinājumi, ieliekamās detaļas) Betons; Stiegrojums B500B; bruto apjoms / Prefabricated reinforced concrete single-layer wall panel b=150mm assembly and joint sealing; assembly and sealing materials (sealant, joint cord, fine-grained joint concrete, reinforcement), incl. fasteners, insert parts) Concrete; Reinforcement B500B; gross volume | D44: m2 | E44: 1338.4
A45: =A44+1 -> 21 | C45: Saliekama dzelzsbetona vienslāņa sienas paneļa b=180mm montāža un šuvju hermetizācija ; montāžas un hermetizācijas materiāli (hermētiķis, šuvju aukla, smalkgraudains šuvju betons , stiegrojums), t.sk. stiprinājumi, ieliekamās detaļas) Betons ; Stiegrojums B500B; bruto apjoms / Prefabricated reinforced concrete single-layer wall panel b=180mm assembly and joint sealing; assembly and sealing materials (sealant, joint cord, fine-grained joint concrete, reinforcement), incl. fasteners, insert parts) Concrete; Reinforcement B500B; gross volume | D45: m2 | E45: 244.56
A46: =A45+1 -> 22 | C46: Saliekama dzelzsbetona vienslāņa sienas paneļa b=200mm montāža un šuvju hermetizācija ; montāžas un hermetizācijas materiāli (hermētiķis, šuvju aukla, smalkgraudains šuvju betons , stiegrojums), t.sk. stiprinājumi, ieliekamās detaļas) Betons; Stiegrojums B500B; bruto apjoms / Prefabricated reinforced concrete single-layer wall panel b=200mm assembly and joint sealing; assembly and sealing materials (sealant, joint cord, fine-grained joint concrete, reinforcement), incl. fasteners, insert parts) Concrete; Reinforcement B500B; gross volume | D46: m2 | E46: 2286.15
A47: =A46+1 -> 23 | C47: Saliekama dzelzsbetona vienslāņa sienas paneļa b=220mm montāža un šuvju hermetizācija ; montāžas un hermetizācijas materiāli (hermētiķis, šuvju aukla, smalkgraudains šuvju betons , stiegrojums), t.sk. stiprinājumi, ieliekamās detaļas) Betons; Stiegrojums B500B; bruto apjoms / Prefabricated reinforced concrete single-layer wall panel b=220mm assembly and joint sealing; assembly and sealing materials (sealant, joint cord, fine-grained joint concrete, reinforcement), incl. fasteners, insert parts) Concrete; Reinforcement B500B; gross volume | D47: m2 | E47: 1348.61
A48: =A47+1 -> 24 | C48: Saliekama dzelzsbetona vienslāņa sienas paneļa b=240mm montāža un šuvju hermetizācija ; montāžas un hermetizācijas materiāli (hermētiķis, šuvju aukla, smalkgraudains šuvju betons , stiegrojums), t.sk. stiprinājumi, ieliekamās detaļas) Betons; Stiegrojums B500B; bruto apjoms / Prefabricated reinforced concrete single-layer wall panel b=240mm assembly and joint sealing; assembly and sealing materials (sealant, joint cord, fine-grained joint concrete, reinforcement), incl. fasteners, insert parts) Concrete; Reinforcement B500B; gross volume | D48: m2 | E48: 24.54
A49: =A48+1 -> 25 | C49: Saliekama siltināta dzelzsbetona trīsslāņu 110/330/200 sienas paneļa montāža un šuvju hermetizācija ; montāžas un hermetizācijas materiāli (hermētiķis, šuvju aukla, smalkgraudains šuvju betons, stiegrojums), t.sk. stiprinājumi, ieliekamās detaļas) Betons; Stiegrojums B500B; Siltumizolācija (piem. PAROC COS 5gt, λ=0,035 W/mK), ugunsreakcijas klase ne zemāk kā B-s1,d0 180-330 mm; gala apdari skat. AR daļā bruto apjoms / Prefabricated reinforced concrete three-layer wall panel 110/330/200 assembly and joint sealing; assembly and sealing materials (sealant, joint cord, fine-grained joint concrete, reinforcement), incl. fasteners, insert parts) Concrete; Reinforcement B500B; Thermal insulation (e.g. PAROC COS 5gt, λ=0.035 W/mK), fire reaction class not lower than B-s1,d0 180-330 mm; finnishings see AR part gross volume | D49: m2 | E49: 2337.87
A50: =A49+1 -> 26 | C50: Saliekama siltināta dzelzsbetona trīsslāņu 110/330/220 sienas paneļa montāža un šuvju hermetizācija ; montāžas un hermetizācijas materiāli (hermētiķis, šuvju aukla, smalkgraudains šuvju betons, stiegrojums), t.sk. stiprinājumi, ieliekamās detaļas) Betons; Stiegrojums B500B; Siltumizolācija (piem. PAROC COS 5gt, λ=0,035 W/mK), ugunsreakcijas klase ne zemāk kā B-s1,d0 180-330 mm bruto apjoms / Prefabricated reinforced concrete three-layer wall panel 110/330/220 assembly and joint sealing; assembly and sealing materials (sealant, joint cord, fine-grained joint concrete, reinforcement), incl. fasteners, insert parts) Concrete; Reinforcement B500B; Thermal insulation (e.g. PAROC COS 5gt, λ=0.035 W/mK), fire reaction class not lower than B-s1,d0 180-330 mm gross volume | D50: m2 | E50: 742.66
C51: CLT sienas / CLT wall
A52: 26.1 | C52: CLT konstrukciju (CLT_sienas_120mm) montāža (kokmateriāls, montāžas elementi (dībeļskrūves, enkuri, leņķdzelži, naglas, skavas, būvkalumi, enkurbultas, skrūves, stiprinājumi, lentas u.c), t.sk. palīgmateriāli (akmens vate, ruberoīds, pergamīns, izolācijas lentas konstrukciju izolācijai no mūra vai metāla, u.c.) / Assembly of CLT structures (beams CLT_Wall_120mm) (timber, assembly elements (dowels, anchors, angle irons, nails, clamps, forgings, anchor bolts, screws, fasteners, tapes, etc.), including auxiliary materials (rock wool, roofing felt, glassine, insulation tapes for insulating structures made of masonry or metal, etc.) | D52: m2 | E52: 95.26
C54: Kolonnas /Columns
C55: Monolītā dzelzsbetona kolonnas / Reinforced concrete columns
C56: Monolītā dzelzsbetona kolonna / Cast in place concrete column 400x400 mm
A57: =A50+1 -> 27 | C57: Veidņu (apjoms precizējams veidņu izklājumā) , tsk. (palīgmateriāli (kokmateriāli, saplāksnis, stiprinājumi, caurlītes, konusi, aizbāžņi, eļļa, plēve) montāža, noma, demontāža kolonnām/ Formwork (volume to be specified in the formwork layout), incl. (auxiliary materials (timber, plywood, fasteners, tubes, cones, plugs, oil, film) assembly, rental, dismantling (column) | D57: m2 | E57: 129.8
A58: =A57+1 -> 28 | C58: Kolonnu betonēšana Betons C40/50, betons ar betona piegādi, sūknēšanu, vibrēšanu, līdzināšanu, mitrināšanu, plēves piesegšanu, tehnoloģisko un deformācijas šuvju izveidi, ieliekamo detaļu iebetonēšanu, ja nepieciešams/ Reinforced concrete column, Concrete C40/50, concrete with concrete delivery, pumping, vibrating, leveling, wetting, covering with film, creating technological and deformation joints, concreting of insert parts, if necessary | D58: m3 | E58: 12.98
A59: =A58+1 -> 29 | C59: Kolonnu stiegrošana un palīgmateriāli (distanceri, sienamās stieples, konusi, uzgriežņi u.c.), stiegrojums B500B / Column reinforcement and consumables (spacers, wall wires, cones, bolts etc.), reinforcement B500B | D59: t | E59: 3.7
C60: Monolītā dzelzsbetona kolonna / Cast in place concrete column 450x450 mm
A61: =A59+1 -> 30 | C61: Veidņu (apjoms precizējams veidņu izklājumā) , tsk. (palīgmateriāli (kokmateriāli, saplāksnis, stiprinājumi, caurlītes, konusi, aizbāžņi, eļļa, plēve) montāža, noma, demontāža kolonnām/ Formwork (volume to be specified in the formwork layout), incl. (auxiliary materials (timber, plywood, fasteners, tubes, cones, plugs, oil, film) assembly, rental, dismantling (column) | D61: m2 | E61: 232.18
A62: =A61+1 -> 31 | C62: Kolonnu betonēšana Betons C40/50, betons ar betona piegādi, sūknēšanu, vibrēšanu, līdzināšanu, mitrināšanu, plēves piesegšanu, tehnoloģisko un deformācijas šuvju izveidi, ieliekamo detaļu iebetonēšanu, ja nepieciešams/ Reinforced concrete column, Concrete C40/50, concrete with concrete delivery, pumping, vibrating, leveling, wetting, covering with film, creating technological and deformation joints, concreting of insert parts, if necessary | D62: m3 | E62: 26.12
A63: =A62+1 -> 32 | C63: Kolonnu stiegrošana un palīgmateriāli (distanceri, sienamās stieples, konusi, uzgriežņi u.c.), stiegrojums B500B / Column reinforcement and consumables (spacers, wall wires, cones, bolts etc.), reinforcement B500B | D63: t | E63: 7.44
C64: Monolītā dzelzsbetona kolonna / Cast in place concrete column 500x500 mm
A65: =A63+1 -> 33 | C65: Veidņu (apjoms precizējams veidņu izklājumā) , tsk. (palīgmateriāli (kokmateriāli, saplāksnis, stiprinājumi, caurlītes, konusi, aizbāžņi, eļļa, plēve) montāža, noma, demontāža kolonnām/ Formwork (volume to be specified in the formwork layout), incl. (auxiliary materials (timber, plywood, fasteners, tubes, cones, plugs, oil, film) assembly, rental, dismantling (column) | D65: m2 | E65: 276.16
A66: =A65+1 -> 34 | C66: Kolonnu betonēšana Betons C40/50 ar kristalizējošu piedevu SHOMBURG BETOCRETE-CP-360-WP, betons ar betona piegādi, sūknēšanu, vibrēšanu, līdzināšanu, mitrināšanu, plēves piesegšanu, tehnoloģisko un deformācijas šuvju izveidi, ieliekamo detaļu iebetonēšanu, ja nepieciešams/ Reinforced concrete column, Concrete C40/50 whith crystallizing additive SHOMBURG BETOCRETE-CP-360-WP, concrete with concrete delivery, pumping, vibrating, leveling, wetting, covering with film, creating technological and deformation joints, concreting of insert parts, if necessary | D66: m3 | E66: 34.52
A67: =A66+1 -> 35 | C67: Kolonnu stiegrošana un palīgmateriāli (distanceri, sienamās stieples, konusi, uzgriežņi u.c.), stiegrojums B500B / Column reinforcement and consumables (spacers, wall wires, cones, bolts etc.), reinforcement B500B | D67: t | E67: 9.84
C68: Monolītā dzelzsbetona kolonna / Cast in place concrete column 500x600 mm
A69: =A67+1 -> 36 | C69: Veidņu (apjoms precizējams veidņu izklājumā) , tsk. (palīgmateriāli (kokmateriāli, saplāksnis, stiprinājumi, caurlītes, konusi, aizbāžņi, eļļa, plēve) montāža, noma, demontāža kolonnām/ Formwork (volume to be specified in the formwork layout), incl. (auxiliary materials (timber, plywood, fasteners, tubes, cones, plugs, oil, film) assembly, rental, dismantling (column) | D69: m2 | E69: 102.48
A70: =A69+1 -> 37 | C70: Kolonnu betonēšana Betons C40/50 ar kristalizējošu piedevu SHOMBURG BETOCRETE-CP-360-WP, betons ar betona piegādi, sūknēšanu, vibrēšanu, līdzināšanu, mitrināšanu, plēves piesegšanu, tehnoloģisko un deformācijas šuvju izveidi, ieliekamo detaļu iebetonēšanu, ja nepieciešams/ Reinforced concrete column, Concrete C40/50 whith crystallizing additive SHOMBURG BETOCRETE-CP-360-WP, concrete with concrete delivery, pumping, vibrating, leveling, wetting, covering with film, creating technological and deformation joints, concreting of insert parts, if necessary | D70: m3 | E70: 16.77
A71: =A70+1 -> 38 | C71: Kolonnu stiegrošana un palīgmateriāli (distanceri, sienamās stieples, konusi, uzgriežņi u.c.), stiegrojums B500B / Column reinforcement and consumables (spacers, wall wires, cones, bolts etc.), reinforcement B500B | D71: t | E71: 4.78
C72: Monolītā dzelzsbetona kolonna / Cast in place concrete column 600x600 mm
A73: =A71+1 -> 39 | C73: Veidņu (apjoms precizējams veidņu izklājumā) , tsk. (palīgmateriāli (kokmateriāli, saplāksnis, stiprinājumi, caurlītes, konusi, aizbāžņi, eļļa, plēve) montāža, noma, demontāža kolonnām/ Formwork (volume to be specified in the formwork layout), incl. (auxiliary materials (timber, plywood, fasteners, tubes, cones, plugs, oil, film) assembly, rental, dismantling (column) | D73: m2 | E73: 66.27
A74: =A73+1 -> 40 | C74: Kolonnu betonēšana Betons C40/50, betons ar betona piegādi, sūknēšanu, vibrēšanu, līdzināšanu, mitrināšanu, plēves piesegšanu, tehnoloģisko un deformācijas šuvju izveidi, ieliekamo detaļu iebetonēšanu, ja nepieciešams/ Reinforced concrete column, Concrete C40/50, concrete with concrete delivery, pumping, vibrating, leveling, wetting, covering with film, creating technological and deformation joints, concreting of insert parts, if necessary | D74: m3 | E74: 9.94
A75: =A74+1 -> 41 | C75: Kolonnu stiegrošana un palīgmateriāli (distanceri, sienamās stieples, konusi, uzgriežņi u.c.), stiegrojums B500B / Column reinforcement and consumables (spacers, wall wires, cones, bolts etc.), reinforcement B500B | D75: t | E75: 2.83
C76: Monolītā dzelzsbetona kolonna / Cast in place concrete column 550x1000mm
A77: =A75+1 -> 42 | C77: Veidņu (apjoms precizējams veidņu izklājumā) , tsk. (palīgmateriāli (kokmateriāli, saplāksnis, stiprinājumi, caurlītes, konusi, aizbāžņi, eļļa, plēve) montāža, noma, demontāža kolonnām/ Formwork (volume to be specified in the formwork layout), incl. (auxiliary materials (timber, plywood, fasteners, tubes, cones, plugs, oil, film) assembly, rental, dismantling (column) | D77: m2 | E77: 33.67
A78: =A77+1 -> 43 | C78: Kolonnu betonēšana Betons C40/50, betons ar betona piegādi, sūknēšanu, vibrēšanu, līdzināšanu, mitrināšanu, plēves piesegšanu, tehnoloģisko un deformācijas šuvju izveidi, ieliekamo detaļu iebetonēšanu, ja nepieciešams/ Reinforced concrete column, Concrete C40/50, concrete with concrete delivery, pumping, vibrating, leveling, wetting, covering with film, creating technological and deformation joints, concreting of insert parts, if necessary | D78: m3 | E78: 3.91
A79: =A78+1 -> 44 | C79: Kolonnu stiegrošana un palīgmateriāli (distanceri, sienamās stieples, konusi, uzgriežņi u.c.), stiegrojums B500B / Column reinforcement and consumables (spacers, wall wires, cones, bolts etc.), reinforcement B500B | D79: t | E79: 1.11
C80: Saliekamā dzelzsbetona kolonna / Precast concrete column 450x450mm
A81: =A79+1 -> 45 | C81: Saliekama dzelzsbetona kolonnas montāža; montāžas un hermetizācijas materiāli, t.sk. stiprinājumi, ieliekamās detaļas; stiegrojums B500B; (betons C40/50) / Precast reinforced concrete column assembly; assembly and sealing materials, incl. fasteners, insert parts; reinforcement B500B; (concrete C40/50) | D81: gb | E81: 1
C82: Kopējais garums / Total length | D82: m | E82: 3.37
C83: Betons C40/50 / Concrete C40/50 | D83: m3 | E83: 0.68
C85: Izmaksas kopā, t. sk. darba devēja sociālais nodoklis (%) /Total costs, including employer's social tax (%) | L85: =SUM($L$13:L84) -> 0 | M85: =SUM($M$13:M84) -> 0 | N85: =SUM($N$13:N84) -> 0 | O85: =SUM($O$13:O84) -> 0 | P85: =SUM($P$13:P84) -> 0

Sheet 1-4T
F1: Lokālā tāme Nr./Local estimate No | G1: 1-4
F2: Tērauda konstrukcijas /Steel structures
A4: =KS!C4 -> Būves nosaukums/Building: Daudzīvokļu ēka / Residental building C2-10
A5: =KS!C5 -> Objekta nosaukums/Object: Dzīvojamās ēkas C2-10 jaunbūve/ Residential building C2-10
A6: =KS!C6 -> Objekta adrese/Object adress: Andrejostas iela 35, Rīga, LV-1045 | M6: Tāmes izmaksas | O6: 0
P8: Tāme sastādīta/Date _____. gada ____. ____________
F10: Vienības izmaksas/Unit rate | N10: Kopā uz visu apjomu/Total amount
A11: N.p.k./No | B11: Kods*/Code | C11: Būvdarbu nosaukums/Description of the construction work | D11: Mērvienība/ Unit | E11: Daudzums/ Quantity | F11: laika norma (c/h)/time rate (w/h) | G11: darba samaksas likme* (euro/h)/labour wage rate (euro/h)* | H11: darba alga/ salary | I11: būvizstrādājumi/ materials | J11: mehānismi/ mechanisms | K11: kopā/ total | L11: darbietilpība (c/h)/labor (w/h) | M11: darba alga/ salary | N11: būvizstrādājumi/ materials | O11: mehānismi/ mechanisms | P11: summa/ Total
A12: 1 | B12: 2 | C12: 3 | D12: 4 | E12: 5 | F12: =E12+1 -> 6 | G12: =F12+1 -> 7 | H12: =G12+1 -> 8 | I12: =H12+1 -> 9 | J12: =I12+1 -> 10 | K12: =J12+1 -> 11 | L12: =K12+1 -> 12 | M12: =L12+1 -> 13 | ... P12: =O12+1 -> 16
C14: Tērauda konstrukciju izgatavošana un montāža, apstrāde (attīrīšana, gruntēšana, krāsošana, pretkorozijas aizsardzība) saskaņā ar projektu, t.sk. palīgmateriāli, stiprinājumi, loksnes, plātnes, skrūves, uzgriežni, ieliekamās detaļas, detalizācijas rasējumu izstrāde / Production and assembly of steel structures, processing (cleaning, priming, painting, corrosion protection) according to the project, including auxiliary materials, fasteners, sheets, plates, screws, nuts, insert parts, development of detail drawings
A15: 1 | C15: Detalizācijas rasējumu izstrāde MKD/Development of detailed drawings for steel constructions | D15: kpl | E15: 1
A16: =A15+1 -> 2 | C16: Tērauda izstrādājumu aptīšana ar sietu, apbetonēšana Betons C30/37 vai pabetonējumi, smalkgraudains betons C35/45/Concreting of steel products Concrete C30/37 or concrete overlays, fine-grained concrete C35/45 | D16: kpl | E16: 1
C17: Tērauda kolonnas / Steel columns
A18: =A16+1 -> 3 | C18: Tērauda kolonnu profils / Steel column profile SHS60x60x4 L=20,35 m | D18: t | E18: 0.14
A19: =A18+1 -> 4 | C19: Tērauda kolonnu profils / Steel column profile SHS150x150x5 L=45,73 m | D19: t | E19: 1.04
A20: =A19+1 -> 5 | C20: +15% metīzēm un loksnēm / +15% for welds and plates | D20: t | E20: 0.177
C21: Tērauda sijas / Steel beams
A22: =A20+1 -> 6 | C22: Tērauda siju profils / Steel beam profile HEA 220 L=63,88 m | D22: t | E22: 3.09
A23: 6.1 | C23: Tērauda siju profils / Steel beam profile HEA 320 L=77,03 m | D23: t | E23: 7.14
A24: =A22+1 -> 7 | C24: Tērauda siju profils / Steel beam profile HEA 500 L=28,38 m | D24: t | E24: 4.26
A25: =A24+1 -> 8 | C25: Tērauda siju profils / Steel beam profile HQ-200-230-110-110-10-10-6 L=38,04 m | D25: t | E25: 2.6
A26: =A25+1 -> 9 | C26: Tērauda siju profils / Steel beam profile HQ-200-230-110-110-15-10-6 L=5,77 m | D26: t | E26: 0.43
A27: =A26+1 -> 10 | C27: Tērauda siju profils / Steel beam profile HQ-200-230-110-20-10-10-6 L=34,24 m | D27: t | E27: 2.1
A28: =A27+1 -> 11 | C28: Tērauda siju profils / Steel beam profile HQ-200-230-110-20-15-10-6 L=14,3 m | D28: t | E28: 0.98
A29: =A28+1 -> 12 | C29: Tērauda siju profils / Steel beam profile HQ-200-277-110-110-12-12-6 L=13,65 m | D29: t | E29: 1.11
A30: =A29+1 -> 13 | C30: Tērauda siju profils / Steel beam profile HQ-200-330-110-20-10-10-6 L=7,43 m | D30: t | E30: 0.53
A31: =A30+1 -> 14 | C31: Tērauda siju profils / Steel beam profile HQ-200-332-110-110-10-12-6 L=4,55 m | D31: t | E31: 0.38
A32: =A31+1 -> 15 | C32: Tērauda siju profils / Steel beam profile HQ-220-235-110-20-25-15-8 L=13,02 m | D32: t | E32: 1.42
A33: =A32+1 -> 16 | C33: Tērauda siju profils / Steel beam profile HQ-250-230-110-110-15-10-6 L=5,54 m | D33: t | E33: 0.47
A34: =A33+1 -> 17 | C34: Tērauda siju profils / Steel beam profile HQ-250-335-110-110-25-15-8 L=16,67 m | D34: t | E34: 2.36
A35: =A34+1 -> 18 | C35: Tērauda siju profils / Steel beam profile HQ-300-277-110-110-12-12-6 L=21,93 m | D35: t | E35: 2.22
A36: =A35+1 -> 19 | C36: Tērauda siju profils / Steel beam profile HQ-300-285-110-110-25-20-8 L=83,16 m | D36: t | E36: 14.13
... A63: =A62+1 -> 46 | C63: +15% metīzēm un loksnēm / +15% for welds and plates | D63: t | E63: 17.402
C64: Tērauda režģis / Steel grating
A65: =A63+1 -> 47 | C65: Tērauda rezģa SP 34x38/50x3 montāža, t.sk. stiprinājumi, palīgmateriāli / Steel grating assembly, incl. fasteners, auxiliary materials | D65: m2 | E65: 3.66
C67: Izmaksas kopā, t. sk. darba devēja sociālais nodoklis (%) /Total costs, including employer's social tax (%) | L67: =SUM($L$13:L66) -> 0 | M67: =SUM($M$13:M66) -> 0 | N67: =SUM($N$13:N66) -> 0 | O67: =SUM($O$13:O66) -> 0 | P67: =SUM($P$13:P66) -> 0

Sheet 1-5P
F1: Lokālā tāme Nr./Local estimate No | G1: 1-5
F2: Pārsegumu, siju montāža / Slabs, beams
A4: =KS!C4 -> Būves nosaukums/Building: Daudzīvokļu ēka / Residental building C2-10
A5: =KS!C5 -> Objekta nosaukums/Object: Dzīvojamās ēkas C2-10 jaunbūve/ Residential building C2-10
A6: =KS!C6 -> Objekta adrese/Object adress: Andrejostas iela 35, Rīga, LV-1045 | M6: Tāmes izmaksas | O6: 0
P8: Tāme sastādīta/Date _____. gada ____. ____________
F10: Vienības izmaksas/Unit rate | N10: Kopā uz visu apjomu/Total amount
A11: N.p.k./No | B11: Kods*/Code | C11: Būvdarbu nosaukums/Description of the construction work | D11: Mērvienība/ Unit | E11: Daudzums/ Quantity | F11: laika norma (c/h)/time rate (w/h) | G11: darba samaksas likme* (euro/h)/labour wage rate (euro/h)* | H11: darba alga/ salary | I11: būvizstrādājumi/ materials | J11: mehānismi/ mechanisms | K11: kopā/ total | L11: darbietilpība (c/h)/labor (w/h) | M11: darba alga/ salary | N11: būvizstrādājumi/ materials | O11: mehānismi/ mechanisms | P11: summa/ Total
A12: 1 | B12: 2 | C12: 3 | D12: 4 | E12: 5 | F12: =E12+1 -> 6 | G12: =F12+1 -> 7 | H12: =G12+1 -> 8 | I12: =H12+1 -> 9 | J12: =I12+1 -> 10 | K12: =J12+1 -> 11 | L12: =K12+1 -> 12 | M12: =L12+1 -> 13 | ... P12: =O12+1 -> 16
A14: 1 | C14: Detalizācijas rasējumu izstrāde saliekamajām DzKD / Development of detailed drawings for prefabricated DzKD | D14: kpl | E14: 1
C15: Pārsegumi /Slabs
C16: Dūmu šahtu konstrukcijas / Smoke shaft structures
C17: Monolīta dzelzsbetona plātne / Reinforced concrete slab, h=200mm
A18: =A14+1 -> 2 | C18: Veidņu (apjoms precizējams veidņu izklājumā) , tsk. (palīgmateriāli (kokmateriāli, saplāksnis, stiprinājumi, caurlītes, konusi, aizbāžņi, eļļa, plēve), stutu montāža/noma/demontāža (pārsegums)/Formwork (volume to be specified in the formwork layout), incl. (auxiliary materials (timber, plywood, fasteners, tubes, cones, plugs, oil, film), studs assembly / rental / dismantling (slab) | D18: m2 | E18: 14.25
A19: =A18+1 -> 3 | C19: Pārseguma betonēšana Betons C40/50, betons ar betona piegādi, sūknēšanu, vibrēšanu, līdzināšanu, mitrināšanu, plēves piesegšanu, tehnoloģisko un deformācijas šuvju izveidi, ieliekamo detaļu iebetonēšanu, ja nepieciešams/Reinforced concrete slab / Concrete C40/50, concrete with concrete delivery, pumping, vibrating, leveling, wetting, covering with film, creating technological and deformation joints, concreting of insert parts, if necessary | D19: m3 | E19: 2.59
A20: =A19+1 -> 4 | C20: Pārseguma stiegrošana, t. sk palīgmateriāli (distanceri, sienamās stieples, konusi, uzgriežņi u.c.), stiegrojums B500B/Slab reinforcement and consumables (spacers, wall wires, cones, bolts etc.), reinforcement B500B | D20: t | E20: 0.41
C21: Pārsegums 1. stāva līmenī / 1st floor slab
C22: Monolīta dzelzsbetona plātne / Reinforced concrete slab, h=250mm
A23: =A20+1 -> 5 | C23: Veidņu (apjoms precizējams veidņu izklājumā) , tsk. (palīgmateriāli (kokmateriāli, saplāksnis, stiprinājumi, caurlītes, konusi, aizbāžņi, eļļa, plēve), stutu montāža/noma/demontāža (pārsegums)/Formwork (volume to be specified in the formwork layout), incl. (auxiliary materials (timber, plywood, fasteners, tubes, cones, plugs, oil, film), studs assembly / rental / dismantling (slab) | D23: m2 | E23: 1206.79
A24: =A23+1 -> 6 | C24: Pārseguma betonēšana Betons C40/50, betons ar betona piegādi, sūknēšanu, vibrēšanu, līdzināšanu, mitrināšanu, plēves piesegšanu, tehnoloģisko un deformācijas šuvju izveidi, ieliekamo detaļu iebetonēšanu, ja nepieciešams/Reinforced concrete slab / Concrete C40/50, concrete with concrete delivery, pumping, vibrating, leveling, wetting, covering with film, creating technological and deformation joints, concreting of insert parts, if necessary | D24: m3 | E24: 274.27
A25: =A24+1 -> 7 | C25: Pārseguma stiegrošana, t. sk palīgmateriāli (distanceri, sienamās stieples, konusi, uzgriežņi u.c.), stiegrojums B500B/Slab reinforcement and consumables (spacers, wall wires, cones, bolts etc.), reinforcement B500B | D25: t | E25: 43.88
C26: Monolīta dzelzsbetona plātne / Reinforced concrete slab, h=300mm
A27: =A25+1 -> 8 | C27: Veidņu (apjoms precizējams veidņu izklājumā) , tsk. (palīgmateriāli (kokmateriāli, saplāksnis, stiprinājumi, caurlītes, konusi, aizbāžņi, eļļa, plēve), stutu montāža/noma/demontāža (pārsegums)/Formwork (volume to be specified in the formwork layout), incl. (auxiliary materials (timber, plywood, fasteners, tubes, cones, plugs, oil, film), studs assembly / rental / dismantling (slab) | D27: m2 | E27: 108.42
A28: =A27+1 -> 9 | C28: Pārseguma betonēšana Betons C40/50, betons ar betona piegādi, sūknēšanu, vibrēšanu, līdzināšanu, mitrināšanu, plēves piesegšanu, tehnoloģisko un deformācijas šuvju izveidi, ieliekamo detaļu iebetonēšanu, ja nepieciešams/Reinforced concrete slab / Concrete C40/50, concrete with concrete delivery, pumping, vibrating, leveling, wetting, covering with film, creating technological and deformation joints, concreting of insert parts, if necessary | D28: m3 | E28: 29.57
A29: =A28+1 -> 10 | C29: Pārseguma stiegrošana, t. sk palīgmateriāli (distanceri, sienamās stieples, konusi, uzgriežņi u.c.), stiegrojums B500B/Slab reinforcement and consumables (spacers, wall wires, cones, bolts etc.), reinforcement B500B | D29: t | E29: 4.73
C30: Monolīta dzelzsbetona plātne / Reinforced concrete slab, h=350mm
A31: =A29+1 -> 11 | C31: Veidņu (apjoms precizējams veidņu izklājumā) , tsk. (palīgmateriāli (kokmateriāli, saplāksnis, stiprinājumi, caurlītes, konusi, aizbāžņi, eļļa, plēve), stutu montāža/noma/demontāža (pārsegums)/Formwork (volume to be specified in the formwork layout), incl. (auxiliary materials (timber, plywood, fasteners, tubes, cones, plugs, oil, film), studs assembly / rental / dismantling (slab) | D31: m2 | E31: 1799.82
A32: =A31+1 -> 12 | C32: Pārseguma betonēšana Betons C40/50, betons ar betona piegādi, sūknēšanu, vibrēšanu, līdzināšanu, mitrināšanu, plēves piesegšanu, tehnoloģisko un deformācijas šuvju izveidi, ieliekamo detaļu iebetonēšanu, ja nepieciešams/Reinforced concrete slab / Concrete C40/50, concrete with concrete delivery, pumping, vibrating, leveling, wetting, covering with film, creating technological and deformation joints, concreting of insert parts, if necessary | D32: m3 | E32: 572.67
A33: =A32+1 -> 13 | C33: Pārseguma stiegrošana, t. sk palīgmateriāli (distanceri, sienamās stieples, konusi, uzgriežņi u.c.), stiegrojums B500B/Slab reinforcement and consumables (spacers, wall wires, cones, bolts etc.), reinforcement B500B | D33: t | E33: 91.63
C34: Pārsegums 2. stāva līmenī / 2nd floor slab
C35: Monolīta dzelzsbetona plātne / Reinforced concrete slab, h=250mm
A36: =A33+1 -> 14 | C36: Veidņu (apjoms precizējams veidņu izklājumā) , tsk. (palīgmateriāli (kokmateriāli, saplāksnis, stiprinājumi, caurlītes, konusi, aizbāžņi, eļļa, plēve), stutu montāža/noma/demontāža (pārsegums)/Formwork (volume to be specified in the formwork layout), incl. (auxiliary materials (timber, plywood, fasteners, tubes, cones, plugs, oil, film), studs assembly / rental / dismantling (slab) | D36: m2 | E36: 115.54
A37: =A36+1 -> 15 | C37: Pārseguma betonēšana Betons C40/50, betons ar betona piegādi, sūknēšanu, vibrēšanu, līdzināšanu, mitrināšanu, plēves piesegšanu, tehnoloģisko un deformācijas šuvju izveidi, ieliekamo detaļu iebetonēšanu, ja nepieciešams/Reinforced concrete slab / Concrete C40/50, concrete with concrete delivery, pumping, vibrating, leveling, wetting, covering with film, creating technological and deformation joints, concreting of insert parts, if necessary | D37: m3 | E37: 26.26
A38: =A37+1 -> 16 | C38: Pārseguma stiegrošana, t. sk palīgmateriāli (distanceri, sienamās stieples, konusi, uzgriežņi u.c.), stiegrojums B500B/Slab reinforcement and consumables (spacers, wall wires, cones, bolts etc.), reinforcement B500B | D38: t | E38: 3.97
C39: Monolīta dzelzsbetona plātne / Reinforced concrete slab, h=300mm
A40: =A38+1 -> 17 | C40: Veidņu (apjoms precizējams veidņu izklājumā) , tsk. (palīgmateriāli (kokmateriāli, saplāksnis, stiprinājumi, caurlītes, konusi, aizbāžņi, eļļa, plēve), stutu montāža/noma/demontāža (pārsegums)/Formwork (volume to be specified in the formwork layout), incl. (auxiliary materials (timber, plywood, fasteners, tubes, cones, plugs, oil, film), studs assembly / rental / dismantling (slab) | D40: m2 | E40: 1427.54
A41: =A40+1 -> 18 | C41: Pārseguma betonēšana Betons C40/50, betons ar betona piegādi, sūknēšanu, vibrēšanu, līdzināšanu, mitrināšanu, plēves piesegšanu, tehnoloģisko un deformācijas šuvju izveidi, ieliekamo detaļu iebetonēšanu, ja nepieciešams/Reinforced concrete slab / Concrete C40/50, concrete with concrete delivery, pumping, vibrating, leveling, wetting, covering with film, creating technological and deformation joints, concreting of insert parts, if necessary | D41: m3 | E41: 389.33
A42: =A41+1 -> 19 | C42: Pārseguma stiegrošana, t. sk palīgmateriāli (distanceri, sienamās stieples, konusi, uzgriežņi u.c.), stiegrojums B500B/Slab reinforcement and consumables (spacers, wall wires, cones, bolts etc.), reinforcement B500B | D42: t | E42: 58.79
C43: Monolīta dzelzsbetona plātne / Reinforced concrete slab, h=400mm
A44: =A42+1 -> 20 | C44: Veidņu (apjoms precizējams veidņu izklājumā) , tsk. (palīgmateriāli (kokmateriāli, saplāksnis, stiprinājumi, caurlītes, konusi, aizbāžņi, eļļa, plēve), stutu montāža/noma/demontāža (pārsegums)/Formwork (volume to be specified in the formwork layout), incl. (auxiliary materials (timber, plywood, fasteners, tubes, cones, plugs, oil, film), studs assembly / rental / dismantling (slab) | D44: m2 | E44: 87.26
A45: =A44+1 -> 21 | C45: Pārseguma betonēšana Betons C40/50, betons ar betona piegādi, sūknēšanu, vibrēšanu, līdzināšanu, mitrināšanu, plēves piesegšanu, tehnoloģisko un deformācijas šuvju izveidi, ieliekamo detaļu iebetonēšanu, ja nepieciešams/Reinforced concrete slab / Concrete C40/50, concrete with concrete delivery, pumping, vibrating, leveling, wetting, covering with film, creating technological and deformation joints, concreting of insert parts, if necessary | D45: m3 | E45: 31.73
A46: =A45+1 -> 22 | C46: Pārseguma stiegrošana, t. sk palīgmateriāli (distanceri, sienamās stieples, konusi, uzgriežņi u.c.), stiegrojums B500B/Slab reinforcement and consumables (spacers, wall wires, cones, bolts etc.), reinforcement B500B | D46: t | E46: 4.79
A47: 22.1 | C47: Monolīta dzelzsbetona plātne / Reinforced concrete slab, h=500mm
A48: 22.2 | C48: Veidņu (apjoms precizējams veidņu izklājumā) , tsk. (palīgmateriāli (kokmateriāli, saplāksnis, stiprinājumi, caurlītes, konusi, aizbāžņi, eļļa, plēve), stutu montāža/noma/demontāža (pārsegums)/Formwork (volume to be specified in the formwork layout), incl. (auxiliary materials (timber, plywood, fasteners, tubes, cones, plugs, oil, film), studs assembly / rental / dismantling (slab) | D48: m2 | E48: 58.78
A49: 22.3 | C49: Pārseguma betonēšana Betons C40/50, betons ar betona piegādi, sūknēšanu, vibrēšanu, līdzināšanu, mitrināšanu, plēves piesegšanu, tehnoloģisko un deformācijas šuvju izveidi, ieliekamo detaļu iebetonēšanu, ja nepieciešams/Reinforced concrete slab / Concrete C40/50, concrete with concrete delivery, pumping, vibrating, leveling, wetting, covering with film, creating technological and deformation joints, concreting of insert parts, if necessary | D49: m3 | E49: 26.72
A50: 22.4 | C50: Pārseguma stiegrošana, t. sk palīgmateriāli (distanceri, sienamās stieples, konusi, uzgriežņi u.c.), stiegrojums B500B/Slab reinforcement and consumables (spacers, wall wires, cones, bolts etc.), reinforcement B500B | D50: t | E50: 4.03
C51: Pārsegums 3. stāva līmenī / 3rd floor slab
C52: Monolīta dzelzsbetona plātne / Reinforced concrete slab, h=80mm
A53: =A46+1 -> 23 | C53: Veidņu (apjoms precizējams veidņu izklājumā) , tsk. (palīgmateriāli (kokmateriāli, saplāksnis, stiprinājumi, caurlītes, konusi, aizbāžņi, eļļa, plēve), stutu montāža/noma/demontāža (pārsegums)/Formwork (volume to be specified in the formwork layout), incl. (auxiliary materials (timber, plywood, fasteners, tubes, cones, plugs, oil, film), studs assembly / rental / dismantling (slab) | D53: m2 | E53: 112.61
A54: =A53+1 -> 24 | C54: Pārseguma betonēšana Betons C40/50, betons ar betona piegādi, sūknēšanu, vibrēšanu, līdzināšanu, mitrināšanu, plēves piesegšanu, tehnoloģisko un deformācijas šuvju izveidi, ieliekamo detaļu iebetonēšanu, ja nepieciešams/Reinforced concrete slab / Concrete C40/50, concrete with concrete delivery, pumping, vibrating, leveling, wetting, covering with film, creating technological and deformation joints, concreting of insert parts, if necessary | D54: m3 | E54: 8.19
A55: =A54+1 -> 25 | C55: Pārseguma stiegrošana, t. sk palīgmateriāli (distanceri, sienamās stieples, konusi, uzgriežņi u.c.), stiegrojums B500B/Slab reinforcement and consumables (spacers, wall wires, cones, bolts etc.), reinforcement B500B | D55: t | E55: 0.45
A56: 25.1 | C56: Monolīta dzelzsbetona plātne / Reinforced concrete slab, h=265mm
A57: 25.2 | C57: Veidņu (apjoms precizējams veidņu izklājumā) , tsk. (palīgmateriāli (kokmateriāli, saplāksnis, stiprinājumi, caurlītes, konusi, aizbāžņi, eļļa, plēve), stutu montāža/noma/demontāža (pārsegums)/Formwork (volume to be specified in the formwork layout), incl. (auxiliary materials (timber, plywood, fasteners, tubes, cones, plugs, oil, film), studs assembly / rental / dismantling (slab) | D57: m2 | E57: 117.76
A58: 25.3 | C58: Pārseguma betonēšana Betons C40/50, betons ar betona piegādi, sūknēšanu, vibrēšanu, līdzināšanu, mitrināšanu, plēves piesegšanu, tehnoloģisko un deformācijas šuvju izveidi, ieliekamo detaļu iebetonēšanu, ja nepieciešams/Reinforced concrete slab / Concrete C40/50, concrete with concrete delivery, pumping, vibrating, leveling, wetting, covering with film, creating technological and deformation joints, concreting of insert parts, if necessary | D58: m3 | E58: 28.37
A59: 25.4 | C59: Pārseguma stiegrošana, t. sk palīgmateriāli (distanceri, sienamās stieples, konusi, uzgriežņi u.c.), stiegrojums B500B/Slab reinforcement and consumables (spacers, wall wires, cones, bolts etc.), reinforcement B500B | D59: t | E59: 1.56
A60: 25.5 | C60: Monolīta dzelzsbetona plātne / Reinforced concrete slab, h=320mm
A61: 25.6 | C61: Veidņu (apjoms precizējams veidņu izklājumā) , tsk. (palīgmateriāli (kokmateriāli, saplāksnis, stiprinājumi, caurlītes, konusi, aizbāžņi, eļļa, plēve), stutu montāža/noma/demontāža (pārsegums)/Formwork (volume to be specified in the formwork layout), incl. (auxiliary materials (timber, plywood, fasteners, tubes, cones, plugs, oil, film), studs assembly / rental / dismantling (slab) | D61: m2 | E61: 8.66
A62: 25.7 | C62: Pārseguma betonēšana Betons C40/50, betons ar betona piegādi, sūknēšanu, vibrēšanu, līdzināšanu, mitrināšanu, plēves piesegšanu, tehnoloģisko un deformācijas šuvju izveidi, ieliekamo detaļu iebetonēšanu, ja nepieciešams/Reinforced concrete slab / Concrete C40/50, concrete with concrete delivery, pumping, vibrating, leveling, wetting, covering with film, creating technological and deformation joints, concreting of insert parts, if necessary | D62: m3 | E62: 2.52
A63: 25.8 | C63: Pārseguma stiegrošana, t. sk palīgmateriāli (distanceri, sienamās stieples, konusi, uzgriežņi u.c.), stiegrojums B500B/Slab reinforcement and consumables (spacers, wall wires, cones, bolts etc.), reinforcement B500B | D63: t | E63: 0.14
A64: 25.9 | C64: Monolīta dzelzsbetona plātne / Reinforced concrete slab, h=550mm
A65: 25.10 | C65: Veidņu (apjoms precizējams veidņu izklājumā) , tsk. (palīgmateriāli (kokmateriāli, saplāksnis, stiprinājumi, caurlītes, konusi, aizbāžņi, eļļa, plēve), stutu montāža/noma/demontāža (pārsegums)/Formwork (volume to be specified in the formwork layout), incl. (auxiliary materials (timber, plywood, fasteners, tubes, cones, plugs, oil, film), studs assembly / rental / dismantling (slab) | D65: m2 | E65: 2.06
A66: 25.11 | C66: Pārseguma betonēšana Betons C40/50, betons ar betona piegādi, sūknēšanu, vibrēšanu, līdzināšanu, mitrināšanu, plēves piesegšanu, tehnoloģisko un deformācijas šuvju izveidi, ieliekamo detaļu iebetonēšanu, ja nepieciešams/Reinforced concrete slab / Concrete C40/50, concrete with concrete delivery, pumping, vibrating, leveling, wetting, covering with film, creating technological and deformation joints, concreting of insert parts, if necessary | D66: m3 | E66: 1.03
A67: 25.12 | C67: Pārseguma stiegrošana, t. sk palīgmateriāli (distanceri, sienamās stieples, konusi, uzgriežņi u.c.), stiegrojums B500B/Slab reinforcement and consumables (spacers, wall wires, cones, bolts etc.), reinforcement B500B | D67: t | E67: 0.06
C68: Pārsegums 4. stāva līmenī / 4th floor slab
C69: Monolīta dzelzsbetona plātne / Reinforced concrete slab, h=80mm
A70: =A55+1 -> 26 | C70: Veidņu (apjoms precizējams veidņu izklājumā) , tsk. (palīgmateriāli (kokmateriāli, saplāksnis, stiprinājumi, caurlītes, konusi, aizbāžņi, eļļa, plēve), stutu montāža/noma/demontāža (pārsegums)/Formwork (volume to be specified in the formwork layout), incl. (auxiliary materials (timber, plywood, fasteners, tubes, cones, plugs, oil, film), studs assembly / rental / dismantling (slab) | D70: m2 | E70: 141.21
A71: =A70+1 -> 27 | C71: Pārseguma betonēšana Betons C40/50, betons ar betona piegādi, sūknēšanu, vibrēšanu, līdzināšanu, mitrināšanu, plēves piesegšanu, tehnoloģisko un deformācijas šuvju izveidi, ieliekamo detaļu iebetonēšanu, ja nepieciešams/Reinforced concrete slab / Concrete C40/50, concrete with concrete delivery, pumping, vibrating, leveling, wetting, covering with film, creating technological and deformation joints, concreting of insert parts, if necessary | D71: m3 | E71: 10.27
A72: =A71+1 -> 28 | C72: Pārseguma stiegrošana, t. sk palīgmateriāli (distanceri, sienamās stieples, konusi, uzgriežņi u.c.), stiegrojums B500B/Slab reinforcement and consumables (spacers, wall wires, cones, bolts etc.), reinforcement B500B | D72: t | E72: 0.56
A73: 28.1 | C73: Monolīta dzelzsbetona plātne / Reinforced concrete slab, h=265mm
A74: 28.2 | C74: Veidņu (apjoms precizējams veidņu izklājumā) , tsk. (palīgmateriāli (kokmateriāli, saplāksnis, stiprinājumi, caurlītes, konusi, aizbāžņi, eļļa, plēve), stutu montāža/noma/demontāža (pārsegums)/Formwork (volume to be specified in the formwork layout), incl. (auxiliary materials (timber, plywood, fasteners, tubes, cones, plugs, oil, film), studs assembly / rental / dismantling (slab) | D74: m2 | E74: 119.38
A75: 28.3 | C75: Pārseguma betonēšana Betons C40/50, betons ar betona piegādi, sūknēšanu, vibrēšanu, līdzināšanu, mitrināšanu, plēves piesegšanu, tehnoloģisko un deformācijas šuvju izveidi, ieliekamo detaļu iebetonēšanu, ja nepieciešams/Reinforced concrete slab / Concrete C40/50, concrete with concrete delivery, pumping, vibrating, leveling, wetting, covering with film, creating technological and deformation joints, concreting of insert parts, if necessary | D75: m3 | E75: 28.76
A76: 28.4 | C76: Pārseguma stiegrošana, t. sk palīgmateriāli (distanceri, sienamās stieples, konusi, uzgriežņi u.c.), stiegrojums B500B/Slab reinforcement and consumables (spacers, wall wires, cones, bolts etc.), reinforcement B500B | D76: t | E76: 1.58
C77: Pārsegums 5. stāva līmenī / 5th floor slab
C78: Monolīta dzelzsbetona plātne / Reinforced concrete slab, h=80mm
A79: =A72+1 -> 29 | C79: Veidņu (apjoms precizējams veidņu izklājumā) , tsk. (palīgmateriāli (kokmateriāli, saplāksnis, stiprinājumi, caurlītes, konusi, aizbāžņi, eļļa, plēve), stutu montāža/noma/demontāža (pārsegums)/Formwork (volume to be specified in the formwork layout), incl. (auxiliary materials (timber, plywood, fasteners, tubes, cones, plugs, oil, film), studs assembly / rental / dismantling (slab) | D79: m2 | E79: 141.21
A80: =A79+1 -> 30 | C80: Pārseguma betonēšana Betons C40/50, betons ar betona piegādi, sūknēšanu, vibrēšanu, līdzināšanu, mitrināšanu, plēves piesegšanu, tehnoloģisko un deformācijas šuvju izveidi, ieliekamo detaļu iebetonēšanu, ja nepieciešams/Reinforced concrete slab / Concrete C40/50, concrete with concrete delivery, pumping, vibrating, leveling, wetting, covering with film, creating technological and deformation joints, concreting of insert parts, if necessary | D80: m3 | E80: 10.27
A81: =A80+1 -> 31 | C81: Pārseguma stiegrošana, t. sk palīgmateriāli (distanceri, sienamās stieples, konusi, uzgriežņi u.c.), stiegrojums B500B/Slab reinforcement and consumables (spacers, wall wires, cones, bolts etc.), reinforcement B500B | D81: t | E81: 0.56
A82: 31.1 | C82: Monolīta dzelzsbetona plātne / Reinforced concrete slab, h=265mm
A83: 31.2 | C83: Veidņu (apjoms precizējams veidņu izklājumā) , tsk. (palīgmateriāli (kokmateriāli, saplāksnis, stiprinājumi, caurlītes, konusi, aizbāžņi, eļļa, plēve), stutu montāža/noma/demontāža (pārsegums)/Formwork (volume to be specified in the formwork layout), incl. (auxiliary materials (timber, plywood, fasteners, tubes, cones, plugs, oil, film), studs assembly / rental / dismantling (slab) | D83: m2 | E83: 119.38
A84: 31.3 | C84: Pārseguma betonēšana Betons C40/50, betons ar betona piegādi, sūknēšanu, vibrēšanu, līdzināšanu, mitrināšanu, plēves piesegšanu, tehnoloģisko un deformācijas šuvju izveidi, ieliekamo detaļu iebetonēšanu, ja nepieciešams/Reinforced concrete slab / Concrete C40/50, concrete with concrete delivery, pumping, vibrating, leveling, wetting, covering with film, creating technological and deformation joints, concreting of insert parts, if necessary | D84: m3 | E84: 28.76
A85: 31.4 | C85: Pārseguma stiegrošana, t. sk palīgmateriāli (distanceri, sienamās stieples, konusi, uzgriežņi u.c.), stiegrojums B500B/Slab reinforcement and consumables (spacers, wall wires, cones, bolts etc.), reinforcement B500B | D85: t | E85: 1.58
A86: 31.5 | C86: Pārsegums 6. stāva līmenī / 6th floor slab
A87: 31.6 | C87: Monolīta dzelzsbetona plātne / Reinforced concrete slab, h=320mm
A88: 31.7 | C88: Veidņu (apjoms precizējams veidņu izklājumā) , tsk. (palīgmateriāli (kokmateriāli, saplāksnis, stiprinājumi, caurlītes, konusi, aizbāžņi, eļļa, plēve), stutu montāža/noma/demontāža (pārsegums)/Formwork (volume to be specified in the formwork layout), incl. (auxiliary materials (timber, plywood, fasteners, tubes, cones, plugs, oil, film), studs assembly / rental / dismantling (slab) | D88: m2 | E88: 173.46
A89: 31.8 | C89: Pārseguma betonēšana Betons C40/50, betons ar betona piegādi, sūknēšanu, vibrēšanu, līdzināšanu, mitrināšanu, plēves piesegšanu, tehnoloģisko un deformācijas šuvju izveidi, ieliekamo detaļu iebetonēšanu, ja nepieciešams/Reinforced concrete slab / Concrete C40/50, concrete with concrete delivery, pumping, vibrating, leveling, wetting, covering with film, creating technological and deformation joints, concreting of insert parts, if necessary | D89: m3 | E89: 50.46
A90: 31.9 | C90: Pārseguma stiegrošana, t. sk palīgmateriāli (distanceri, sienamās stieples, konusi, uzgriežņi u.c.), stiegrojums B500B/Slab reinforcement and consumables (spacers, wall wires, cones, bolts etc.), reinforcement B500B | D90: t | E90: 2.78
A91: 31.10 | C91: Pārsegums 7. stāva līmenī / 7th floor slab
A92: 31.11 | C92: Monolīta dzelzsbetona plātne / Reinforced concrete slab, h=220mm
A93: 31.12 | C93: Veidņu (apjoms precizējams veidņu izklājumā) , tsk. (palīgmateriāli (kokmateriāli, saplāksnis, stiprinājumi, caurlītes, konusi, aizbāžņi, eļļa, plēve), stutu montāža/noma/demontāža (pārsegums)/Formwork (volume to be specified in the formwork layout), incl. (auxiliary materials (timber, plywood, fasteners, tubes, cones, plugs, oil, film), studs assembly / rental / dismantling (slab) | D93: m2 | E93: 155.75
A94: 31.13 | C94: Pārseguma betonēšana Betons C40/50, betons ar betona piegādi, sūknēšanu, vibrēšanu, līdzināšanu, mitrināšanu, plēves piesegšanu, tehnoloģisko un deformācijas šuvju izveidi, ieliekamo detaļu iebetonēšanu, ja nepieciešams/Reinforced concrete slab / Concrete C40/50, concrete with concrete delivery, pumping, vibrating, leveling, wetting, covering with film, creating technological and deformation joints, concreting of insert parts, if necessary | D94: m3 | E94: 31.15
A95: 31.14 | C95: Pārseguma stiegrošana, t. sk palīgmateriāli (distanceri, sienamās stieples, konusi, uzgriežņi u.c.), stiegrojums B500B/Slab reinforcement and consumables (spacers, wall wires, cones, bolts etc.), reinforcement B500B | D95: t | E95: 1.71
C96: Dobo pārseguma paneļi / Slabs
A97: =A81+1 -> 32 | C97: Saliekama dzelzsbetona plātnes dobo paneļu HCS 220 Betons C40/50 (b=220mm) montāža, (t.sk.montāžas materiāli, stiprinājumi, ieliekamās detaļas, palīgmateriāli)/ Precast reinforced concrete slab HCS 220 Concrete 40/50 (b=220mm) assembly, (including assembly materials, fasteners, insert parts, auxiliary materials),t sk. including: | D97: m2 | E97: 964.81
A98: =A97+0.1 -> 32.1 | C98: Panelis / Slab HCS 500 500x3575 mm | D98: kpl | E98: 1
A99: =A98+0.1 -> 32.2 | C99: Panelis / Slab HCS 500 500x7995 mm | D99: kpl | E99: 1
A100: =A99+0.1 -> 32.3 | C100: Panelis / Slab HCS 500 640x2640 mm | D100: kpl | E100: 1
A101: =A100+0.1 -> 32.4 | C101: Panelis / Slab HCS 500 640x3575 mm | D101: kpl | E101: 1
A102: =A101+0.1 -> 32.5 | C102: Panelis / Slab HCS 500 640x7450 mm | D102: kpl | E102: 1
A103: =A102+0.1 -> 32.6 | C103: Panelis / Slab HCS 500 640x7515 mm | D103: kpl | E103: 2
A104: =A103+0.1 -> 32.7 | C104: Panelis / Slab HCS 500 690x3775 mm | D104: kpl | E104: 1
...

Sheet 1-6K
F1: Lokālā tāme Nr./Local estimate No | G1: 1-6
F2: Kāpnes, margas / Staircases, railings
A4: =KS!C4 -> Būves nosaukums/Building: Daudzīvokļu ēka / Residental building C2-10
A5: =KS!C5 -> Objekta nosaukums/Object: Dzīvojamās ēkas C2-10 jaunbūve/ Residential building C2-10
A6: =KS!C6 -> Objekta adrese/Object adress: Andrejostas iela 35, Rīga, LV-1045 | M6: Tāmes izmaksas | O6: 0
P8: Tāme sastādīta/Date _____. gada ____. ____________
F10: Vienības izmaksas/Unit rate | N10: Kopā uz visu apjomu/Total amount
A11: N.p.k./No | B11: Kods*/Code | C11: Būvdarbu nosaukums/Description of the construction work | D11: Mērvienība/ Unit | E11: Daudzums/ Quantity | F11: laika norma (c/h)/time rate (w/h) | G11: darba samaksas likme* (euro/h)/labour wage rate (euro/h)* | H11: darba alga/ salary | I11: būvizstrādājumi/ materials | J11: mehānismi/ mechanisms | K11: kopā/ total | L11: darbietilpība (c/h)/labor (w/h) | M11: darba alga/ salary | N11: būvizstrādājumi/ materials | O11: mehānismi/ mechanisms | P11: summa/ Total
A12: 1 | B12: 2 | C12: 3 | D12: 4 | E12: 5 | F12: =E12+1 -> 6 | G12: =F12+1 -> 7 | H12: =G12+1 -> 8 | I12: =H12+1 -> 9 | J12: =I12+1 -> 10 | K12: =J12+1 -> 11 | L12: =K12+1 -> 12 | M12: =L12+1 -> 13 | ... P12: =O12+1 -> 16
C14: Kāpnes
A15: 1 | C15: Detalizācijas rasējumu izstrāde saliekamajām DzKD / Development of detailed drawings for prefabricated DzKD | D15: kpl | E15: 1
C16: Saliekamās dz/b kāpnes / Precast stair
A17: =A15+1 -> 2 | B17: KP-01 | C17: Saliekama dzelzsbetona kāpņu podestu montāža (t. sk. dzelzsbetona izstrādājums Betons C35/45) un ieliekamās detaļas, stiprinājumi, palīgmateriāli)/Assembly of prefabricated reinforced concrete stair landings (incl. reinforced concrete product (exposed concrete surface , Concrete 35/45 ) and inserts, fasteners, auxiliary materials); 1 izstrādājuma tilpums/ volume for 1 item 0,66 m³ | D17: kpl | E17: 18
A18: =A17+1 -> 3 | B18: KL-01 | C18: Saliekama dzelzsbetona kāpņu laidu montāža (t. sk. dzelzsbetona izstrādājums Betons C35/45) un ieliekamās detaļas, stiprinājumi, palīgmateriāli)/Assembly of prefabricated reinforced concrete stair run (incl. reinforced concrete product (exposed concrete surface , Concrete 35/45 ) and inserts, fasteners, auxiliary materials) 1 izstrādājuma tilpums/ volume for 1 item 0,82 m³ | D18: kpl | E18: 3
A19: =A18+1 -> 4 | B19: KL-02 | C19: Saliekama dzelzsbetona kāpņu laidu montāža (t. sk. dzelzsbetona izstrādājums Betons C35/45) un ieliekamās detaļas, stiprinājumi, palīgmateriāli)/Assembly of prefabricated reinforced concrete stair run (incl. reinforced concrete product (exposed concrete surface , Concrete 35/45 ) and inserts, fasteners, auxiliary materials) 1 izstrādājuma tilpums/ volume for 1 item 0,92 m³ | D19: kpl | E19: 3
A20: =A19+1 -> 5 | B20: KL-03 | C20: Saliekama dzelzsbetona kāpņu laidu montāža (t. sk. dzelzsbetona izstrādājums Betons C35/45) un ieliekamās detaļas, stiprinājumi, palīgmateriāli)/Assembly of prefabricated reinforced concrete stair run (incl. reinforced concrete product (exposed concrete surface , Concrete 35/45 ) and inserts, fasteners, auxiliary materials) 1 izstrādājuma tilpums/ volume for 1 item 0,67 m³ | D20: kpl | E20: 3
A21: =A20+1 -> 6 | B21: KL-04 | C21: Saliekama dzelzsbetona kāpņu laidu montāža (t. sk. dzelzsbetona izstrādājums Betons C35/45) un ieliekamās detaļas, stiprinājumi, palīgmateriāli)/Assembly of prefabricated reinforced concrete stair run (incl. reinforced concrete product (exposed concrete surface , Concrete 35/45 ) and inserts, fasteners, auxiliary materials) 1 izstrādājuma tilpums/ volume for 1 item 0,93 m³ | D21: kpl | E21: 3
A22: =A21+1 -> 7 | B22: KL-05 | C22: Saliekama dzelzsbetona kāpņu laidu montāža (t. sk. dzelzsbetona izstrādājums Betons C35/45) un ieliekamās detaļas, stiprinājumi, palīgmateriāli)/Assembly of prefabricated reinforced concrete stair run (incl. reinforced concrete product (exposed concrete surface , Concrete 35/45 ) and inserts, fasteners, auxiliary materials) 1 izstrādājuma tilpums/ volume for 1 item 0,93 m³ | D22: kpl | E22: 3
A23: =A22+1 -> 8 | B23: KL-06 | C23: Saliekama dzelzsbetona kāpņu laidu montāža (t. sk. dzelzsbetona izstrādājums Betons C35/45) un ieliekamās detaļas, stiprinājumi, palīgmateriāli)/Assembly of prefabricated reinforced concrete stair run (incl. reinforced concrete product (exposed concrete surface , Concrete 35/45 ) and inserts, fasteners, auxiliary materials) 1 izstrādājuma tilpums/ volume for 1 item 0,88 m³ | D23: kpl | E23: 9
A24: =A23+1 -> 9 | B24: KL-07 | C24: Saliekama dzelzsbetona kāpņu laidu montāža (t. sk. dzelzsbetona izstrādājums Betons C35/45) un ieliekamās detaļas, stiprinājumi, palīgmateriāli)/Assembly of prefabricated reinforced concrete stair run (incl. reinforced concrete product (exposed concrete surface , Concrete 35/45 ) and inserts, fasteners, auxiliary materials) 1 izstrādājuma tilpums/ volume for 1 item 0,90 m³ | D24: kpl | E24: 9
A25: =A24+1 -> 10 | B25: KL-08 | C25: Saliekama dzelzsbetona kāpņu laidu montāža (t. sk. dzelzsbetona izstrādājums Betons C35/45) un ieliekamās detaļas, stiprinājumi, palīgmateriāli)/Assembly of prefabricated reinforced concrete stair run (incl. reinforced concrete product (exposed concrete surface , Concrete 35/45 ) and inserts, fasteners, auxiliary materials) 1 izstrādājuma tilpums/ volume for 1 item 0,91 m³ | D25: kpl | E25: 3
A26: =A25+1 -> 11 | B26: KL-09 | C26: Saliekama dzelzsbetona kāpņu laidu montāža (t. sk. dzelzsbetona izstrādājums Betons C35/45) un ieliekamās detaļas, stiprinājumi, palīgmateriāli)/Assembly of prefabricated reinforced concrete stair run (incl. reinforced concrete product (exposed concrete surface , Concrete 35/45 ) and inserts, fasteners, auxiliary materials) 1 izstrādājuma tilpums/ volume for 1 item 0,97 m³ | D26: kpl | E26: 3
A27: =A26+1 -> 12 | C27: Visu ēku kāpņu telpas kapnēm pirmajam un pēdējam pakāpienam paredzams kontrastējošs melns, nodilumizturīgs krasojums 5 cm platumā visā kāpņu platumā / All staircases in the building must have a contrasting black, wear-resistant marking on the first and last step - 5 cm wide across the full width of the stair | D27: kpl | E27: 72
A28: =A27+1 -> 13 | C28: Uz kāpņu margām pie pirmā un pēdējā pakāpiena iestrādā stāva numura taktilais apzīmējums vai numurs Braila akstā / A tactile floor number or Braille number must be installed on the handrail at the first and last step | D28: kpl | E28: 72
A29: 13.1 | C29: Komercplatības kāpņu izgatavošana un montāža, apstrāde (attīrīšana, gruntēšana, krāsošana, pretkorozijas un ugunsizturības R60 aizsardzība) saskaņā ar projektu, t.sk. palīgmateriāli, stiprinājumi, loksnes, plātnes, skrūves, uzgriežni, ieliekamās detaļas, detalizācijas rasējumu izstrāde / Retail stair production and assembly of steel structures, processing (cleaning, priming, painting, corrosion and fireproof R60 protection) according to the project, including auxiliary materials, fasteners, sheets, plates, screws, nuts, insert parts, development of detail drawings | D29: kpl | E29: 1
C31: Margas/Railings
A32: =A28+1 -> 14 | B32: M-1 | C32: Kāpņu telpas margas montāža, t.sk. stiprinājumi, palīgmateriāli / Staircase railings assembly, including fasteners, consumables | D32: m | E32: 60.71
A33: =A32+1 -> 15 | B33: M-2 | C33: Kāpņu telpas margas montāža, t.sk. stiprinājumi, palīgmateriāli / Staircase railings assembly, including fasteners, consumables | D33: m | E33: 48.58
A34: =A33+1 -> 16 | B34: M-3 | C34: Kāpņu telpas margas montāža, t.sk. stiprinājumi, palīgmateriāli / Staircase railings assembly, including fasteners, consumables | D34: m | E34: 27.23
A35: =A34+1 -> 17 | B35: M-4 | C35: Kāpņu telpas margas montāža, t.sk. stiprinājumi, palīgmateriāli / Staircase railings assembly, including fasteners, consumables | D35: m | E35: 54.46
A36: =A35+1 -> 18 | B36: M-5 | C36: Terases margas montāža, t.sk. stiprinājumi, palīgmateriāli / Terrace railings assembly, including fasteners, consumables | D36: m | E36: 58.37
A37: =A36+1 -> 19 | B37: M-6 | C37: Balkonu margas montāža, t.sk. stiprinājumi, palīgmateriāli/ Balcony railings assembly, including fasteners, consumables | D37: m | E37: 44.05
A38: =A37+1 -> 20 | B38: M-7 | C38: Terases margas montāža, t.sk. stiprinājumi, palīgmateriāli / Terrace railings assembly, including fasteners, consumables | D38: m | E38: 157.09
A39: =A38+1 -> 21 | B39: M-8 | C39: Balkonu margas montāža, t.sk. stiprinājumi, palīgmateriāli/ Balcony railings assembly, including fasteners, consumables | D39: m | E39: 347.94
A40: =A39+1 -> 22 | B40: M-9 | C40: Balkonu stikla margas montāža, t.sk. stiprinājumi, palīgmateriāli / Balcony glass railings assembly, including fasteners, consumables | D40: m | E40: 230.33
A41: =A40+1 -> 23 | B41: M-10 | C41: Franču balkonu stikla margas montāža, t.sk. stiprinājumi, palīgmateriāli / French balcony glass railings assembly, including fasteners, consumables | D41: m | E41: 11.45
A42: =A40+1 -> 23 | B42: M-11 | C42: Iekštelpas stikla margas montāža, t.sk. stiprinājumi, palīgmateriāli / Indoor glass railings assembly, including fasteners, consumables | D42: m | E42: 14.93
A43: =A41+1 -> 24 | B43: M-12 | C43: Iekštelpas stikla margas montāža, t.sk. stiprinājumi, palīgmateriāli / Indoor glass railings assembly, including fasteners, consumables | D43: m | E43: 2.23
C45: Izmaksas kopā, t. sk. darba devēja sociālais nodoklis (%) /Total costs, including employer's social tax (%) | L45: =SUM($L$13:L44) -> 0 | M45: =SUM($M$13:M44) -> 0 | N45: =SUM($N$13:N44) -> 0 | O45: =SUM($O$13:O44) -> 0 | P45: =SUM($P$13:P44) -> 0

Sheet 1-7J
F1: Lokālā tāme Nr./Local estimate No | G1: 1-7
F2: Jumta un jumta elementu montāža / Roof and roof elements
A4: =KS!C4 -> Būves nosaukums/Building: Daudzīvokļu ēka / Residental building C2-10
A5: =KS!C5 -> Objekta nosaukums/Object: Dzīvojamās ēkas C2-10 jaunbūve/ Residential building C2-10
A6: =KS!C6 -> Objekta adrese/Object adress: Andrejostas iela 35, Rīga, LV-1045 | M6: Tāmes izmaksas | P6: euro
P8: Tāme sastādīta/Date _____. gada ____. ____________
F10: Vienības izmaksas/Unit rate | N10: Kopā uz visu apjomu/Total amount
A11: N.p.k./No | B11: Kods*/Code | C11: Būvdarbu nosaukums/Description of the construction work | D11: Mērvienība/ Unit | E11: Daudzums/ Quantity | F11: laika norma (c/h)/time rate (w/h) | G11: darba samaksas likme* (euro/h)/labour wage rate (euro/h)* | H11: darba alga/ salary | I11: būvizstrādājumi/ materials | J11: mehānismi/ mechanisms | K11: kopā/ total | L11: darbietilpība (c/h)/labor (w/h) | M11: darba alga/ salary | N11: būvizstrādājumi/ materials | O11: mehānismi/ mechanisms | P11: summa/ Total
A12: 1 | B12: 2 | C12: 3 | D12: 4 | E12: 5 | F12: =E12+1 -> 6 | G12: =F12+1 -> 7 | H12: =G12+1 -> 8 | I12: =H12+1 -> 9 | J12: =I12+1 -> 10 | K12: =J12+1 -> 11 | L12: =K12+1 -> 12 | M12: =L12+1 -> 13 | ... P12: =O12+1 -> 16
B14: P-1-5.1 | C14: DZ/B dobpaneļu starpstāvu pārsegums 500mm, jumta terase / RC hollow core slab floor 500mm, roof terrace | D14: m² | E14: 235
A15: 1 | C15: Tvaika izolācija Multiplex Super AL – SD 1500 / Vapour insulation Multiplex Super AL – SD 1500 - mm | D15: m2 | E15: 235
A16: =A15+1 -> 2 | C16: Slīpumu veidojošs slānis XPS (piem. FINNFOAM F-300,λ=0,033W/mK, spiedes izturība >300kPa) 20-160 mm / Slope-forming layer XPS (e.g. FINNFOAM F-300, λ=0.033W/mK, compressive strength >300kPa) 20-160 mm | D16: m2 | E16: 235
A17: =A16+1 -> 3 | C17: XPS siltumizolācija (piem. FINNFOAM F-300, λ=0,033W/mK, spiedes izturība >300kPa) 120 mm / XPS thermal insulation (e.g. FINNFOAM F-300, λ=0.033W/mK, compressive strength >300kPa) 120 mm | D17: m2 | E17: 235
A18: =A17+1 -> 4 | C18: Jumta siltumizolācijas plāksne (piemēram, PAROC ROB 80, λ=0,038 W/mK) 20 mm / Roof thermal insulation board (e.g. PAROC ROB 80, λ=0.038 W/mK) 20 mm | D18: m2 | E18: 235
B20: P-1-5.2 | C20: DZ/B dobpaneļu starpstāvu pārsegums 500mm, jumta terase / RC hollow core slab floor 500mm, roof terrace | D20: m² | E20: 121
A21: =A18+1 -> 5 | C21: Tvaika izolācija Multiplex Super AL – SD 1500 / Vapour insulation Multiplex Super AL – SD 1500 - mm | D21: m2 | E21: 121
A22: =A21+1 -> 6 | C22: Slīpumu veidojošs slānis XPS (piem. FINNFOAM F-300,λ=0,033W/mK, spiedes izturība >300kPa) 20-160 mm / Slope-forming layer XPS (e.g. FINNFOAM F-300, λ=0.033W/mK, compressive strength >300kPa) 20-160 mm | D22: m2 | E22: 121
A23: =A22+1 -> 7 | C23: XPS siltumizolācija (piem. FINNFOAM F-300, λ=0,033W/mK, spiedes izturība >300kPa) 120 mm / XPS thermal insulation (e.g. FINNFOAM F-300, λ=0.033W/mK, compressive strength >300kPa) 120 mm | D23: m2 | E23: 121
A24: =A23+1 -> 8 | C24: Jumta siltumizolācijas plāksne (piemēram, PAROC ROB 80, λ=0,038 W/mK) 20 mm / Roof thermal insulation board (e.g. PAROC ROB 80, λ=0.038 W/mK) 20 mm | D24: m2 | E24: 121
B26: P-1-5.2* | C26: DZ/B dobpaneļu starpstāvu pārsegums 320mm, jumta terase / RC hollow core slab floor 320mm, roof terrace | D26: m² | E26: 42
A27: =A24+1 -> 9 | C27: Tvaika izolācija Multiplex Super AL – SD 1500 / Vapour insulation Multiplex Super AL – SD 1500 - mm | D27: m2 | E27: 42
A28: =A27+1 -> 10 | C28: Slīpumu veidojošs slānis XPS (piem. FINNFOAM F-300,λ=0,033W/mK, spiedes izturība >300kPa) 20-160 mm / Slope-forming layer XPS (e.g. FINNFOAM F-300, λ=0.033W/mK, compressive strength >300kPa) 20-160 mm | D28: m2 | E28: 42
A29: =A28+1 -> 11 | C29: XPS siltumizolācija (piem. FINNFOAM F-300, λ=0,033W/mK, spiedes izturība >300kPa) 120 mm / XPS thermal insulation (e.g. FINNFOAM F-300, λ=0.033W/mK, compressive strength >300kPa) 120 mm | D29: m2 | E29: 42
A30: =A29+1 -> 12 | C30: Jumta siltumizolācijas plāksne (piemēram, PAROC ROB 80, λ=0,038 W/mK) 20 mm / Roof thermal insulation board (e.g. PAROC ROB 80, λ=0.038 W/mK) 20 mm | D30: m2 | E30: 42
B32: P-1-6.1 | C32: DZ/B dobpaneļu starpstāvu pārsegums 500mm, jumta dārzs / RC hollow core slab floor 500mm, roof garden | D32: m² | E32: 49
A33: =A30+1 -> 13 | C33: Tvaika izolācija Multiplex Super AL – SD 1500 / Vapour insulation Multiplex Super AL – SD 1500 - mm | D33: m2 | E33: 49
A34: =A33+1 -> 14 | C34: Slīpumu veidojošs slānis XPS (piem. FINNFOAM F-300,λ=0,033W/mK, spiedes izturība >300kPa) 20-160 mm / Slope-forming layer XPS (e.g. FINNFOAM F-300, λ=0.033W/mK, compressive strength >300kPa) 20-160 mm | D34: m2 | E34: 49
A35: =A34+1 -> 15 | C35: XPS siltumizolācija (piem. FINNFOAM F-300, λ=0,033W/mK, spiedes izturība >300kPa) 120 mm / XPS thermal insulation (e.g. FINNFOAM F-300, λ=0.033W/mK, compressive strength >300kPa) 120 mm | D35: m2 | E35: 49
A36: =A35+1 -> 16 | C36: Jumta siltumizolācijas plāksne (piemēram, PAROC ROB 80, λ=0,038 W/mK) 20 mm / Roof thermal insulation board (e.g. PAROC ROB 80, λ=0.038 W/mK) 20 mm | D36: m2 | E36: 49
B38: P-1-6.2 | C38: DZ/B dobpaneļu starpstāvu pārsegums 500mm, jumta dārzs / RC hollow core slab floor 500mm, roof garden | D38: m² | E38: 98
A39: =A36+1 -> 17 | C39: Tvaika izolācija Multiplex Super AL – SD 1500 / Vapour insulation Multiplex Super AL – SD 1500 - mm | D39: m2 | E39: 98
A40: =A39+1 -> 18 | C40: Slīpumu veidojošs slānis XPS (piem. FINNFOAM F-300,λ=0,033W/mK, spiedes izturība >300kPa) 20-160 mm / Slope-forming layer XPS (e.g. FINNFOAM F-300, λ=0.033W/mK, compressive strength >300kPa) 20-160 mm | D40: m2 | E40: 98
A41: =A40+1 -> 19 | C41: XPS siltumizolācija (piem. FINNFOAM F-300, λ=0,033W/mK, spiedes izturība >300kPa) 120 mm / XPS thermal insulation (e.g. FINNFOAM F-300, λ=0.033W/mK, compressive strength >300kPa) 120 mm | D41: m2 | E41: 98
A42: =A41+1 -> 20 | C42: Jumta siltumizolācijas plāksne (piemēram, PAROC ROB 80, λ=0,038 W/mK) 20 mm / Roof thermal insulation board (e.g. PAROC ROB 80, λ=0.038 W/mK) 20 mm | D42: m2 | E42: 98
B44: P-1-6.3 | C44: DZ/B dobpaneļu starpstāvu pārsegums 500mm, jumta dārzs / RC hollow core slab floor 500mm, roof garden | D44: m² | E44: 50
A45: =A42+1 -> 21 | C45: Tvaika izolācija Multiplex Super AL – SD 1500 / Vapour insulation Multiplex Super AL – SD 1500 - mm | D45: m2 | E45: 50
A46: =A45+1 -> 22 | C46: Slīpumu veidojošs slānis XPS (piem. FINNFOAM F-300,λ=0,033W/mK, spiedes izturība >300kPa) 20-160 mm / Slope-forming layer XPS (e.g. FINNFOAM F-300, λ=0.033W/mK, compressive strength >300kPa) 20-160 mm | D46: m2 | E46: 50
A47: =A46+1 -> 23 | C47: XPS siltumizolācija (piem. FINNFOAM F-300, λ=0,033W/mK, spiedes izturība >300kPa) 120 mm / XPS thermal insulation (e.g. FINNFOAM F-300, λ=0.033W/mK, compressive strength >300kPa) 120 mm | D47: m2 | E47: 50
A48: =A47+1 -> 24 | C48: Jumta siltumizolācijas plāksne (piemēram, PAROC ROB 80, λ=0,038 W/mK) 20 mm / Roof thermal insulation board (e.g. PAROC ROB 80, λ=0.038 W/mK) 20 mm | D48: m2 | E48: 50
B50: P-1-7.1 | C50: DZ/B dobpaneļu starpstāvu pārsegums 500mm, jumta apstādījumi / RC hollow core slab floor 500mm, roof greenery | D50: m² | E50: 39
A51: =A48+1 -> 25 | C51: Tvaika izolācija Multiplex Super AL – SD 1500 / Vapour insulation Multiplex Super AL – SD 1500 - mm | D51: m2 | E51: 39
A52: =A51+1 -> 26 | C52: Slīpumu veidojošs slānis XPS (piem. FINNFOAM F-300,λ=0,033W/mK, spiedes izturība >300kPa) 20-160 mm / Slope-forming layer XPS (e.g. FINNFOAM F-300, λ=0.033W/mK, compressive strength >300kPa) 20-160 mm | D52: m2 | E52: 39
A53: =A52+1 -> 27 | C53: XPS siltumizolācija (piem. FINNFOAM F-300, λ=0,033W/mK, spiedes izturība >300kPa) 120 mm / XPS thermal insulation (e.g. FINNFOAM F-300, λ=0.033W/mK, compressive strength >300kPa) 120 mm | D53: m2 | E53: 39
A54: =A53+1 -> 28 | C54: Jumta siltumizolācijas plāksne (piemēram, PAROC ROB 80, λ=0,038 W/mK) 20 mm / Roof thermal insulation board (e.g. PAROC ROB 80, λ=0.038 W/mK) 20 mm | D54: m2 | E54: 39
B56: P-1-7.2 | C56: DZ/B dobpaneļu starpstāvu pārsegums 500mm, jumta apstādījumi / RC hollow core slab floor 500mm, roof greenery | D56: m² | E56: 204
A57: =A54+1 -> 29 | C57: Tvaika izolācija Multiplex Super AL – SD 1500 / Vapour insulation Multiplex Super AL – SD 1500 - mm | D57: m2 | E57: 204
A58: =A57+1 -> 30 | C58: Slīpumu veidojošs slānis XPS (piem. FINNFOAM F-300,λ=0,033W/mK, spiedes izturība >300kPa) 20-160 mm / Slope-forming layer XPS (e.g. FINNFOAM F-300, λ=0.033W/mK, compressive strength >300kPa) 20-160 mm | D58: m2 | E58: 204
A59: =A58+1 -> 31 | C59: XPS siltumizolācija (piem. FINNFOAM F-300, λ=0,033W/mK, spiedes izturība >300kPa) 120 mm / XPS thermal insulation (e.g. FINNFOAM F-300, λ=0.033W/mK, compressive strength >300kPa) 120 mm | D59: m2 | E59: 204
A60: =A59+1 -> 32 | C60: Jumta siltumizolācijas plāksne (piemēram, PAROC ROB 80, λ=0,038 W/mK) 20 mm / Roof thermal insulation board (e.g. PAROC ROB 80, λ=0.038 W/mK) 20 mm | D60: m2 | E60: 204
B62: P-1-7.2* | C62: DZ/B dobpaneļu starpstāvu pārsegums 320mm, jumta apstādījumi / RC hollow core slab floor 320mm, roof greenery | D62: m² | E62: 19
A63: =A60+1 -> 33 | C63: Tvaika izolācija Multiplex Super AL – SD 1500 / Vapour insulation Multiplex Super AL – SD 1500 - mm | D63: m2 | E63: 19
A64: =A63+1 -> 34 | C64: Slīpumu veidojošs slānis XPS (piem. FINNFOAM F-300,λ=0,033W/mK, spiedes izturība >300kPa) 20-160 mm / Slope-forming layer XPS (e.g. FINNFOAM F-300, λ=0.033W/mK, compressive strength >300kPa) 20-160 mm | D64: m2 | E64: 19
A65: =A64+1 -> 35 | C65: XPS siltumizolācija (piem. FINNFOAM F-300, λ=0,033W/mK, spiedes izturība >300kPa) 120 mm / XPS thermal insulation (e.g. FINNFOAM F-300, λ=0.033W/mK, compressive strength >300kPa) 120 mm | D65: m2 | E65: 19
A66: =A65+1 -> 36 | C66: Jumta siltumizolācijas plāksne (piemēram, PAROC ROB 80, λ=0,038 W/mK) 20 mm / Roof thermal insulation board (e.g. PAROC ROB 80, λ=0.038 W/mK) 20 mm | D66: m2 | E66: 19
B68: P-1-8.1 | C68: Monolīta DZ/B pārsegums virs ārtelpas 300 mm / Monolithic RC slab floor above outdoor space 300 mm | D68: m² | E68: 44
A69: =A66+1 -> 37 | C69: Slīpumu veidojošs slānis XPS (piem. FINNFOAM F-300,λ=0,033W/mK, spiedes izturība >300kPa) 20-160 mm / Slope-forming layer XPS (e.g. FINNFOAM F-300, λ=0.033W/mK, compressive strength >300kPa) 20-160 mm | D69: m2 | E69: 44
A70: =A69+1 -> 38 | C70: Jumta siltumizolācijas plāksne (piemēram, PAROC ROB 80, λ=0,038 W/mK) 20 mm / Roof thermal insulation board (e.g. PAROC ROB 80, λ=0.038 W/mK) 20 mm | D70: m2 | E70: 44
B72: P-1-8.2 | C72: Monolīta DZ/B pārsegums virs ārtelpas 300 mm / Monolithic RC slab floor above outdoor space 300 mm | D72: m² | E72: 39
A73: =A70+1 -> 39 | C73: Slīpumu veidojošs slānis XPS (piem. FINNFOAM F-300,λ=0,033W/mK, spiedes izturība >300kPa) 20-160 mm / Slope-forming layer XPS (e.g. FINNFOAM F-300, λ=0.033W/mK, compressive strength >300kPa) 20-160 mm | D73: m2 | E73: 39
A74: =A73+1 -> 40 | C74: Jumta siltumizolācijas plāksne (piemēram, PAROC ROB 80, λ=0,038 W/mK) 20 mm / Roof thermal insulation board (e.g. PAROC ROB 80, λ=0.038 W/mK) 20 mm | D74: m2 | E74: 39
B76: P-1-8.3 | C76: Monolīta DZ/B pārsegums virs ārtelpas 300 mm / Monolithic RC slab floor above outdoor space 300 mm | D76: m² | E76: 11
A77: =A74+1 -> 41 | C77: Slīpumu veidojošs slānis XPS (piem. FINNFOAM F-300,λ=0,033W/mK, spiedes izturība >300kPa) 20-160 mm / Slope-forming layer XPS (e.g. FINNFOAM F-300, λ=0.033W/mK, compressive strength >300kPa) 20-160 mm | D77: m2 | E77: 11
A78: =A77+1 -> 42 | C78: Jumta siltumizolācijas plāksne (piemēram, PAROC ROB 80, λ=0,038 W/mK) 20 mm / Roof thermal insulation board (e.g. PAROC ROB 80, λ=0.038 W/mK) 20 mm | D78: m2 | E78: 11
B80: P-2-7.1 | C80: Monolīta DZ/B pagrabstāva pārsegums 350mm, apstādījumi / RC slab basement floor 350mm, greenery | D80: m² | E80: 55.51
A81: =A78+1 -> 43 | C81: Tvaika izolācija Multiplex Super AL – SD 1500 / Vapour insulation Multiplex Super AL – SD 1500 - mm | D81: m2 | E81: 55.51
A82: =A81+1 -> 44 | C82: Slīpumu veidojošs slānis XPS (piem. FINNFOAM F-300,λ=0,033W/mK, spiedes izturība >300kPa) 20-100 mm / Slope-forming layer XPS (e.g. FINNFOAM F-300, λ=0.033W/mK, compressive strength >300kPa) 20-100 mm | D82: m2 | E82: 55.51
A83: =A82+1 -> 45 | C83: XPS siltumizolācija (piem. FINNFOAM F-300, λ=0,033W/mK, spiedes izturība >300kPa) 200 mm / XPS thermal insulation (e.g. FINNFOAM F-300, λ=0.033W/mK, compressive strength >300kPa) 200 mm | D83: m2 | E83: 55.51
B85: P-2-7.2 | C85: Monolīta DZ/B pagrabstāva pārsegums 350mm, apstādījumi / RC slab basement floor 350mm, greenery | D85: m² | E85: 59.95
A86: =A83+1 -> 46 | C86: Tvaika izolācija Multiplex Super AL – SD 1500 / Vapour insulation Multiplex Super AL – SD 1500 - mm | D86: m2 | E86: 59.95
A87: =A86+1 -> 47 | C87: Slīpumu veidojošs slānis XPS (piem. FINNFOAM F-300,λ=0,033W/mK, spiedes izturība >300kPa) 20-100 mm / Slope-forming layer XPS (e.g. FINNFOAM F-300, λ=0.033W/mK, compressive strength >300kPa) 20-100 mm | D87: m2 | E87: 59.95
A88: =A87+1 -> 48 | C88: XPS siltumizolācija (piem. FINNFOAM F-300, λ=0,033W/mK, spiedes izturība >300kPa) 200 mm / XPS thermal insulation (e.g. FINNFOAM F-300, λ=0.033W/mK, compressive strength >300kPa) 200 mm | D88: m2 | E88: 59.95
B90: P-6-1 | C90: DZ/B dobpaneļu pārsegums 220mm jumta segums / RC hollow core slab floor 220mm, roof | D90: m² | E90: 1164
B91: P-6-1* | C91: DZ/B dobpaneļu pārsegums 220mm jumta segums virs lifta šahtas / RC hollow core slab floor 220mm, roof over the elevator shaft | D91: m² | E91: 24
A92: =A88+1 -> 49 | C92: Tvaika izolācija uz izlīdzinātas virsmas (piemēram, WITEK AL-S, SD>1500mm) / Vapour insulation on a leveled surface (e.g. WITEK AL-S, SD>1500mm) | D92: m2 | E92: 1188
A93: =A92+1 -> 50 | C93: Slīpumu veidojošs slānis (piem. Thermowhite WD100R) 20-160 mm / Slope-forming layer (e.g. Thermowhite WD100R) 20-160 mm | D93: m2 | E93: 1188
A94: =A93+1 -> 51 | C94: Siltumizolācija piemēram, PAROC ROS 60, λ=0,036 W/mK) 2x150 mm / Thermal insulation (e.g. PAROC ROS 60, λ=0.036 W/mK) 2x150 m | D94: m2 | E94: 1188
A95: =A94+1 -> 52 | C95: Jumta siltumizolācijas plāksne (piemēram, PAROC ROB 80, λ=0,038 W/mK) 20 mm / Roof thermal insulation board (e.g. PAROC ROB 80, λ=0.038 W/mK) 20 mm | D95: m2 | E95: 1188
A96: =A95+1 -> 53 | C96: Elektrību vadošs apakšklājs (piem. CONTROLIT PK) / Electrically conductive underlay (e.g. CONTROLIT PK) | D96: m2 | E96: 1188
A97: =A96+1 -> 54 | C97: Jumta ruļļveida vai membrānas seguma materiāls (piem. WOLFIN TECTOFIN SK) / Roof roll or membrane covering material (e.g. WOLFIN TECTOFIN SK) | D97: m2 | E97: 1188
B99: P-6-2 | C99: DZ/B dobpaneļu starpstāvu pārsegums 320mm, terase / RC hollow core slab floor 320mm, roof terrace | D99: m² | E99: 403
B100: P-6-2* | C100: DZ/B dobpaneļu starpstāvu pārsegums 320mm, terase jumta izbūvēm / RC hollow core slab floor 320mm, terrace for roof dormers | D100: m² | E100: 33
A101: =A97+1 -> 55 | C101: Tvaika izolācija uz izlīdzinātas virsmas (piemēram, WITEK AL-S, SD>1500mm) / Vapour insulation on a leveled surface (e.g. WITEK AL-S, SD>1500mm) | D101: m2 | E101: 436
A102: =A101+1 -> 56 | C102: Slīpumu veidojoša siltumizolācija (piemēram, KINGSPAN THERMA TT46, λ=0,022 W/mK) 160-240 mm / Slope-forming thermal insulation (e.g. KINGSPAN THERMA TT46, λ=0.022 W/mK) 160-240 m | D102: m2 | E102: 436
A103: =A102+1 -> 57 | C103: Jumta siltumizolācijas plāksne (piemēram, PAROC ROB 80, λ=0,038 W/mK) 20 mm / Roof thermal insulation board (e.g. PAROC ROB 80, λ=0.038 W/mK) 20 mm | D103: m2 | E103: 436
A104: =A103+1 -> 58 | C104: Elektrību vadošs apakšklājs (piem. CONTROLIT PK) / Electrically conductive underlay (e.g. CONTROLIT PK) | D104: m2 | E104: 436
A105: =A104+1 -> 59 | C105: Jumta ruļļveida vai membrānas seguma materiāls (piem. WOLFIN TECTOFIN SK) / Roof roll or membrane covering material (e.g. WOLFIN TECTOFIN SK) | D105: m2 | E105: 436
A106: =A105+1 -> 60 | C106: Terases laipu balsti / distanceri (piem. ZinCo Elefeet) 70-150 mm/ Terrace footing supports / spacers (e.g. ZinCo Elefeet) 70-150 mm | D106: m2 | E106: 436
A107: =A106+1 -> 61 | B107: F-07 | C107: Terases segums (pēc IN projekta) 30 mm Terases flīzes, Neslīdošas R10, Atlas Concorde Clay matte sensitech/ Terrace cover (according to IN project) 30 mm Terrace tile, non-slip R10, Atlas Concorde matte sensitech | D107: m2 | E107: 436
B109: P-7-1 | C109: Tērauda karkass, sendvičpaneļi un skārda apšuvums / Steel frame, sandwich panels and metal cladding | D109: m² | E109: 263
A110: 61.1 | C110: Ģipškartons (blīvums ≥1000 kg/m³), 2 kārtās 25 mm / Gypsumboard (density ≥1000 kg/m³), 2 layers 25 mm | D110: m2 | E110: 263
A111: 61.2 | C111: Metāla karkass ar skaņas izolāciju (≥25 kg/m³) 50 mm / Metal construction with insulation (≥25 kg/m³) 50 mm | D111: m2 | E111: 263
A112: 61.3 | C112: Tvaika izolācijas plēve (piem. Isover Vario Xtra, sd=0.3m) / Vapour barrier film (e.g. Isover Vario Xtra, sd=0.3m) | D112: m2 | E112: 263
A113: 61.4 | C113: Tērauda konstrukcija (skatīt BK daļā) / siltumizolācijā (piem. PAROC Ultra, λ=0,035 W/mK), ugunsreakcijas klase ne zemāk kā A2-s1, d0 200 mm / Steel structure (according to BK project) / thermal insulation e.g. PAROC Ultra, λ=0.035 W/mK), fire reaction class not lower than A2-s1, d0 200 mm | D113: m2 | E113: 263
A114: 61.5 | C114: Profilēts, ar minerālvati pildīts sienu sendvičpanelis piem. Ruukki SPA E), ugunsreakcijas klase ≥ A2-s1, d0 200mm / Mineral wool-filled sandwich panel (e.g. Ruukki SPA E), fire reaction class ≥ A2-s1, d0 200mm | D114: m2 | E114: 263
A115: 61.6 | C115: Koka latojums, apstrādāts ar antipirēnu, B-s1, d0 50mm / Wooden slats, treated with flame retardant, B-s1, d0 50mm | D115: m2 | E115: 263
A116: 61.7 | C116: Retināts dēļu klājs, apstrādāts ar antipirēnu, B-s1, d0 20mm / Board deck, treated with flame retardant, B-s1, d0 20mm | D116: m2 | E116: 263
A117: 61.8 | C117: Skārda jumta segums (toni skatīt krāsu pasē) / Metal cladding (color tone in color passport) | D117: m2 | E117: 263
B119: P-7-2 | C119: Koka karkass un skārda apšuvums / Wood frame and metal cladding | D119: m² | E119: 84
A120: 61.9 | C120: Ģipškartons (blīvums ≥1000 kg/m³), 2 kārtās 25 mm / Gypsumboard (density ≥1000 kg/m³), 2 layers 25 mm | D120: m2 | E120: 84
A121: 61.10 | C121: Metāla karkass ar skaņas izolāciju (≥25 kg/m³) 50 mm / Metal construction with insulation (≥25 kg/m³) 50 mm | D121: m2 | E121: 84
...

Sheet 1-8F
F1: Lokālā tāme Nr./Local estimate No | G1: 1-8
F2: Fasādes konstrukcijas un apdare / Facade finishing
A4: =KS!C4 -> Būves nosaukums/Building: Daudzīvokļu ēka / Residental building C2-10
A5: =KS!C5 -> Objekta nosaukums/Object: Dzīvojamās ēkas C2-10 jaunbūve/ Residential building C2-10
A6: =KS!C6 -> Objekta adrese/Object adress: Andrejostas iela 35, Rīga, LV-1045 | M6: Tāmes izmaksas | P6: euro
P8: Tāme sastādīta/Date _____. gada ____. ____________
F10: Vienības izmaksas/Unit rate | N10: Kopā uz visu apjomu/Total amount
A11: N.p.k./No | B11: Kods*/Code | C11: Būvdarbu nosaukums/Description of the construction work | D11: Mērvienība/ Unit | E11: Daudzums/ Quantity | F11: laika norma (c/h)/time rate (w/h) | G11: darba samaksas likme* (euro/h)/labour wage rate (euro/h)* | H11: darba alga/ salary | I11: būvizstrādājumi/ materials | J11: mehānismi/ mechanisms | K11: kopā/ total | L11: darbietilpība (c/h)/labor (w/h) | M11: darba alga/ salary | N11: būvizstrādājumi/ materials | O11: mehānismi/ mechanisms | P11: summa/ Total
A12: 1 | B12: 2 | C12: 3 | D12: 4 | E12: 5 | F12: =E12+1 -> 6 | G12: =F12+1 -> 7 | H12: =G12+1 -> 8 | I12: =H12+1 -> 9 | J12: =I12+1 -> 10 | K12: =J12+1 -> 11 | L12: =K12+1 -> 12 | M12: =L12+1 -> 13 | ... P12: =O12+1 -> 16
C14: Sastatnes/Scaffolding
A15: 1 | C15: Sastatņu montāža/noma/demontāža/Scaffolding assembly / rental / dismantling | D15: kpl | E15: 1
C17: Fasādes/Facade
A18: =A15+1 -> 2 | C18: Fasādes paraugu sagatavošana, saskaņošana/Facade sample preparation, coordination | D18: kpl | E18: 1
B20: AS-1-1 | C20: Saliekamais trīsslāņu DZ/B panelis (fasādes sijas un pilastri) / Precast RC sandwich panel (facade beams and pilasters) | D20: m² | E20: 483.09
A21: skat. BK daļā, T1-3S, see BK part T1-3S | B21: FK | C21: FK - Vertikālais betona panelis, skatīt ĀS-1-1 sienu sastāvu, toni skatīt krāsu pasē. / FK - Vertical concrete panel, see ĀS-1-1 wall construction, color tone in color passport | D21: m2 | E21: 478.8
A22: skat. BK daļā, T1-3S, see BK part T1-3S | B22: FS | C22: FS - Horizontālais betona panelis ar dzegu, skatīt ĀS-1-1 sienu sastāvu, toni skatīt krāsu pasē. / FS - Horizontal concrete panel with cornice, see ĀS-1-1 wall construction, color tone in color passport | D22: m2 | E22: 124.8
B24: AS-1-2.1 | C24: Monolīta DZ/B siena 200mm ar ventilējamo fasādi / Monolithic RC wall 200mm with ventilated facade | D24: m² | E24: 81.41
B25: AS-1-2.2 | C25: Monolīta DZ/B siena 250mm ar ventilējamo fasādi / Monolithic RC wall 250mm with ventilated facade | D25: m² | E25: 221.26
A26: =A18+1 -> 3 | C26: Siltumizolācijā (piem. PAROC Ultra, λ=0,035 W/mK), ugunsreakcijas klase ne zemāk kā A2-s1, d0 150mm / Thermal insulation (e.g. PAROC Ultra, λ=0.035 W/mK), fire reaction class not lower than A2-s1, d0 150mm | D26: m2 | E26: 302.67
A27: =A26+1 -> 4 | C27: Akmensvates pretvēja izolācija ar melnu stiklašķiedras audumu (piem. PAROC WAS 50tb, λ=0,034 W/mK) 30 mm / Stone wool wind insulation board with black glass fibre abric (e.g. PAROC WAS 50tb, λ=0,034 W/mK) 30 mm | D27: m2 | E27: 302.67
A28: =A27+1 -> 5 | C28: Alumīnija apakškonstrukcija (stiprināt caur izolējošo starpliku) 75-175 mm / Aluminum substructure (fasten through insulating spacer) 75-175 mm | D28: m2 | E28: 442.7
A29: =A28+1 -> 6 | B29: FC1 | C29: Šķiedrcementa plāksnes, 1. stāva iebrauktuvē, 10mm (piem. Equitone, Eternit- natura. Stiprinājums uz BOSTIK vai SIKA slēptas līmēšanas sistēmas). Toni skatīt krāsu pasē. Alumīnija profilu šuvju vietās nosegt ar melnu EPDM lenti (platums 60mm) / Fiber cement boards, 1st floor entrance, 10mm (e.g. Equitone, Eternit-natura. Fastening on BOSTIK or SIKA hidden adhesive system). Color tone see in color passport. Cover the aluminum profile joints with black EPDM tape (width 60mm) | D29: m2 | E29: 295.8
A30: =A29+1 -> 7 | B30: FC1* | C30: Šķiedrcementa plāksnes, 1. stāva iebrauktuvē (cokola līmenī), 10mm (piem. Equitone, Eternit- natura. Stiprinājums uz BOSTIK vai SIKA slēptas līmēšanas sistēmas). Toni skatīt krāsu pasē. Alumīnija profilu šuvju vietās nosegt ar melnu EPDM lenti (platums 60mm) / Fiber cement boards, 1st floor entrance (at plinth level), 10mm (e.g. Equitone, Eternit-natura. Fastening on BOSTIK or SIKA hidden adhesive system). Color tone see in color passport. Cover the aluminum profile joints with black EPDM tape (width 60mm) | D30: m2 | E30: 133.6
A31: =A30+1 -> 8 | B31: FC2 | C31: Šķiedrcementa plāksnes, 1. stāva ielas fasādei, 10mm (piem. Equitone, Eternit- natura. Stiprinājums uz BOSTIK vai SIKA slēptas līmēšanas sistēmas). Toni skatīt krāsu pasē. Alumīnija profilu šuvju vietās nosegt ar melnu EPDM lenti (platums 60mm) / Fiber cement boards, 1st floor street facade, 10mm (e.g. Equitone, Eternit-natura. Fastening on BOSTIK or SIKA hidden adhesive system). Color tone see in color passport. Cover the aluminum profile joints with black EPDM tape (width 60mm) | D31: m2 | E31: 13.3
B33: AS-1-3 | C33: Saliekamais trīsslāņu DZ/B panelis / Precast RC sandwich panel | D33: m² | E33: 156.83
A34: skat. BK daļā, T1-3S, see BK part T1-3S | B34: FP1 | C34: FP1 - Panelis ar eksponēta betona apdari, skatīt ĀS-1-3 sienu sastāvu, toni skatīt krāsu pasē. /FP1 - Panel with exposed concrete finish, see ĀS-1-3 wall construction, color tone in color passport | D34: m2 | E34: 146.2
A35: skat. BK daļā, T1-3S, see BK part T1-3S | B35: AS-1-4.1 | C35: Saliekamais trīsslāņu DZ/B panelis, 200mm / Precast RC sandwich panel, 200mm | D35: m² | E35: 1394.18
A36: skat. BK daļā, T1-3S, see BK part T1-3S | B36: AS-1-4.1P | C36: Saliekamais trīsslāņu DZ/B panelis (parapeta fragments ar papildus siltumizolāciju un jumta apdari, skatīt mezglus M-69), 200mm / Precast RC sandwich panel (parapet fragment with additional thermal insulation and roof finish, see detail M-69), 200mm | D36: m² | E36: 110.4
A37: skat. BK daļā, T1-3S, see BK part T1-3S | B37: AS-1-4.2 | C37: Saliekamais trīsslāņu DZ/B panelis, 220mm / Precast RC sandwich panel, 220mm | D37: m² | E37: 636.44
A38: skat. BK daļā, T1-3S, see BK part T1-3S | B38: AS-1-4.2P | C38: Saliekamais trīsslāņu DZ/B panelis (parapeta fragments ar papildus siltumizolāciju un jumta apdari, skatīt mezglus M-69), 220mm / Precast RC sandwich panel (parapet fragment with additional thermal insulation and roof finish, see detail M-69), 220mm | D38: m² | E38: 49.05
A39: skat. BK daļā, T1-3S, see BK part T1-3S | B39: FP2 | C39: FP2 – Panelis ar ķieģeļflīžu apdari, skatīt ĀS-1-4 sienu sastāvus, toni skatīt krāsu pasē. / FP2 - Panel with brick tile finish, see ĀS-1-4 wall construction, color tone in color passport | D39: m2 | E39: 674.6
A40: skat. BK daļā, T1-3S, see BK part T1-3S | B40: FP3 | C40: FP3 – Panelis ar ķieģeļflīžu apdari, skatīt ĀS-1-4 sienu sastāvus, toni skatīt krāsu pasē. / FP3 - Panel with brick tile finish, see ĀS-1-4 wall construction, color tone in color passport | D40: m2 | E40: 758.8
A41: skat. BK daļā, T1-3S, see BK part T1-3S | B41: FP4 | C41: FP4 – Panelis ar ķieģeļflīžu apdari, skatīt ĀS-1-4 sienu sastāvus, toni skatīt krāsu pasē. / FP4 - Panel with brick tile finish, see ĀS-1-4 wall construction, color tone in color passport | D41: m2 | E41: 922.7
B43: AS-1-5 | C43: Saliekamais DZ/B panelis ar ventilējamo fasādi / Precast RC panel with ventilated facade | D43: m² | E43: 157.69
A44: =A31+1 -> 9 | C44: Siltumizolācijā (piem. PAROC Ultra, λ=0,035 W/mK), ugunsreakcijas klase ne zemāk kā A2-s1, d0 200mm / Thermal insulation (e.g. PAROC Ultra, λ=0.035 W/mK), fire reaction class not lower than A2-s1, d0 200mm | D44: m2 | E44: 157.69
A45: =A44+1 -> 10 | C45: Pretvēja plēve, tonis melns / Windproof film, color tone - black | D45: m2 | E45: 157.69
A46: =A45+1 -> 11 | C46: Alumīnija apakškonstrukcija (stiprināt caur izolējošo starpliku) 275 mm / Aluminum substructure (fasten through insulating spacer) 275 mm | D46: m2 | E46: 157.69
A47: =A46+1 -> 12 | B47: FC3 | C47: Šķiedrcementa plāksnes, 6. stāva fasādei, 10mm (piem. Equitone, Eternit- natura. Stiprinājums uz BOSTIK vai SIKA slēptas līmēšanas sistēmas). Toni skatīt krāsu pasē. Alumīnija profilu šuvju vietās nosegt ar melnu EPDM lenti (platums 60mm) / Fiber cement boards, for the 6th floor facade, 10mm (e.g. Equitone, Eternit-natura. Fastening on BOSTIK or SIKA hidden adhesive system). Color tone see in color passport. Cover the aluminum profile joints with black EPDM tape (width 60mm) | D47: m2 | E47: 162
B49: AS-1-5P | C49: Saliekamais DZ/B panelis ar ventilējamo fasādi (parapeta fragments ar papildus siltumizolāciju un jumta apdari, skatīt mezglus M-78) / Precast RC panel with ventilated facade (parapet fragment with additional thermal insulation and roof finish, see detail M-78) | D49: m² | E49: 62.8
A50: =A47+1 -> 13 | C50: Jumta siltumizolācijas plāksne (piem. PAROC ROB 80, λ=0,038 W/mK) 20 mm/ Roof thermal insulation board (e.g. PAROC ROB 80, λ=0.038 W/mK) 20 mm | D50: m2 | E50: 62.8
A51: =A50+1 -> 14 | C51: Siltumizolācija (piem. PAROC ROS 60, λ=0,036 W/mK) 80 mm / Thermal insulation (e.g. PAROC ROS 60, λ=0.036 W/mK) 80 mm | D51: m2 | E51: 62.8
A52: =A51+1 -> 15 | C52: Siltumizolācijā (piem. PAROC Ultra, λ=0,035 W/mK), ugunsreakcijas klase ne zemāk kā A2-s1, d0 150mm / Thermal insulation (e.g. PAROC Ultra, λ=0.035 W/mK), fire reaction class not lower than A2-s1, d0 150mm | D52: m2 | E52: 62.8
A53: =A52+1 -> 16 | C53: Akmensvates pretvēja izolācija ar melnu stiklašķiedras audumu (piem. PAROC WAS 50tb, λ=0,034 W/mK) 50 mm / Stone wool wind insulation board with black glass fibre fabric (e.g. PAROC WAS 50tb, λ=0,034 W/mK) 50 mm | D53: m2 | E53: 62.8
A54: =A53+1 -> 17 | C54: Alumīnija apakškonstrukcija (stiprināt caur izolējošo starpliku) 275 mm / Aluminum substructure (fasten through insulating spacer) 275 mm | D54: m2 | E54: 62.8
A55: =A54+1 -> 18 | B55: FC3 | C55: Šķiedrcementa plāksnes, 6. stāva fasādei, 10mm (piem. Equitone, Eternit- natura. Stiprinājums uz BOSTIK vai SIKA slēptas līmēšanas sistēmas). Toni skatīt krāsu pasē. Alumīnija profilu šuvju vietās nosegt ar melnu EPDM lenti (platums 60mm) / Fiber cement boards, for the 6th floor facade, 10mm (e.g. Equitone, Eternit-natura. Fastening on BOSTIK or SIKA hidden adhesive system). Color tone see in color passport. Cover the aluminum profile joints with black EPDM tape (width 60mm) | D55: m2 | E55: 62.8
B57: AS-1-6P | C57: Parapeta fragments no fasādes sistēmas un tērauda konstrukcijas, skatīt mezglus M-74 / Parapet fragment from the facade system and steel structure, see detail M-74 | D57: m² | E57: 54.08
A58: =A55+1 -> 19 | C58: Jumta siltumizolācijas plāksne (piem. PAROC ROB 80, λ=0,038 W/mK) 20 mm/ Roof thermal insulation board (e.g. PAROC ROB 80, λ=0.038 W/mK) 20 mm | D58: m2 | E58: 54.08
A59: =A58+1 -> 20 | C59: Siltumizolācija (piem. PAROC ROS 60, λ=0,036 W/mK) 160 mm / Thermal insulation (e.g. PAROC ROS 60, λ=0.036 W/mK) 160 mm | D59: m2 | E59: 54.08
A60: =A59+1 -> 21 | C60: Siltumizolācijas plāksnes (piem. Kooltherm) λ=0.021 W/mK, Spiedes stiprība ≥ 100 kPa / Thermal insulation boards (e.g. Kooltherm) λ=0.021 W/mK, Compressive strength ≥ 100 kPa | D60: m2 | E60: 54.08
A61: =A60+1 -> 22 | C61: Siltumizolācijā (piem. PAROC Ultra, λ=0,035 W/mK) / Thermal insulation (e.g. PAROC Ultra, λ=0.035 W/mK) | D61: m2 | E61: 54.08
A62: =A61+1 -> 23 | C62: Mitrumizturīgs saplāksnis 21mm / Moistureresistant plywood 21mm | D62: m2 | E62: 54.08
B64: AS-1-7 | C64: Metāla karkass, CLT paneļi un skārda apšuvums / Metal frame, CLT panels and metal cladding | D64: m² | E64: 87.16
A65: 23.1 | C65: Ģipškartons (blīvums ≥1000 kg/m³), 2 kārtās 25 mm / Gypsumboard (density ≥1000 kg/m³), 2 layers 25 mm | D65: m2 | E65: 87.16
A66: 23.2 | C66: Metāla karkass ar skaņas izolāciju (≥25 kg/m³) 50 mm / Metal construction with insulation (≥25 kg/m³) 50 mm | D66: m2 | E66: 87.16
A67: 23.3 | C67: Šuves un stiprinājuma vietās paredzēt tvaika izolējošas lentes, SD vērtībā atbilstoši LBN / Provide vapor barrier tapes at joints and fastening points, with SD value according to LBN | D67: m2 | E67: 87.16
A68: 23.4 | C68: Siltumizolācijā (piem. PAROC Ultra, λ=0,035 W/mK), ugunsreakcijas klase ne zemāk kā A2-s1, d0 80mm / Thermal insulation (e.g. PAROC Ultra, λ=0.035 W/mK), fire reaction class not lower than A2-s1, d0 80mm | D68: m2 | E68: 87.16
A69: 23.5 | C69: Akmensvates pretvēja izolācija (piem. PAROC WAS 50tb, λ=0,034 W/mK), 30 mm / stone wool wind insulation board (e.g. PAROC WAS 50tb, λ=0,034 W/mK), 30mm | D69: m2 | E69: 87.16
A70: 23.6 | C70: Tērauda / Koka latojums, ugunsreakcija ≥ B-s1, d0 50mm / Steel / Wooden slats, fire reaction ≥ B-s1, d0 50mm | D70: m2 | E70: 87.16
A71: 23.7 | C71: Retināts dēļu klājs, apstrādāts ar antipirēnu, B-s1, d0 20mm / Board deck, treated with flame retardant, B-s1, d0 20mm | D71: m2 | E71: 87.16
A72: 23.8 | C72: Skārda jumta segums (toni skatīt krāsu pasē) / Metal cladding (color tone in color passport) | D72: m2 | E72: 87.16
B74: AS-1-7* | C74: Metāla karkass un skārda apšuvums (skatīt mezglus M-76) / Metal frame and metal cladding (see detail M-76) | D74: m² | E74: 131.63
A75: =A62+1 -> 24 | C75: Ģipškartons (blīvums ≥1000 kg/m³), 2 kārtās 25 mm / Gypsumboard (density ≥1000 kg/m³), 2 layers 25 mm | D75: m2 | E75: 131.63
A76: =A75+1 -> 25 | C76: Metāla karkass ar skaņas izolāciju (≥25 kg/m³) 50 mm / Metal construction with insulation (≥25 kg/m³) 50 mm | D76: m2 | E76: 131.63
A77: =A76+1 -> 26 | C77: Šuves un stiprinājuma vietās paredzēt tvaika izolējošas lentes, SD vērtībā atbilstoši LBN / Provide vapor barrier tapes at joints and fastening points, with SD value according to LBN | D77: m2 | E77: 131.63
A78: =A77+1 -> 27 | C78: Siltumizolācijā (piem. PAROC Ultra, λ=0,035 W/mK), ugunsreakcijas klase ne zemāk kā A2-s1, d0 80mm / Thermal insulation (e.g. PAROC Ultra, λ=0.035 W/mK), fire reaction class not lower than A2-s1, d0 80mm | D78: m2 | E78: 131.63
A79: 27.1 | C79: Akmensvates pretvēja izolācija (piem. PAROC WAS 50tb, λ=0,034 W/mK), 30 mm / stone wool wind insulation board (e.g. PAROC WAS 50tb, λ=0,034 W/mK), 30mm | D79: m2 | E79: 131.63
A80: =A78+1 -> 28 | C80: Tērauda / Koka latojums, ugunsreakcija ≥ B-s1, d0 50mm / Steel / Wooden slats, fire reaction ≥ B-s1, d0 50mm | D80: m2 | E80: 131.63
A81: =A80+1 -> 29 | C81: Retināts dēļu klājs, apstrādāts ar antipirēnu, B-s1, d0 20mm / Board deck, treated with flame retardant, B-s1, d0 20mm | D81: m2 | E81: 131.63
A82: =A81+1 -> 30 | C82: Skārda jumta segums (toni skatīt krāsu pasē) / Metal cladding (color tone in color passport) | D82: m2 | E82: 131.63
B84: AS-1-8 | C84: Metāla karkass, sendvičpaneļi un skārda apšuvums / Metal frame, sandwich panels and metal cladding | D84: m² | E84: 6.98
A85: 30.1 | C85: Ģipškartons (blīvums ≥1000 kg/m³), 2 kārtās 25 mm / Gypsumboard (density ≥1000 kg/m³), 2 layers 25 mm | D85: m2 | E85: 6.98
A86: 30.2 | C86: Tērauda konstrukcijas (skatīt BK) karkass ar skaņas izolāciju (≥25 kg/m³) 50 mm / Steel structure (according to BK project) with insulation (≥25 kg/m³) 50 mm | D86: m2 | E86: 6.98
A87: 30.3 | C87: Šuves un stiprinājuma vietās paredzēt tvaika izolējošas lentes, SD vērtībā atbilstoši LBN / Provide vapor barrier tapes at joints and fastening points, with SD value according to LBN | D87: m2 | E87: 6.98
A88: 30.4 | C88: Profilēts, ar minerālvati pildīts sienu sendvičpanelis piem. Ruukki SPA E), ugunsreakcijas klase ≥ A2-s1, d0 200mm / Mineral wool-filled sandwich panel (e.g. Ruukki SPA E), fire reaction class ≥ A2-s1, d0 200mm | D88: m2 | E88: 6.98
A89: 30.5 | C89: Tērauda / Koka latojums, ugunsreakcija ≥ B-s1, d0 50mm / Steel / Wooden slats, fire reaction ≥ B-s1, d0 50mm | D89: m2 | E89: 6.98
A90: 30.6 | C90: Retināts dēļu klājs, apstrādāts ar antipirēnu, B-s1, d0 20mm / Board deck, treated with flame retardant, B-s1, d0 20mm | D90: m2 | E90: 6.98
A91: 30.7 | C91: Skārda jumta segums (toni skatīt krāsu pasē) / Metal cladding (color tone in color passport) | D91: m2 | E91: 6.98
B93: AS-2-1 | C93: Pagrabstāva ārsiena / Basement exterior wall | D93: m² | E93: 412.66
A94: =A82+1 -> 31 | C94: Hidroizolācija / Waterproofing | D94: m2 | E94: 412.66
A95: =A94+1 -> 32 | C95: XPS siltumizolācija (spiedes stiprība ≥40 kPa, piem. TENAPORS EXTRA) 150 mm/ XPS insulation (compressive strength ≥40 kPa, e.g., TENAPORS EXTRA) 150 mm | D95: m2 | E95: 412.66
B97: AS-2-2 | C97: Pagrabstāva siena pret C2-9 / Basement wall towards C2-9 | D97: m² | E97: 137.86
A98: =A95+1 -> 33 | C98: Hidroizolācija / Waterproofing | D98: m2 | E98: 137.86
A99: =A98+1 -> 34 | C99: XPS siltumizolācija (spiedes stiprība ≥40 kPa, piem. TENAPORS EXTRA) 100 mm / XPS insulation (compressive strength ≥40 kPa, e.g., TENAPORS EXTRA) 100 mm | D99: m2 | E99: 137.86
B101: AS-2-3 | C101: Pagrabstāva ārsiena bez siltumizolācijas / Basement exterior wall without thermal insulation | D101: m² | E101: 170.2
A102: =A99+1 -> 35 | C102: Hidroizolācija / Waterproofing | D102: m2 | E102: 170.2
C104: FASĀDES SKĀRDA ELEMENTI / FACADE TIN ELEMENTS
A105: =A102+1 -> 36 | B105: SK-17 | C105: Krāsota loga palodzes skārda (Toni skatīt krāsu pasē) montāža, t.sk. stiprinājumi, izolācija, palīgmateriāli / Painted window sill sheet metal (See color passport for shades)assembly, incl. fasteners, insulation, auxiliary materials 30+125+ mm | D105: m | E105: 12
A106: =A105+1 -> 37 | B106: SK-18 | C106: Krāsota loga palodzes skārda (Toni skatīt krāsu pasē) montāža, t.sk. stiprinājumi, izolācija, palīgmateriāli / Painted window sill sheet metal (See color passport for shades)assembly, incl. fasteners, insulation, auxiliary materials 45+285+ mm | D106: m | E106: 12.8
A107: =A106+1 -> 38 | B107: SK-19 | C107: Krāsota loga palodzes skārda (Toni skatīt krāsu pasē) montāža, t.sk. stiprinājumi, izolācija, palīgmateriāli / Painted window sill sheet metal (See color passport for shades)assembly, incl. fasteners, insulation, auxiliary materials 45+355+ mm | D107: m | E107: 14.5
A108: =A107+1 -> 39 | B108: SK-20 | C108: Krāsota loga palodzes skārda (Toni skatīt krāsu pasē) montāža, t.sk. stiprinājumi, izolācija, palīgmateriāli / Painted window sill sheet metal (See color passport for shades)assembly, incl. fasteners, insulation, auxiliary materials 30+295+ mm | D108: m | E108: 20.1
A109: =A108+1 -> 40 | B109: SK-21 | C109: Krāsota loga palodzes skārda (Toni skatīt krāsu pasē) montāža, t.sk. stiprinājumi, izolācija, palīgmateriāli / Painted window sill sheet metal (See color passport for shades)assembly, incl. fasteners, insulation, auxiliary materials 30+365+ mm | D109: m | E109: 94.8
A110: =A109+1 -> 41 | B110: LN-1 | C110: Iebūvējamas taisnstūra lietus ūdens notekas. Iebūvēs dziļums ~260mm. Notekas stiprinājumu un izvietojumu attiecībā pret paneļu dekora izvietojumu precizēt ar paneļu ražotājiem un saskaņot ar arhitektu. 28 gb montāža, t.sk. stiprinājumi, izolācija, palīgmateriāli / Built-in rectangular rainwater gutters. Built-in depth ~260mm. The gutter fastening and placement in relation to the panel decor placement should be specified with the panel manufacturers and coordinated with the architect. 28 pcs assembly, incl. fasteners, insulation, auxiliary materials | D110: m | E110: 367.86
C112: MARKĪZES / AWNINGS
A113: =A110+1 -> 42 | B113: MK-1 | C113: Markīzes – nojumes no metāla konstrukcijas (materiāls un izklājumi tiks precizēti kopā ar 1. stāva fasādes sistēmu detalizāciju). Stiprināmas pie vertikāla stiklojuma profila ar tam paredzētu kronšteinu ( piem. SCHUCO Schwertanbinder) montāža, t.sk. stiprinājumi, izolācija, palīgmateriāli / Awnings made of metal construction (material and layouts will be specified together with the detailing of the 1ST floor facade systems). Attached to a vertical glazing profile with a dedicated bracket (e.g. SCHUCO Schwertanbinder) assembly, incl. fasteners, insulation, auxiliary materials | D113: kpl | E113: 6
A114: =A113+1 -> 43 | B114: MK-2 | C114: Markīzes – nojumes no metāla konstrukcijas (materiāls un izklājumi tiks precizēti kopā ar 1. stāva fasādes sistēmu detalizāciju). Stiprināmas pie vertikāla stiklojuma profila ar tam paredzētu kronšteinu ( piem. SCHUCO Schwertanbinder) montāža, t.sk. stiprinājumi, izolācija, palīgmateriāli / Awnings made of metal construction (material and layouts will be specified together with the detailing of the 1ST floor facade systems). Attached to a vertical glazing profile with a dedicated bracket (e.g. SCHUCO Schwertanbinder) assembly, incl. fasteners, insulation, auxiliary materials | D114: kpl | E114: 1
